{"textures":{"0":"modelengine:entity/viking_decor3","1":"modelengine:entity/viking_decor3_variation1","2":"modelengine:entity/viking_axe","3":"modelengine:entity/viking_shield2"},"elements":[{"name":"cube","from":[2.6,10.014776,15.470001],"to":[3.7999997,17.214775,17.27],"rotation":{"angle":22.5,"axis":"z","origin":[2.7499998,14.064776,7.97]},"faces":{"down":{"uv":[6.875,4.75,7.125,4.375],"rotation":0,"texture":"#0","tintindex":0},"east":{"uv":[6.375,6.25,6.75,7.75],"rotation":0,"texture":"#0","tintindex":0},"north":{"uv":[1.25,6.5,1.5,8.0],"rotation":0,"texture":"#0","tintindex":0},"south":{"uv":[1.0,6.5,1.25,8.0],"rotation":0,"texture":"#0","tintindex":0},"up":{"uv":[6.875,4.0,7.125,4.375],"rotation":0,"texture":"#0","tintindex":0},"west":{"uv":[6.0,6.25,6.375,7.75],"rotation":0,"texture":"#0","tintindex":0}}},{"name":"cube","from":[1.9999998,9.414776,-1.3300004],"to":[15.2,10.614777,17.27],"rotation":{"angle":0.0,"axis":"x","origin":[8.0,4.0147758,8.27]},"faces":{"down":{"uv":[2.75,0.0,0.0,3.875],"rotation":0,"texture":"#0","tintindex":0},"east":{"uv":[6.0,5.5,9.875,5.75],"rotation":0,"texture":"#0","tintindex":0},"north":{"uv":[6.0,6.0,8.75,6.25],"rotation":0,"texture":"#0","tintindex":0},"south":{"uv":[0.75,6.25,3.5,6.5],"rotation":0,"texture":"#0","tintindex":0},"up":{"uv":[2.75,3.875,0.0,0.0],"rotation":0,"texture":"#0","tintindex":0},"west":{"uv":[6.0,5.75,9.875,6.0],"rotation":0,"texture":"#0","tintindex":0}}},{"name":"cube","from":[4.3999996,10.614777,1.0699997],"to":[12.8,14.214776,7.0699997],"rotation":{"angle":0.0,"axis":"x","origin":[7.4,4.0147758,7.0699997]},"faces":{"down":{"uv":[0.0,0.0,7.0,5.0],"rotation":0,"texture":"#1","tintindex":0},"east":{"uv":[7.0,6.0,12.0,9.0],"rotation":0,"texture":"#1","tintindex":0},"north":{"uv":[14.0,3.0,7.0,6.0],"rotation":0,"texture":"#1","tintindex":0},"south":{"uv":[7.0,3.0,14.0,6.0],"rotation":0,"texture":"#1","tintindex":0},"up":{"uv":[7.0,5.0,0.0,0.0],"rotation":0,"texture":"#1","tintindex":0},"west":{"uv":[7.0,6.0,12.0,9.0],"rotation":0,"texture":"#1","tintindex":0}}},{"name":"cube","from":[3.2454426,14.443831,1.0699997],"to":[4.4454427,14.443831,7.0699997],"rotation":{"angle":-22.5,"axis":"z","origin":[3.8454425,14.443831,4.0699997]},"faces":{"down":{"uv":[1.0,10.0,0.0,15.0],"rotation":0,"texture":"#1","tintindex":0},"east":{"uv":[0.0,0.0,5.0,0.0],"rotation":0,"texture":"#1","tintindex":0},"north":{"uv":[0.0,0.0,1.0,0.0],"rotation":0,"texture":"#1","tintindex":0},"south":{"uv":[0.0,0.0,1.0,0.0],"rotation":0,"texture":"#1","tintindex":0},"up":{"uv":[1.0,15.0,0.0,10.0],"rotation":0,"texture":"#1","tintindex":0},"west":{"uv":[0.0,0.0,5.0,0.0],"rotation":0,"texture":"#1","tintindex":0}}},{"name":"cube","from":[3.2454426,10.693832,1.0699997],"to":[4.4454427,10.693832,7.0699997],"rotation":{"angle":0.0,"axis":"x","origin":[3.8454425,14.443831,4.0699997]},"faces":{"down":{"uv":[1.0,10.0,0.0,15.0],"rotation":0,"texture":"#1","tintindex":0},"east":{"uv":[0.0,0.0,5.0,0.0],"rotation":0,"texture":"#1","tintindex":0},"north":{"uv":[0.0,0.0,1.0,0.0],"rotation":0,"texture":"#1","tintindex":0},"south":{"uv":[0.0,0.0,1.0,0.0],"rotation":0,"texture":"#1","tintindex":0},"up":{"uv":[1.0,15.0,0.0,10.0],"rotation":0,"texture":"#1","tintindex":0},"west":{"uv":[0.0,0.0,5.0,0.0],"rotation":0,"texture":"#1","tintindex":0}}},{"name":"cube","from":[12.754558,10.693832,1.0699997],"to":[13.954558,10.693832,7.0699997],"rotation":{"angle":0.0,"axis":"x","origin":[10.954557,14.443831,4.0699997]},"faces":{"down":{"uv":[0.0,10.0,1.0,15.0],"rotation":0,"texture":"#1","tintindex":0},"east":{"uv":[5.0,0.0,0.0,0.0],"rotation":0,"texture":"#1","tintindex":0},"north":{"uv":[1.0,0.0,0.0,0.0],"rotation":0,"texture":"#1","tintindex":0},"south":{"uv":[1.0,0.0,0.0,0.0],"rotation":0,"texture":"#1","tintindex":0},"up":{"uv":[0.0,15.0,1.0,10.0],"rotation":0,"texture":"#1","tintindex":0},"west":{"uv":[5.0,0.0,0.0,0.0],"rotation":0,"texture":"#1","tintindex":0}}},{"name":"cube","from":[14.266726,10.614777,5.1067863],"to":[15.466725,14.214776,5.1067863],"rotation":{"angle":22.5,"axis":"y","origin":[14.866725,-5.585225,33.906788]},"faces":{"down":{"uv":[0.0,0.0,1.0,0.0],"rotation":0,"texture":"#1","tintindex":0},"east":{"uv":[0.0,0.0,5.0,0.0],"rotation":270,"texture":"#1","tintindex":0},"north":{"uv":[1.0,10.0,0.0,13.0],"rotation":180,"texture":"#1","tintindex":0},"south":{"uv":[1.0,13.0,0.0,10.0],"rotation":0,"texture":"#1","tintindex":0},"up":{"uv":[0.0,0.0,1.0,0.0],"rotation":180,"texture":"#1","tintindex":0},"west":{"uv":[0.0,0.0,5.0,0.0],"rotation":90,"texture":"#1","tintindex":0}}},{"name":"cube","from":[14.267185,10.614777,3.0321052],"to":[15.467186,14.214776,3.0321052],"rotation":{"angle":-22.5,"axis":"y","origin":[14.867186,-5.585225,-25.767895]},"faces":{"down":{"uv":[0.0,0.0,1.0,0.0],"rotation":0,"texture":"#1","tintindex":0},"east":{"uv":[0.0,0.0,5.0,0.0],"rotation":270,"texture":"#1","tintindex":0},"north":{"uv":[0.0,13.0,1.0,10.0],"rotation":0,"texture":"#1","tintindex":0},"south":{"uv":[0.0,10.0,1.0,13.0],"rotation":180,"texture":"#1","tintindex":0},"up":{"uv":[0.0,0.0,1.0,0.0],"rotation":180,"texture":"#1","tintindex":0},"west":{"uv":[0.0,0.0,5.0,0.0],"rotation":90,"texture":"#1","tintindex":0}}},{"name":"cube","from":[1.7328151,10.614777,3.0321052],"to":[2.932815,14.214776,3.0321052],"rotation":{"angle":22.5,"axis":"y","origin":[2.3328152,-5.585225,-25.767895]},"faces":{"down":{"uv":[1.0,0.0,0.0,0.0],"rotation":0,"texture":"#1","tintindex":0},"east":{"uv":[0.0,0.0,5.0,0.0],"rotation":90,"texture":"#1","tintindex":0},"north":{"uv":[1.0,13.0,0.0,10.0],"rotation":0,"texture":"#1","tintindex":0},"south":{"uv":[1.0,10.0,0.0,13.0],"rotation":180,"texture":"#1","tintindex":0},"up":{"uv":[1.0,0.0,0.0,0.0],"rotation":180,"texture":"#1","tintindex":0},"west":{"uv":[0.0,0.0,5.0,0.0],"rotation":270,"texture":"#1","tintindex":0}}},{"name":"cube","from":[1.733274,10.614777,5.1067863],"to":[2.933274,14.214776,5.1067863],"rotation":{"angle":-22.5,"axis":"y","origin":[2.3332741,-5.585225,33.906788]},"faces":{"down":{"uv":[1.0,0.0,0.0,0.0],"rotation":0,"texture":"#1","tintindex":0},"east":{"uv":[0.0,0.0,5.0,0.0],"rotation":90,"texture":"#1","tintindex":0},"north":{"uv":[0.0,10.0,1.0,13.0],"rotation":180,"texture":"#1","tintindex":0},"south":{"uv":[0.0,13.0,1.0,10.0],"rotation":0,"texture":"#1","tintindex":0},"up":{"uv":[1.0,0.0,0.0,0.0],"rotation":180,"texture":"#1","tintindex":0},"west":{"uv":[0.0,0.0,5.0,0.0],"rotation":270,"texture":"#1","tintindex":0}}},{"name":"cube","from":[6.0627537,15.362272,1.0699997],"to":[7.2627535,15.362272,7.0699997],"rotation":{"angle":-22.5,"axis":"z","origin":[3.8454425,14.443831,4.0699997]},"faces":{"down":{"uv":[1.0,10.0,0.0,15.0],"rotation":0,"texture":"#1","tintindex":0},"east":{"uv":[0.0,0.0,5.0,0.0],"rotation":0,"texture":"#1","tintindex":0},"north":{"uv":[0.0,0.0,1.0,0.0],"rotation":0,"texture":"#1","tintindex":0},"south":{"uv":[0.0,0.0,1.0,0.0],"rotation":0,"texture":"#1","tintindex":0},"up":{"uv":[1.0,15.0,0.0,10.0],"rotation":0,"texture":"#1","tintindex":0},"west":{"uv":[0.0,0.0,5.0,0.0],"rotation":0,"texture":"#1","tintindex":0}}},{"name":"cube","from":[10.308886,14.214222,0.46999955],"to":[11.508885,14.214222,6.47],"rotation":{"angle":22.5,"axis":"z","origin":[10.954557,14.443831,4.0699997]},"faces":{"down":{"uv":[0.0,10.0,1.0,15.0],"rotation":0,"texture":"#1","tintindex":0},"east":{"uv":[5.0,0.0,0.0,0.0],"rotation":0,"texture":"#1","tintindex":0},"north":{"uv":[1.0,0.0,0.0,0.0],"rotation":0,"texture":"#1","tintindex":0},"south":{"uv":[1.0,0.0,0.0,0.0],"rotation":0,"texture":"#1","tintindex":0},"up":{"uv":[0.0,15.0,1.0,10.0],"rotation":0,"texture":"#1","tintindex":0},"west":{"uv":[5.0,0.0,0.0,0.0],"rotation":0,"texture":"#1","tintindex":0}}},{"name":"cube","from":[12.571869,13.525392,1.0699997],"to":[13.771869,13.525392,7.0699997],"rotation":{"angle":22.5,"axis":"z","origin":[10.954557,14.443831,4.0699997]},"faces":{"down":{"uv":[0.0,10.0,1.0,15.0],"rotation":0,"texture":"#1","tintindex":0},"east":{"uv":[5.0,0.0,0.0,0.0],"rotation":0,"texture":"#1","tintindex":0},"north":{"uv":[1.0,0.0,0.0,0.0],"rotation":0,"texture":"#1","tintindex":0},"south":{"uv":[1.0,0.0,0.0,0.0],"rotation":0,"texture":"#1","tintindex":0},"up":{"uv":[0.0,15.0,1.0,10.0],"rotation":0,"texture":"#1","tintindex":0},"west":{"uv":[5.0,0.0,0.0,0.0],"rotation":0,"texture":"#1","tintindex":0}}},{"name":"cube","from":[5.6,10.614777,8.27],"to":[11.6,14.214776,16.670002],"rotation":{"angle":0.0,"axis":"x","origin":[5.6,4.0147758,11.27]},"faces":{"down":{"uv":[0.0,0.0,7.0,5.0],"rotation":270,"texture":"#1","tintindex":0},"east":{"uv":[14.0,3.0,7.0,6.0],"rotation":0,"texture":"#1","tintindex":0},"north":{"uv":[7.0,6.0,12.0,9.0],"rotation":0,"texture":"#1","tintindex":0},"south":{"uv":[7.0,6.0,12.0,9.0],"rotation":0,"texture":"#1","tintindex":0},"up":{"uv":[7.0,5.0,0.0,0.0],"rotation":90,"texture":"#1","tintindex":0},"west":{"uv":[7.0,3.0,14.0,6.0],"rotation":0,"texture":"#1","tintindex":0}}},{"name":"cube","from":[5.6,14.443831,7.1154423],"to":[11.6,14.443831,8.315443],"rotation":{"angle":22.5,"axis":"x","origin":[8.6,14.443831,7.7154427]},"faces":{"down":{"uv":[1.0,10.0,0.0,15.0],"rotation":270,"texture":"#1","tintindex":0},"east":{"uv":[0.0,0.0,1.0,0.0],"rotation":0,"texture":"#1","tintindex":0},"north":{"uv":[0.0,0.0,5.0,0.0],"rotation":0,"texture":"#1","tintindex":0},"south":{"uv":[0.0,0.0,5.0,0.0],"rotation":0,"texture":"#1","tintindex":0},"up":{"uv":[1.0,15.0,0.0,10.0],"rotation":90,"texture":"#1","tintindex":0},"west":{"uv":[0.0,0.0,1.0,0.0],"rotation":0,"texture":"#1","tintindex":0}}},{"name":"cube","from":[5.6,13.525392,16.441868],"to":[11.6,13.525392,17.641869],"rotation":{"angle":-22.5,"axis":"x","origin":[8.6,14.443831,14.824557]},"faces":{"down":{"uv":[0.0,10.0,1.0,15.0],"rotation":270,"texture":"#1","tintindex":0},"east":{"uv":[1.0,0.0,0.0,0.0],"rotation":0,"texture":"#1","tintindex":0},"north":{"uv":[5.0,0.0,0.0,0.0],"rotation":0,"texture":"#1","tintindex":0},"south":{"uv":[5.0,0.0,0.0,0.0],"rotation":0,"texture":"#1","tintindex":0},"up":{"uv":[0.0,15.0,1.0,10.0],"rotation":90,"texture":"#1","tintindex":0},"west":{"uv":[1.0,0.0,0.0,0.0],"rotation":0,"texture":"#1","tintindex":0}}},{"name":"cube","from":[5.6,15.362272,9.9327545],"to":[11.6,15.362272,11.132753],"rotation":{"angle":22.5,"axis":"x","origin":[8.6,14.443831,7.7154427]},"faces":{"down":{"uv":[1.0,10.0,0.0,15.0],"rotation":270,"texture":"#1","tintindex":0},"east":{"uv":[0.0,0.0,1.0,0.0],"rotation":0,"texture":"#1","tintindex":0},"north":{"uv":[0.0,0.0,5.0,0.0],"rotation":0,"texture":"#1","tintindex":0},"south":{"uv":[0.0,0.0,5.0,0.0],"rotation":0,"texture":"#1","tintindex":0},"up":{"uv":[1.0,15.0,0.0,10.0],"rotation":90,"texture":"#1","tintindex":0},"west":{"uv":[0.0,0.0,1.0,0.0],"rotation":0,"texture":"#1","tintindex":0}}},{"name":"cube","from":[6.2,14.214222,14.178885],"to":[12.2,14.214222,15.378885],"rotation":{"angle":-22.5,"axis":"x","origin":[8.6,14.443831,14.824557]},"faces":{"down":{"uv":[0.0,10.0,1.0,15.0],"rotation":270,"texture":"#1","tintindex":0},"east":{"uv":[1.0,0.0,0.0,0.0],"rotation":0,"texture":"#1","tintindex":0},"north":{"uv":[5.0,0.0,0.0,0.0],"rotation":0,"texture":"#1","tintindex":0},"south":{"uv":[5.0,0.0,0.0,0.0],"rotation":0,"texture":"#1","tintindex":0},"up":{"uv":[0.0,15.0,1.0,10.0],"rotation":90,"texture":"#1","tintindex":0},"west":{"uv":[1.0,0.0,0.0,0.0],"rotation":0,"texture":"#1","tintindex":0}}},{"name":"cube","from":[7.5632133,10.614777,18.136726],"to":[7.5632133,14.214776,19.336727],"rotation":{"angle":22.5,"axis":"y","origin":[-21.23679,-5.585225,18.736725]},"faces":{"down":{"uv":[0.0,0.0,1.0,0.0],"rotation":270,"texture":"#1","tintindex":0},"east":{"uv":[1.0,10.0,0.0,13.0],"rotation":180,"texture":"#1","tintindex":0},"north":{"uv":[0.0,0.0,5.0,0.0],"rotation":90,"texture":"#1","tintindex":0},"south":{"uv":[0.0,0.0,5.0,0.0],"rotation":270,"texture":"#1","tintindex":0},"up":{"uv":[0.0,0.0,1.0,0.0],"rotation":270,"texture":"#1","tintindex":0},"west":{"uv":[1.0,13.0,0.0,10.0],"rotation":0,"texture":"#1","tintindex":0}}},{"name":"cube","from":[9.637895,10.614777,18.137184],"to":[9.637895,14.214776,19.337185],"rotation":{"angle":-22.5,"axis":"y","origin":[38.437897,-5.585225,18.737185]},"faces":{"down":{"uv":[0.0,0.0,1.0,0.0],"rotation":270,"texture":"#1","tintindex":0},"east":{"uv":[0.0,13.0,1.0,10.0],"rotation":0,"texture":"#1","tintindex":0},"north":{"uv":[0.0,0.0,5.0,0.0],"rotation":90,"texture":"#1","tintindex":0},"south":{"uv":[0.0,0.0,5.0,0.0],"rotation":270,"texture":"#1","tintindex":0},"up":{"uv":[0.0,0.0,1.0,0.0],"rotation":270,"texture":"#1","tintindex":0},"west":{"uv":[0.0,10.0,1.0,13.0],"rotation":180,"texture":"#1","tintindex":0}}},{"name":"cube","from":[7.5632133,10.614777,5.6032743],"to":[7.5632133,14.214776,6.803274],"rotation":{"angle":-22.5,"axis":"y","origin":[-21.23679,-5.585225,6.2032747]},"faces":{"down":{"uv":[1.0,0.0,0.0,0.0],"rotation":270,"texture":"#1","tintindex":0},"east":{"uv":[0.0,10.0,1.0,13.0],"rotation":180,"texture":"#1","tintindex":0},"north":{"uv":[0.0,0.0,5.0,0.0],"rotation":270,"texture":"#1","tintindex":0},"south":{"uv":[0.0,0.0,5.0,0.0],"rotation":90,"texture":"#1","tintindex":0},"up":{"uv":[1.0,0.0,0.0,0.0],"rotation":270,"texture":"#1","tintindex":0},"west":{"uv":[0.0,13.0,1.0,10.0],"rotation":0,"texture":"#1","tintindex":0}}},{"name":"cube","from":[9.637895,10.614777,5.602815],"to":[9.637895,14.214776,6.8028154],"rotation":{"angle":22.5,"axis":"y","origin":[38.437897,-5.585225,6.202815]},"faces":{"down":{"uv":[1.0,0.0,0.0,0.0],"rotation":270,"texture":"#1","tintindex":0},"east":{"uv":[1.0,13.0,0.0,10.0],"rotation":0,"texture":"#1","tintindex":0},"north":{"uv":[0.0,0.0,5.0,0.0],"rotation":270,"texture":"#1","tintindex":0},"south":{"uv":[0.0,0.0,5.0,0.0],"rotation":90,"texture":"#1","tintindex":0},"up":{"uv":[1.0,0.0,0.0,0.0],"rotation":270,"texture":"#1","tintindex":0},"west":{"uv":[1.0,10.0,0.0,13.0],"rotation":180,"texture":"#1","tintindex":0}}},{"name":"cube","from":[5.6,10.693832,7.1154423],"to":[11.6,10.693832,8.315443],"rotation":{"angle":0.0,"axis":"x","origin":[8.6,14.443831,7.7154427]},"faces":{"down":{"uv":[1.0,10.0,0.0,15.0],"rotation":270,"texture":"#1","tintindex":0},"east":{"uv":[0.0,0.0,1.0,0.0],"rotation":0,"texture":"#1","tintindex":0},"north":{"uv":[0.0,0.0,5.0,0.0],"rotation":0,"texture":"#1","tintindex":0},"south":{"uv":[0.0,0.0,5.0,0.0],"rotation":0,"texture":"#1","tintindex":0},"up":{"uv":[1.0,15.0,0.0,10.0],"rotation":90,"texture":"#1","tintindex":0},"west":{"uv":[0.0,0.0,1.0,0.0],"rotation":0,"texture":"#1","tintindex":0}}},{"name":"cube","from":[5.6,10.693832,16.624557],"to":[11.6,10.693832,17.824558],"rotation":{"angle":0.0,"axis":"x","origin":[8.6,14.443831,14.824557]},"faces":{"down":{"uv":[0.0,10.0,1.0,15.0],"rotation":270,"texture":"#1","tintindex":0},"east":{"uv":[1.0,0.0,0.0,0.0],"rotation":0,"texture":"#1","tintindex":0},"north":{"uv":[5.0,0.0,0.0,0.0],"rotation":0,"texture":"#1","tintindex":0},"south":{"uv":[5.0,0.0,0.0,0.0],"rotation":0,"texture":"#1","tintindex":0},"up":{"uv":[0.0,15.0,1.0,10.0],"rotation":90,"texture":"#1","tintindex":0},"west":{"uv":[1.0,0.0,0.0,0.0],"rotation":0,"texture":"#1","tintindex":0}}},{"name":"cube","from":[4.3999996,14.214776,4.6699996],"to":[12.8,17.814777,10.67],"rotation":{"angle":0.0,"axis":"x","origin":[9.8,7.6147757,4.6699996]},"faces":{"down":{"uv":[0.0,0.0,7.0,5.0],"rotation":180,"texture":"#1","tintindex":0},"east":{"uv":[7.0,6.0,12.0,9.0],"rotation":0,"texture":"#1","tintindex":0},"north":{"uv":[7.0,3.0,14.0,6.0],"rotation":0,"texture":"#1","tintindex":0},"south":{"uv":[14.0,3.0,7.0,6.0],"rotation":0,"texture":"#1","tintindex":0},"up":{"uv":[7.0,5.0,0.0,0.0],"rotation":180,"texture":"#1","tintindex":0},"west":{"uv":[7.0,6.0,12.0,9.0],"rotation":0,"texture":"#1","tintindex":0}}},{"name":"cube","from":[12.754558,18.04383,4.6699996],"to":[13.954558,18.04383,10.67],"rotation":{"angle":22.5,"axis":"z","origin":[13.354558,18.04383,7.67]},"faces":{"down":{"uv":[1.0,10.0,0.0,15.0],"rotation":180,"texture":"#1","tintindex":0},"east":{"uv":[0.0,0.0,5.0,0.0],"rotation":0,"texture":"#1","tintindex":0},"north":{"uv":[0.0,0.0,1.0,0.0],"rotation":0,"texture":"#1","tintindex":0},"south":{"uv":[0.0,0.0,1.0,0.0],"rotation":0,"texture":"#1","tintindex":0},"up":{"uv":[1.0,15.0,0.0,10.0],"rotation":180,"texture":"#1","tintindex":0},"west":{"uv":[0.0,0.0,5.0,0.0],"rotation":0,"texture":"#1","tintindex":0}}},{"name":"cube","from":[3.4281316,17.125393,4.6699996],"to":[4.6281314,17.125393,10.67],"rotation":{"angle":-22.5,"axis":"z","origin":[6.2454424,18.04383,7.67]},"faces":{"down":{"uv":[0.0,10.0,1.0,15.0],"rotation":180,"texture":"#1","tintindex":0},"east":{"uv":[5.0,0.0,0.0,0.0],"rotation":0,"texture":"#1","tintindex":0},"north":{"uv":[1.0,0.0,0.0,0.0],"rotation":0,"texture":"#1","tintindex":0},"south":{"uv":[1.0,0.0,0.0,0.0],"rotation":0,"texture":"#1","tintindex":0},"up":{"uv":[0.0,15.0,1.0,10.0],"rotation":180,"texture":"#1","tintindex":0},"west":{"uv":[5.0,0.0,0.0,0.0],"rotation":0,"texture":"#1","tintindex":0}}},{"name":"cube","from":[9.937246,18.962273,4.6699996],"to":[11.137247,18.962273,10.67],"rotation":{"angle":22.5,"axis":"z","origin":[13.354558,18.04383,7.67]},"faces":{"down":{"uv":[1.0,10.0,0.0,15.0],"rotation":180,"texture":"#1","tintindex":0},"east":{"uv":[0.0,0.0,5.0,0.0],"rotation":0,"texture":"#1","tintindex":0},"north":{"uv":[0.0,0.0,1.0,0.0],"rotation":0,"texture":"#1","tintindex":0},"south":{"uv":[0.0,0.0,1.0,0.0],"rotation":0,"texture":"#1","tintindex":0},"up":{"uv":[1.0,15.0,0.0,10.0],"rotation":180,"texture":"#1","tintindex":0},"west":{"uv":[0.0,0.0,5.0,0.0],"rotation":0,"texture":"#1","tintindex":0}}},{"name":"cube","from":[5.691115,17.814222,5.2699995],"to":[6.891115,17.814222,11.27],"rotation":{"angle":-22.5,"axis":"z","origin":[6.2454424,18.04383,7.67]},"faces":{"down":{"uv":[0.0,10.0,1.0,15.0],"rotation":180,"texture":"#1","tintindex":0},"east":{"uv":[5.0,0.0,0.0,0.0],"rotation":0,"texture":"#1","tintindex":0},"north":{"uv":[1.0,0.0,0.0,0.0],"rotation":0,"texture":"#1","tintindex":0},"south":{"uv":[1.0,0.0,0.0,0.0],"rotation":0,"texture":"#1","tintindex":0},"up":{"uv":[0.0,15.0,1.0,10.0],"rotation":180,"texture":"#1","tintindex":0},"west":{"uv":[5.0,0.0,0.0,0.0],"rotation":0,"texture":"#1","tintindex":0}}},{"name":"cube","from":[1.733274,14.214776,6.6332135],"to":[2.933274,17.814777,6.6332135],"rotation":{"angle":22.5,"axis":"y","origin":[2.3332741,-1.9852247,-22.166786]},"faces":{"down":{"uv":[0.0,0.0,1.0,0.0],"rotation":180,"texture":"#1","tintindex":0},"east":{"uv":[0.0,0.0,5.0,0.0],"rotation":90,"texture":"#1","tintindex":0},"north":{"uv":[1.0,13.0,0.0,10.0],"rotation":0,"texture":"#1","tintindex":0},"south":{"uv":[1.0,10.0,0.0,13.0],"rotation":180,"texture":"#1","tintindex":0},"up":{"uv":[0.0,0.0,1.0,0.0],"rotation":0,"texture":"#1","tintindex":0},"west":{"uv":[0.0,0.0,5.0,0.0],"rotation":270,"texture":"#1","tintindex":0}}},{"name":"cube","from":[1.7328151,14.214776,8.707895],"to":[2.932815,17.814777,8.707895],"rotation":{"angle":-22.5,"axis":"y","origin":[2.3328152,-1.9852247,37.507896]},"faces":{"down":{"uv":[0.0,0.0,1.0,0.0],"rotation":180,"texture":"#1","tintindex":0},"east":{"uv":[0.0,0.0,5.0,0.0],"rotation":90,"texture":"#1","tintindex":0},"north":{"uv":[0.0,10.0,1.0,13.0],"rotation":180,"texture":"#1","tintindex":0},"south":{"uv":[0.0,13.0,1.0,10.0],"rotation":0,"texture":"#1","tintindex":0},"up":{"uv":[0.0,0.0,1.0,0.0],"rotation":0,"texture":"#1","tintindex":0},"west":{"uv":[0.0,0.0,5.0,0.0],"rotation":270,"texture":"#1","tintindex":0}}},{"name":"cube","from":[14.266726,14.214776,6.6332135],"to":[15.466725,17.814777,6.6332135],"rotation":{"angle":-22.5,"axis":"y","origin":[14.866725,-1.9852247,-22.166786]},"faces":{"down":{"uv":[1.0,0.0,0.0,0.0],"rotation":180,"texture":"#1","tintindex":0},"east":{"uv":[0.0,0.0,5.0,0.0],"rotation":270,"texture":"#1","tintindex":0},"north":{"uv":[0.0,13.0,1.0,10.0],"rotation":0,"texture":"#1","tintindex":0},"south":{"uv":[0.0,10.0,1.0,13.0],"rotation":180,"texture":"#1","tintindex":0},"up":{"uv":[1.0,0.0,0.0,0.0],"rotation":0,"texture":"#1","tintindex":0},"west":{"uv":[0.0,0.0,5.0,0.0],"rotation":90,"texture":"#1","tintindex":0}}},{"name":"cube","from":[14.267185,14.214776,8.707895],"to":[15.467186,17.814777,8.707895],"rotation":{"angle":22.5,"axis":"y","origin":[14.867186,-1.9852247,37.507896]},"faces":{"down":{"uv":[1.0,0.0,0.0,0.0],"rotation":180,"texture":"#1","tintindex":0},"east":{"uv":[0.0,0.0,5.0,0.0],"rotation":270,"texture":"#1","tintindex":0},"north":{"uv":[1.0,10.0,0.0,13.0],"rotation":180,"texture":"#1","tintindex":0},"south":{"uv":[1.0,13.0,0.0,10.0],"rotation":0,"texture":"#1","tintindex":0},"up":{"uv":[1.0,0.0,0.0,0.0],"rotation":0,"texture":"#1","tintindex":0},"west":{"uv":[0.0,0.0,5.0,0.0],"rotation":90,"texture":"#1","tintindex":0}}},{"name":"cube","from":[12.754558,14.293832,4.6699996],"to":[13.954558,14.293832,10.67],"rotation":{"angle":0.0,"axis":"x","origin":[13.354558,18.04383,7.67]},"faces":{"down":{"uv":[1.0,10.0,0.0,15.0],"rotation":180,"texture":"#1","tintindex":0},"east":{"uv":[0.0,0.0,5.0,0.0],"rotation":0,"texture":"#1","tintindex":0},"north":{"uv":[0.0,0.0,1.0,0.0],"rotation":0,"texture":"#1","tintindex":0},"south":{"uv":[0.0,0.0,1.0,0.0],"rotation":0,"texture":"#1","tintindex":0},"up":{"uv":[1.0,15.0,0.0,10.0],"rotation":180,"texture":"#1","tintindex":0},"west":{"uv":[0.0,0.0,5.0,0.0],"rotation":0,"texture":"#1","tintindex":0}}},{"name":"cube","from":[3.2454426,14.293832,4.6699996],"to":[4.4454427,14.293832,10.67],"rotation":{"angle":0.0,"axis":"x","origin":[6.2454424,18.04383,7.67]},"faces":{"down":{"uv":[0.0,10.0,1.0,15.0],"rotation":180,"texture":"#1","tintindex":0},"east":{"uv":[5.0,0.0,0.0,0.0],"rotation":0,"texture":"#1","tintindex":0},"north":{"uv":[1.0,0.0,0.0,0.0],"rotation":0,"texture":"#1","tintindex":0},"south":{"uv":[1.0,0.0,0.0,0.0],"rotation":0,"texture":"#1","tintindex":0},"up":{"uv":[0.0,15.0,1.0,10.0],"rotation":180,"texture":"#1","tintindex":0},"west":{"uv":[5.0,0.0,0.0,0.0],"rotation":0,"texture":"#1","tintindex":0}}},{"name":"cube","from":[12.2,7.0147758,-12.7300005],"to":[14.0,9.414776,17.27],"rotation":{"angle":0.0,"axis":"x","origin":[8.0,4.0147758,8.27]},"faces":{"down":{"uv":[0.75,5.5,0.375,11.75],"rotation":0,"texture":"#0","tintindex":0},"east":{"uv":[0.0,3.875,6.25,4.375],"rotation":0,"texture":"#0","tintindex":0},"north":{"uv":[2.625,6.5,3.0,7.0],"rotation":0,"texture":"#0","tintindex":0},"south":{"uv":[3.0,6.5,3.375,7.0],"rotation":0,"texture":"#0","tintindex":0},"up":{"uv":[0.375,11.75,0.0,5.5],"rotation":0,"texture":"#0","tintindex":0},"west":{"uv":[0.0,4.375,6.25,4.875],"rotation":0,"texture":"#0","tintindex":0}}},{"name":"cube","from":[3.1999998,7.0147758,-12.7300005],"to":[5.0,9.414776,17.27],"rotation":{"angle":0.0,"axis":"x","origin":[9.2,4.0147758,8.27]},"faces":{"down":{"uv":[0.375,5.5,0.75,11.75],"rotation":0,"texture":"#0","tintindex":0},"east":{"uv":[6.25,4.375,0.0,4.875],"rotation":0,"texture":"#0","tintindex":0},"north":{"uv":[3.0,6.5,2.625,7.0],"rotation":0,"texture":"#0","tintindex":0},"south":{"uv":[3.375,6.5,3.0,7.0],"rotation":0,"texture":"#0","tintindex":0},"up":{"uv":[0.0,11.75,0.375,5.5],"rotation":0,"texture":"#0","tintindex":0},"west":{"uv":[6.25,3.875,0.0,4.375],"rotation":0,"texture":"#0","tintindex":0}}},{"name":"cube","from":[1.3999997,6.414776,7.0699997],"to":[15.8,9.414776,8.87],"rotation":{"angle":0.0,"axis":"x","origin":[8.0,4.0147758,8.27]},"faces":{"down":{"uv":[8.5,3.375,5.5,3.75],"rotation":0,"texture":"#0","tintindex":0},"east":{"uv":[1.875,6.5,2.25,7.125],"rotation":0,"texture":"#0","tintindex":0},"north":{"uv":[5.5,1.75,8.5,2.375],"rotation":0,"texture":"#0","tintindex":0},"south":{"uv":[5.5,2.375,8.5,3.0],"rotation":0,"texture":"#0","tintindex":0},"up":{"uv":[8.5,3.375,5.5,3.0],"rotation":0,"texture":"#0","tintindex":0},"west":{"uv":[2.25,6.5,2.625,7.125],"rotation":0,"texture":"#0","tintindex":0}}},{"name":"cube","from":[15.8,7.0147758,7.0699997],"to":[18.2,8.814775,8.87],"rotation":{"angle":0.0,"axis":"x","origin":[8.0,4.0147758,8.27]},"faces":{"down":{"uv":[6.0,6.75,5.5,7.125],"rotation":0,"texture":"#0","tintindex":0},"east":{"uv":[6.75,6.25,7.125,6.625],"rotation":0,"texture":"#0","tintindex":0},"north":{"uv":[4.0,6.75,4.5,7.125],"rotation":0,"texture":"#0","tintindex":0},"south":{"uv":[4.5,6.75,5.0,7.125],"rotation":0,"texture":"#0","tintindex":0},"up":{"uv":[5.5,7.125,5.0,6.75],"rotation":0,"texture":"#0","tintindex":0},"west":{"uv":[6.75,6.625,7.125,7.0],"rotation":0,"texture":"#0","tintindex":0}}},{"name":"cube","from":[-1.0000005,7.0147758,7.0699997],"to":[1.3999997,8.814775,8.87],"rotation":{"angle":0.0,"axis":"x","origin":[9.2,4.0147758,8.27]},"faces":{"down":{"uv":[5.5,6.75,6.0,7.125],"rotation":0,"texture":"#0","tintindex":0},"east":{"uv":[7.125,6.625,6.75,7.0],"rotation":0,"texture":"#0","tintindex":0},"north":{"uv":[4.5,6.75,4.0,7.125],"rotation":0,"texture":"#0","tintindex":0},"south":{"uv":[5.0,6.75,4.5,7.125],"rotation":0,"texture":"#0","tintindex":0},"up":{"uv":[5.0,7.125,5.5,6.75],"rotation":0,"texture":"#0","tintindex":0},"west":{"uv":[7.125,6.25,6.75,6.625],"rotation":0,"texture":"#0","tintindex":0}}},{"name":"cube","from":[1.3999997,10.014776,-1.9299998],"to":[15.8,13.614776,-1.3300004],"rotation":{"angle":0.0,"axis":"x","origin":[8.0,4.0147758,8.27]},"faces":{"down":{"uv":[9.25,3.875,6.25,4.0],"rotation":0,"texture":"#0","tintindex":0},"east":{"uv":[3.375,6.5,3.5,7.25],"rotation":0,"texture":"#0","tintindex":0},"north":{"uv":[5.5,0.0,8.5,0.75],"rotation":0,"texture":"#0","tintindex":0},"south":{"uv":[0.75,5.5,3.75,6.25],"rotation":0,"texture":"#0","tintindex":0},"up":{"uv":[8.5,3.875,5.5,3.75],"rotation":0,"texture":"#0","tintindex":0},"west":{"uv":[2.625,7.0,2.75,7.75],"rotation":0,"texture":"#0","tintindex":0}}},{"name":"cube","from":[14.6,10.614777,-1.3300004],"to":[15.2,13.614776,17.87],"rotation":{"angle":-22.5,"axis":"z","origin":[14.45,14.064776,7.97]},"faces":{"down":{"uv":[3.75,6.25,3.625,10.25],"rotation":0,"texture":"#0","tintindex":0},"east":{"uv":[0.0,4.875,4.0,5.5],"rotation":0,"texture":"#0","tintindex":0},"north":{"uv":[2.125,7.125,2.25,7.75],"rotation":0,"texture":"#0","tintindex":0},"south":{"uv":[2.25,7.125,2.375,7.75],"rotation":0,"texture":"#0","tintindex":0},"up":{"uv":[3.625,10.25,3.5,6.25],"rotation":0,"texture":"#0","tintindex":0},"west":{"uv":[4.0,4.875,8.0,5.5],"rotation":0,"texture":"#0","tintindex":0}}},{"name":"cube","from":[14.6,14.214776,-1.3300004],"to":[15.2,16.614777,17.87],"rotation":{"angle":-22.5,"axis":"z","origin":[14.45,14.064776,7.97]},"faces":{"down":{"uv":[1.0,6.5,0.875,10.5],"rotation":0,"texture":"#0","tintindex":0},"east":{"uv":[5.5,0.75,9.5,1.25],"rotation":0,"texture":"#0","tintindex":0},"north":{"uv":[2.375,7.125,2.5,7.625],"rotation":0,"texture":"#0","tintindex":0},"south":{"uv":[2.5,7.125,2.625,7.625],"rotation":0,"texture":"#0","tintindex":0},"up":{"uv":[0.875,10.5,0.75,6.5],"rotation":0,"texture":"#0","tintindex":0},"west":{"uv":[5.5,1.25,9.5,1.75],"rotation":0,"texture":"#0","tintindex":0}}},{"name":"cube","from":[13.400001,10.014776,-1.3300004],"to":[14.6,17.214775,0.46999955],"rotation":{"angle":-22.5,"axis":"z","origin":[14.45,14.064776,7.97]},"faces":{"down":{"uv":[7.125,4.375,6.875,4.75],"rotation":0,"texture":"#0","tintindex":0},"east":{"uv":[6.0,6.25,6.375,7.75],"rotation":0,"texture":"#0","tintindex":0},"north":{"uv":[1.0,6.5,1.25,8.0],"rotation":0,"texture":"#0","tintindex":0},"south":{"uv":[1.25,6.5,1.5,8.0],"rotation":0,"texture":"#0","tintindex":0},"up":{"uv":[7.125,4.375,6.875,4.0],"rotation":0,"texture":"#0","tintindex":0},"west":{"uv":[6.375,6.25,6.75,7.75],"rotation":0,"texture":"#0","tintindex":0}}},{"name":"cube","from":[13.400001,10.014776,15.470001],"to":[14.6,17.214775,17.27],"rotation":{"angle":-22.5,"axis":"z","origin":[14.45,14.064776,7.97]},"faces":{"down":{"uv":[7.125,4.75,6.875,4.375],"rotation":0,"texture":"#0","tintindex":0},"east":{"uv":[6.375,6.25,6.0,7.75],"rotation":0,"texture":"#0","tintindex":0},"north":{"uv":[1.5,6.5,1.25,8.0],"rotation":0,"texture":"#0","tintindex":0},"south":{"uv":[1.25,6.5,1.0,8.0],"rotation":0,"texture":"#0","tintindex":0},"up":{"uv":[7.125,4.0,6.875,4.375],"rotation":0,"texture":"#0","tintindex":0},"west":{"uv":[6.75,6.25,6.375,7.75],"rotation":0,"texture":"#0","tintindex":0}}},{"name":"cube","from":[2.6,10.014776,-1.3300004],"to":[3.7999997,17.214775,0.46999955],"rotation":{"angle":22.5,"axis":"z","origin":[2.7499998,14.064776,7.97]},"faces":{"down":{"uv":[6.875,4.375,7.125,4.75],"rotation":0,"texture":"#0","tintindex":0},"east":{"uv":[6.75,6.25,6.375,7.75],"rotation":0,"texture":"#0","tintindex":0},"north":{"uv":[1.25,6.5,1.0,8.0],"rotation":0,"texture":"#0","tintindex":0},"south":{"uv":[1.5,6.5,1.25,8.0],"rotation":0,"texture":"#0","tintindex":0},"up":{"uv":[6.875,4.375,7.125,4.0],"rotation":0,"texture":"#0","tintindex":0},"west":{"uv":[6.375,6.25,6.0,7.75],"rotation":0,"texture":"#0","tintindex":0}}},{"name":"cube","from":[1.9999998,14.214776,-1.3300004],"to":[2.6,16.614777,17.87],"rotation":{"angle":22.5,"axis":"z","origin":[2.7499998,14.064776,7.97]},"faces":{"down":{"uv":[0.875,6.5,1.0,10.5],"rotation":0,"texture":"#0","tintindex":0},"east":{"uv":[9.5,1.25,5.5,1.75],"rotation":0,"texture":"#0","tintindex":0},"north":{"uv":[2.5,7.125,2.375,7.625],"rotation":0,"texture":"#0","tintindex":0},"south":{"uv":[2.625,7.125,2.5,7.625],"rotation":0,"texture":"#0","tintindex":0},"up":{"uv":[0.75,10.5,0.875,6.5],"rotation":0,"texture":"#0","tintindex":0},"west":{"uv":[9.5,0.75,5.5,1.25],"rotation":0,"texture":"#0","tintindex":0}}},{"name":"cube","from":[1.9999998,10.614777,-1.3300004],"to":[2.6,13.614776,17.87],"rotation":{"angle":22.5,"axis":"z","origin":[2.7499998,14.064776,7.97]},"faces":{"down":{"uv":[3.625,6.25,3.75,10.25],"rotation":0,"texture":"#0","tintindex":0},"east":{"uv":[8.0,4.875,4.0,5.5],"rotation":0,"texture":"#0","tintindex":0},"north":{"uv":[2.25,7.125,2.125,7.75],"rotation":0,"texture":"#0","tintindex":0},"south":{"uv":[2.375,7.125,2.25,7.75],"rotation":0,"texture":"#0","tintindex":0},"up":{"uv":[3.5,10.25,3.625,6.25],"rotation":0,"texture":"#0","tintindex":0},"west":{"uv":[4.0,4.875,0.0,5.5],"rotation":0,"texture":"#0","tintindex":0}}}],"display":{"head":{"translation":[0.0,-6.4,0.0],"rotation":[0.0,0.0,0.0],"scale":[3.8095,3.8095,3.8095]}}}