{"textures":{"0":"modelengine:entity/airship","1":"modelengine:entity/stearingwheel"},"elements":[{"name":"cube","from":[-0.14320016,21.414135,3.5071998],"to":[15.02,29.139736,12.4928],"rotation":{"angle":0.0,"axis":"x","origin":[8.0,21.835335,8.0]},"faces":{"down":{"uv":[5.6,1.6666667,2.8,3.3333335],"rotation":0,"texture":"#0","tintindex":0},"east":{"uv":[5.6,2.0666666,7.2666664,3.7333333],"rotation":0,"texture":"#0","tintindex":0},"north":{"uv":[0.0,0.0,2.8,1.6666667],"rotation":0,"texture":"#0","tintindex":0},"south":{"uv":[0.0,1.6666667,2.8,3.3333335],"rotation":0,"texture":"#0","tintindex":0},"up":{"uv":[5.6,1.6666667,2.8,0.0],"rotation":0,"texture":"#0","tintindex":0},"west":{"uv":[2.8,6.0,4.4666667,7.666667],"rotation":0,"texture":"#0","tintindex":0}}},{"name":"cube","from":[-0.14320016,21.975735,12.4928],"to":[15.02,29.838135,13.0544],"rotation":{"angle":0.0,"axis":"x","origin":[8.0,21.835335,8.0]},"faces":{"down":{"uv":[14.6,10.466667,11.800001,10.566668],"rotation":0,"texture":"#0","tintindex":0},"east":{"uv":[3.5666666,12.166667,3.6666667,13.633334],"rotation":0,"texture":"#0","tintindex":0},"north":{"uv":[0.0,3.3333335,2.8,4.8],"rotation":0,"texture":"#0","tintindex":0},"south":{"uv":[2.8,3.3333335,5.6,4.8],"rotation":0,"texture":"#0","tintindex":0},"up":{"uv":[14.6,10.466667,11.800001,10.366667],"rotation":0,"texture":"#0","tintindex":0},"west":{"uv":[11.366667,12.433333,11.466667,13.900001],"rotation":0,"texture":"#0","tintindex":0}}},{"name":"cube","from":[-0.14320016,23.098934,13.0544],"to":[15.02,28.714935,13.616],"rotation":{"angle":0.0,"axis":"x","origin":[8.0,21.835335,8.0]},"faces":{"down":{"uv":[14.7,4.0,11.900001,4.1000004],"rotation":0,"texture":"#0","tintindex":0},"east":{"uv":[12.933333,12.566668,13.033333,13.6],"rotation":0,"texture":"#0","tintindex":0},"north":{"uv":[5.6,0.0,8.400001,1.0333333],"rotation":0,"texture":"#0","tintindex":0},"south":{"uv":[5.6,1.0333333,8.400001,2.0666666],"rotation":0,"texture":"#0","tintindex":0},"up":{"uv":[14.7,4.0,11.900001,3.9],"rotation":0,"texture":"#0","tintindex":0},"west":{"uv":[12.966667,1.3333334,13.066668,2.3666668],"rotation":0,"texture":"#0","tintindex":0}}},{"name":"cube","from":[0.4183998,24.222134,13.616],"to":[14.4584,27.591736,14.1776],"rotation":{"angle":0.0,"axis":"x","origin":[8.0,21.835335,8.0]},"faces":{"down":{"uv":[15.033333,9.833334,12.433333,9.933333],"rotation":0,"texture":"#0","tintindex":0},"east":{"uv":[12.033333,13.2,12.133334,13.833334],"rotation":0,"texture":"#0","tintindex":0},"north":{"uv":[7.2666664,3.1000001,9.866667,3.7333333],"rotation":0,"texture":"#0","tintindex":0},"south":{"uv":[7.9333334,3.7333333,10.533334,4.366667],"rotation":0,"texture":"#0","tintindex":0},"up":{"uv":[14.6,3.2333333,12.0,3.1333332],"rotation":0,"texture":"#0","tintindex":0},"west":{"uv":[7.066667,13.233334,7.166667,13.866667],"rotation":0,"texture":"#0","tintindex":0}}},{"name":"cube","from":[-4.7296004,21.975735,4.0688],"to":[-0.14320016,28.578136,11.9312],"rotation":{"angle":0.0,"axis":"x","origin":[5.66,21.835335,8.0]},"faces":{"down":{"uv":[10.033334,4.366667,9.200001,5.8333335],"rotation":0,"texture":"#0","tintindex":0},"east":{"uv":[0.0,7.5,1.4666667,8.966667],"rotation":0,"texture":"#0","tintindex":0},"north":{"uv":[3.3,9.133333,4.133333,10.6],"rotation":0,"texture":"#0","tintindex":0},"south":{"uv":[4.133333,9.133333,4.9666667,10.6],"rotation":0,"texture":"#0","tintindex":0},"up":{"uv":[5.8,10.6,4.9666667,9.133333],"rotation":0,"texture":"#0","tintindex":0},"west":{"uv":[1.4666667,7.666667,2.9333334,9.133333],"rotation":0,"texture":"#0","tintindex":0}}},{"name":"cube","from":[-7.8184004,22.537334,4.6303997],"to":[-4.7296004,28.016537,11.3696],"rotation":{"angle":0.0,"axis":"x","origin":[3.7879996,21.835335,8.0]},"faces":{"down":{"uv":[1.9666667,11.033333,1.4,12.266666],"rotation":0,"texture":"#0","tintindex":0},"east":{"uv":[8.400001,0.0,9.633333,1.2333333],"rotation":0,"texture":"#0","tintindex":0},"north":{"uv":[5.0,10.6,5.566667,11.833334],"rotation":0,"texture":"#0","tintindex":0},"south":{"uv":[10.933333,7.033334,11.5,8.266666],"rotation":0,"texture":"#0","tintindex":0},"up":{"uv":[1.4,12.266666,0.8333334,11.033333],"rotation":0,"texture":"#0","tintindex":0},"west":{"uv":[8.666667,7.366667,9.900001,8.6],"rotation":0,"texture":"#0","tintindex":0}}},{"name":"cube","from":[-9.4096,23.098934,5.192],"to":[-7.8184004,27.454937,10.808001],"rotation":{"angle":0.0,"axis":"x","origin":[4.256,21.835335,8.0]},"faces":{"down":{"uv":[10.066668,12.333334,9.766666,13.366667],"rotation":0,"texture":"#0","tintindex":0},"east":{"uv":[9.900001,7.3,10.933333,8.333334],"rotation":0,"texture":"#0","tintindex":0},"north":{"uv":[8.3,10.1,8.6,11.133334],"rotation":0,"texture":"#0","tintindex":0},"south":{"uv":[9.166667,12.333334,9.466667,13.366667],"rotation":0,"texture":"#0","tintindex":0},"up":{"uv":[9.766666,13.366667,9.466667,12.333334],"rotation":0,"texture":"#0","tintindex":0},"west":{"uv":[9.900001,8.333334,10.933333,9.366667],"rotation":0,"texture":"#0","tintindex":0}}},{"name":"cube","from":[-9.4096,23.660534,10.808001],"to":[-7.8184004,28.153336,11.3696],"rotation":{"angle":0.0,"axis":"x","origin":[4.256,21.835335,8.0]},"faces":{"down":{"uv":[14.1,1.0666667,13.800001,1.1666667],"rotation":0,"texture":"#0","tintindex":0},"east":{"uv":[13.166667,1.3333334,13.266666,2.1666667],"rotation":0,"texture":"#0","tintindex":0},"north":{"uv":[10.933333,0.0,11.233334,0.8333334],"rotation":0,"texture":"#0","tintindex":0},"south":{"uv":[4.533334,12.466667,4.8333335,13.300001],"rotation":0,"texture":"#0","tintindex":0},"up":{"uv":[14.066668,13.0,13.766666,12.900001],"rotation":0,"texture":"#0","tintindex":0},"west":{"uv":[13.166667,7.7000003,13.266666,8.533334],"rotation":0,"texture":"#0","tintindex":0}}},{"name":"cube","from":[-7.8184004,23.098934,11.3696],"to":[-4.7296004,28.714935,11.9312],"rotation":{"angle":0.0,"axis":"x","origin":[3.7879996,21.835335,8.0]},"faces":{"down":{"uv":[13.866667,9.266666,13.300001,9.366667],"rotation":0,"texture":"#0","tintindex":0},"east":{"uv":[12.333334,12.966667,12.433333,14.0],"rotation":0,"texture":"#0","tintindex":0},"north":{"uv":[9.133333,11.300001,9.700001,12.333334],"rotation":0,"texture":"#0","tintindex":0},"south":{"uv":[9.700001,11.300001,10.266666,12.333334],"rotation":0,"texture":"#0","tintindex":0},"up":{"uv":[13.833334,8.566668,13.266666,8.466667],"rotation":0,"texture":"#0","tintindex":0},"west":{"uv":[12.433333,12.966667,12.533333,14.0],"rotation":0,"texture":"#0","tintindex":0}}},{"name":"cube","from":[-10.439201,23.660534,5.7536],"to":[-9.4096,26.893337,10.2464],"rotation":{"angle":0.0,"axis":"x","origin":[2.8519998,21.835335,8.0]},"faces":{"down":{"uv":[0.20000002,12.7,0.0,13.533333],"rotation":0,"texture":"#0","tintindex":0},"east":{"uv":[10.933333,8.266666,11.766666,9.1],"rotation":0,"texture":"#0","tintindex":0},"north":{"uv":[2.266667,12.633334,2.4666667,13.466667],"rotation":0,"texture":"#0","tintindex":0},"south":{"uv":[2.4666667,12.633334,2.6666667,13.466667],"rotation":0,"texture":"#0","tintindex":0},"up":{"uv":[12.866667,11.400001,12.666667,10.566668],"rotation":0,"texture":"#0","tintindex":0},"west":{"uv":[11.066668,5.3333335,11.900001,6.166667],"rotation":0,"texture":"#0","tintindex":0}}},{"name":"cube","from":[-9.4096,24.222134,11.3696],"to":[-7.8184004,27.591736,11.9312],"rotation":{"angle":0.0,"axis":"x","origin":[4.256,21.835335,8.0]},"faces":{"down":{"uv":[14.166667,3.7000003,13.866667,3.8],"rotation":0,"texture":"#0","tintindex":0},"east":{"uv":[13.266666,1.3333334,13.366667,1.9666667],"rotation":0,"texture":"#0","tintindex":0},"north":{"uv":[6.633333,12.6,6.9333334,13.233334],"rotation":0,"texture":"#0","tintindex":0},"south":{"uv":[6.9333334,12.6,7.2333336,13.233334],"rotation":0,"texture":"#0","tintindex":0},"up":{"uv":[14.133334,8.5,13.833334,8.400001],"rotation":0,"texture":"#0","tintindex":0},"west":{"uv":[13.266666,7.633333,13.366667,8.266666],"rotation":0,"texture":"#0","tintindex":0}}},{"name":"cube","from":[-7.8184004,23.660534,11.9312],"to":[-4.7296004,28.153336,12.4928],"rotation":{"angle":0.0,"axis":"x","origin":[3.7879996,21.835335,8.0]},"faces":{"down":{"uv":[13.933333,10.666667,13.366667,10.766666],"rotation":0,"texture":"#0","tintindex":0},"east":{"uv":[13.2,0.0,13.300001,0.8333334],"rotation":0,"texture":"#0","tintindex":0},"north":{"uv":[7.533334,11.333334,8.1,12.166667],"rotation":0,"texture":"#0","tintindex":0},"south":{"uv":[11.5,6.166667,12.066668,7.0],"rotation":0,"texture":"#0","tintindex":0},"up":{"uv":[13.933333,1.9333334,13.366667,1.8333334],"rotation":0,"texture":"#0","tintindex":0},"west":{"uv":[8.666667,13.2,8.766666,14.033333],"rotation":0,"texture":"#0","tintindex":0}}},{"name":"cube","from":[-4.7296004,23.098934,12.4928],"to":[-0.14320016,28.714935,13.0544],"rotation":{"angle":0.0,"axis":"x","origin":[5.66,21.835335,8.0]},"faces":{"down":{"uv":[13.900001,11.6,13.066668,11.7],"rotation":0,"texture":"#0","tintindex":0},"east":{"uv":[12.533333,12.966667,12.633334,14.0],"rotation":0,"texture":"#0","tintindex":0},"north":{"uv":[10.433333,0.8666667,11.266666,1.9],"rotation":0,"texture":"#0","tintindex":0},"south":{"uv":[2.3000002,10.433333,3.1333332,11.466667],"rotation":0,"texture":"#0","tintindex":0},"up":{"uv":[13.900001,11.6,13.066668,11.5],"rotation":0,"texture":"#0","tintindex":0},"west":{"uv":[12.633334,12.966667,12.733334,14.0],"rotation":0,"texture":"#0","tintindex":0}}},{"name":"cube","from":[-9.4096,25.345333,11.9312],"to":[-7.8184004,26.468536,12.4928],"rotation":{"angle":0.0,"axis":"x","origin":[4.256,21.835335,8.0]},"faces":{"down":{"uv":[14.166667,8.1,13.866667,8.200001],"rotation":0,"texture":"#0","tintindex":0},"east":{"uv":[1.1333334,10.200001,1.2333333,10.400001],"rotation":0,"texture":"#0","tintindex":0},"north":{"uv":[0.8333334,10.200001,1.1333334,10.400001],"rotation":0,"texture":"#0","tintindex":0},"south":{"uv":[10.833334,11.6,11.133334,11.800001],"rotation":0,"texture":"#0","tintindex":0},"up":{"uv":[14.166667,8.1,13.866667,8.0],"rotation":0,"texture":"#0","tintindex":0},"west":{"uv":[7.4333334,11.966667,7.533334,12.166667],"rotation":0,"texture":"#0","tintindex":0}}},{"name":"cube","from":[-7.8184004,24.783733,12.4928],"to":[-4.7296004,27.030136,13.0544],"rotation":{"angle":0.0,"axis":"x","origin":[3.7879996,21.835335,8.0]},"faces":{"down":{"uv":[13.933333,10.866667,13.366667,10.966667],"rotation":0,"texture":"#0","tintindex":0},"east":{"uv":[10.466667,13.533333,10.566668,13.933333],"rotation":0,"texture":"#0","tintindex":0},"north":{"uv":[12.533333,3.4,13.1,3.8],"rotation":0,"texture":"#0","tintindex":0},"south":{"uv":[12.533333,5.1000004,13.1,5.5],"rotation":0,"texture":"#0","tintindex":0},"up":{"uv":[13.933333,10.866667,13.366667,10.766666],"rotation":0,"texture":"#0","tintindex":0},"west":{"uv":[10.566668,13.533333,10.666667,13.933333],"rotation":0,"texture":"#0","tintindex":0}}},{"name":"cube","from":[-4.7296004,24.222134,13.0544],"to":[-0.14320016,27.591736,13.616],"rotation":{"angle":0.0,"axis":"x","origin":[5.66,21.835335,8.0]},"faces":{"down":{"uv":[13.900001,12.1,13.066668,12.2],"rotation":0,"texture":"#0","tintindex":0},"east":{"uv":[13.300001,0.0,13.400001,0.6333333],"rotation":0,"texture":"#0","tintindex":0},"north":{"uv":[11.266666,1.2333333,12.1,1.8666667],"rotation":0,"texture":"#0","tintindex":0},"south":{"uv":[6.7000003,11.333334,7.533334,11.966667],"rotation":0,"texture":"#0","tintindex":0},"up":{"uv":[13.900001,11.800001,13.066668,11.7],"rotation":0,"texture":"#0","tintindex":0},"west":{"uv":[4.5,13.300001,4.6000004,13.933333],"rotation":0,"texture":"#0","tintindex":0}}},{"name":"cube","from":[-4.7296004,22.537334,11.9312],"to":[-0.14320016,29.276535,12.4928],"rotation":{"angle":0.0,"axis":"x","origin":[5.66,21.835335,8.0]},"faces":{"down":{"uv":[13.900001,12.300001,13.066668,12.400001],"rotation":0,"texture":"#0","tintindex":0},"east":{"uv":[7.666667,4.766667,7.7666664,6.0],"rotation":0,"texture":"#0","tintindex":0},"north":{"uv":[5.8,10.1,6.633333,11.333334],"rotation":0,"texture":"#0","tintindex":0},"south":{"uv":[6.633333,10.1,7.4666667,11.333334],"rotation":0,"texture":"#0","tintindex":0},"up":{"uv":[13.900001,12.300001,13.066668,12.2],"rotation":0,"texture":"#0","tintindex":0},"west":{"uv":[4.4,12.533333,4.5,13.766666],"rotation":0,"texture":"#0","tintindex":0}}},{"name":"cube","from":[-10.439201,24.222134,10.2464],"to":[-9.4096,27.591736,10.808001],"rotation":{"angle":0.0,"axis":"x","origin":[2.8519998,21.835335,8.0]},"faces":{"down":{"uv":[14.133334,4.8,13.933333,4.9],"rotation":0,"texture":"#0","tintindex":0},"east":{"uv":[4.6000004,13.300001,4.7000003,13.933333],"rotation":0,"texture":"#0","tintindex":0},"north":{"uv":[1.0,12.7,1.2,13.333334],"rotation":0,"texture":"#0","tintindex":0},"south":{"uv":[1.2,12.7,1.4,13.333334],"rotation":0,"texture":"#0","tintindex":0},"up":{"uv":[10.266666,12.433333,10.066668,12.333334],"rotation":0,"texture":"#0","tintindex":0},"west":{"uv":[4.7000003,13.300001,4.8,13.933333],"rotation":0,"texture":"#0","tintindex":0}}},{"name":"cube","from":[-10.439201,24.783733,10.808001],"to":[-9.4096,27.030136,11.3696],"rotation":{"angle":0.0,"axis":"x","origin":[2.8519998,21.835335,8.0]},"faces":{"down":{"uv":[14.133334,5.8,13.933333,5.9000006],"rotation":0,"texture":"#0","tintindex":0},"east":{"uv":[13.566668,7.6,13.666667,8.0],"rotation":0,"texture":"#0","tintindex":0},"north":{"uv":[9.6,2.7000003,9.8,3.1000001],"rotation":0,"texture":"#0","tintindex":0},"south":{"uv":[11.5,7.8333335,11.7,8.233334],"rotation":0,"texture":"#0","tintindex":0},"up":{"uv":[5.7666664,14.033333,5.566667,13.933333],"rotation":0,"texture":"#0","tintindex":0},"west":{"uv":[7.8333335,13.566668,7.9333334,13.966667],"rotation":0,"texture":"#0","tintindex":0}}},{"name":"cube","from":[-11.0008,24.222134,6.3152],"to":[-10.439201,27.591736,9.684801],"rotation":{"angle":0.0,"axis":"x","origin":[3.3199997,21.835335,8.0]},"faces":{"down":{"uv":[10.933333,13.300001,10.833334,13.933333],"rotation":0,"texture":"#0","tintindex":0},"east":{"uv":[11.733334,11.1,12.366667,11.733334],"rotation":0,"texture":"#0","tintindex":0},"north":{"uv":[4.8,13.300001,4.9,13.933333],"rotation":0,"texture":"#0","tintindex":0},"south":{"uv":[4.9,13.300001,5.0,13.933333],"rotation":0,"texture":"#0","tintindex":0},"up":{"uv":[5.1000004,13.933333,5.0,13.300001],"rotation":0,"texture":"#0","tintindex":0},"west":{"uv":[11.733334,11.733334,12.366667,12.366667],"rotation":0,"texture":"#0","tintindex":0}}},{"name":"cube","from":[-11.0008,24.783733,9.684801],"to":[-10.439201,27.030136,10.2464],"rotation":{"angle":0.0,"axis":"x","origin":[3.3199997,21.835335,8.0]},"faces":{"down":{"uv":[14.1,14.0,14.0,14.1],"rotation":0,"texture":"#0","tintindex":0},"east":{"uv":[13.566668,8.0,13.666667,8.400001],"rotation":0,"texture":"#0","tintindex":0},"north":{"uv":[7.9333334,13.566668,8.033334,13.966667],"rotation":0,"texture":"#0","tintindex":0},"south":{"uv":[9.166667,13.566668,9.266666,13.966667],"rotation":0,"texture":"#0","tintindex":0},"up":{"uv":[14.0,14.1,13.900001,14.0],"rotation":0,"texture":"#0","tintindex":0},"west":{"uv":[9.266666,13.566668,9.366667,13.966667],"rotation":0,"texture":"#0","tintindex":0}}},{"name":"cube","from":[-0.14320016,24.783733,13.616],"to":[0.4183998,27.030136,14.1776],"rotation":{"angle":0.0,"axis":"x","origin":[8.0,21.835335,8.0]},"faces":{"down":{"uv":[2.4,14.033333,2.3000002,14.133334],"rotation":0,"texture":"#0","tintindex":0},"east":{"uv":[10.666667,13.566668,10.766666,13.966667],"rotation":0,"texture":"#0","tintindex":0},"north":{"uv":[9.366667,13.566668,9.466667,13.966667],"rotation":0,"texture":"#0","tintindex":0},"south":{"uv":[11.133334,13.566668,11.233334,13.966667],"rotation":0,"texture":"#0","tintindex":0},"up":{"uv":[2.3000002,14.133334,2.2,14.033333],"rotation":0,"texture":"#0","tintindex":0},"west":{"uv":[11.233334,13.566668,11.333334,13.966667],"rotation":0,"texture":"#0","tintindex":0}}},{"name":"cube","from":[14.4584,24.783733,13.616],"to":[15.02,27.030136,14.1776],"rotation":{"angle":0.0,"axis":"x","origin":[8.0,21.835335,8.0]},"faces":{"down":{"uv":[14.133334,3.0,14.033333,3.1000001],"rotation":0,"texture":"#0","tintindex":0},"east":{"uv":[8.5,13.6,8.6,14.0],"rotation":0,"texture":"#0","tintindex":0},"north":{"uv":[13.6,5.1000004,13.7,5.5],"rotation":0,"texture":"#0","tintindex":0},"south":{"uv":[12.933333,13.6,13.033333,14.0],"rotation":0,"texture":"#0","tintindex":0},"up":{"uv":[14.133334,3.0,14.033333,2.9],"rotation":0,"texture":"#0","tintindex":0},"west":{"uv":[13.333334,13.6,13.433333,14.0],"rotation":0,"texture":"#0","tintindex":0}}},{"name":"cube","from":[25.316002,24.690132,9.684801],"to":[25.877598,26.936535,10.2464],"rotation":{"angle":0.0,"axis":"x","origin":[11.556801,29.884937,8.0]},"faces":{"down":{"uv":[14.133334,6.5,14.033333,6.6],"rotation":0,"texture":"#0","tintindex":0},"east":{"uv":[2.1000001,13.666667,2.2,14.066668],"rotation":0,"texture":"#0","tintindex":0},"north":{"uv":[3.5666666,13.633334,3.6666667,14.033333],"rotation":0,"texture":"#0","tintindex":0},"south":{"uv":[11.666667,13.7,11.766666,14.1],"rotation":0,"texture":"#0","tintindex":0},"up":{"uv":[14.133334,6.5,14.033333,6.4000006],"rotation":0,"texture":"#0","tintindex":0},"west":{"uv":[5.7666664,13.733334,5.866667,14.133334],"rotation":0,"texture":"#0","tintindex":0}}},{"name":"cube","from":[25.316002,24.128532,6.3152],"to":[25.877598,27.498135,9.684801],"rotation":{"angle":0.0,"axis":"x","origin":[11.556801,29.884937,8.0]},"faces":{"down":{"uv":[1.1,13.333334,1.0,13.966667],"rotation":0,"texture":"#0","tintindex":0},"east":{"uv":[0.0,12.066668,0.6333333,12.7],"rotation":0,"texture":"#0","tintindex":0},"north":{"uv":[10.933333,13.300001,11.033333,13.933333],"rotation":0,"texture":"#0","tintindex":0},"south":{"uv":[11.033333,13.300001,11.133334,13.933333],"rotation":0,"texture":"#0","tintindex":0},"up":{"uv":[13.333334,13.933333,13.233334,13.300001],"rotation":0,"texture":"#0","tintindex":0},"west":{"uv":[12.066668,5.8,12.7,6.4333334],"rotation":0,"texture":"#0","tintindex":0}}},{"name":"cube","from":[24.2864,24.690132,10.808001],"to":[25.316002,26.936535,11.3696],"rotation":{"angle":0.0,"axis":"x","origin":[12.0248,29.884937,8.0]},"faces":{"down":{"uv":[14.133334,7.4333334,13.933333,7.533334],"rotation":0,"texture":"#0","tintindex":0},"east":{"uv":[4.366667,13.766666,4.4666667,14.166667],"rotation":0,"texture":"#0","tintindex":0},"north":{"uv":[13.1,5.1000004,13.300001,5.5],"rotation":0,"texture":"#0","tintindex":0},"south":{"uv":[13.166667,4.1000004,13.366667,4.5],"rotation":0,"texture":"#0","tintindex":0},"up":{"uv":[14.133334,6.0,13.933333,5.9000006],"rotation":0,"texture":"#0","tintindex":0},"west":{"uv":[6.5,13.766666,6.6,14.166667],"rotation":0,"texture":"#0","tintindex":0}}},{"name":"cube","from":[24.2864,24.128532,10.2464],"to":[25.316002,27.498135,10.808001],"rotation":{"angle":0.0,"axis":"x","origin":[12.0248,29.884937,8.0]},"faces":{"down":{"uv":[14.133334,13.2,13.933333,13.300001],"rotation":0,"texture":"#0","tintindex":0},"east":{"uv":[1.1,13.333334,1.2,13.966667],"rotation":0,"texture":"#0","tintindex":0},"north":{"uv":[12.800001,4.1000004,13.0,4.7333336],"rotation":0,"texture":"#0","tintindex":0},"south":{"uv":[11.666667,12.800001,11.866667,13.433333],"rotation":0,"texture":"#0","tintindex":0},"up":{"uv":[14.133334,11.466667,13.933333,11.366667],"rotation":0,"texture":"#0","tintindex":0},"west":{"uv":[1.2,13.333334,1.3000001,13.966667],"rotation":0,"texture":"#0","tintindex":0}}},{"name":"cube","from":[15.02,22.443733,11.9312],"to":[19.6064,29.182938,12.4928],"rotation":{"angle":0.0,"axis":"x","origin":[9.216801,29.884937,8.0]},"faces":{"down":{"uv":[13.933333,0.8666667,13.1,0.9666667],"rotation":0,"texture":"#0","tintindex":0},"east":{"uv":[7.2333336,12.6,7.3333335,13.833334],"rotation":0,"texture":"#0","tintindex":0},"north":{"uv":[7.4666667,10.1,8.3,11.333334],"rotation":0,"texture":"#0","tintindex":0},"south":{"uv":[0.0,10.200001,0.8333334,11.433333],"rotation":0,"texture":"#0","tintindex":0},"up":{"uv":[13.900001,12.5,13.066668,12.400001],"rotation":0,"texture":"#0","tintindex":0},"west":{"uv":[1.4,12.7,1.5,13.933333],"rotation":0,"texture":"#0","tintindex":0}}},{"name":"cube","from":[15.02,24.128532,13.0544],"to":[19.6064,27.498135,13.616],"rotation":{"angle":0.0,"axis":"x","origin":[9.216801,29.884937,8.0]},"faces":{"down":{"uv":[13.933333,3.4,13.1,3.5],"rotation":0,"texture":"#0","tintindex":0},"east":{"uv":[1.3000001,13.333334,1.4,13.966667],"rotation":0,"texture":"#0","tintindex":0},"north":{"uv":[0.0,11.433333,0.8333334,12.066668],"rotation":0,"texture":"#0","tintindex":0},"south":{"uv":[1.9666667,11.466667,2.8,12.1],"rotation":0,"texture":"#0","tintindex":0},"up":{"uv":[13.933333,1.0666667,13.1,0.9666667],"rotation":0,"texture":"#0","tintindex":0},"west":{"uv":[2.6666667,13.333334,2.766667,13.966667],"rotation":0,"texture":"#0","tintindex":0}}},{"name":"cube","from":[19.6064,24.690132,12.4928],"to":[22.695202,26.936535,13.0544],"rotation":{"angle":0.0,"axis":"x","origin":[11.0888,29.884937,8.0]},"faces":{"down":{"uv":[13.933333,12.5,13.366667,12.6],"rotation":0,"texture":"#0","tintindex":0},"east":{"uv":[13.800001,9.366667,13.900001,9.766666],"rotation":0,"texture":"#0","tintindex":0},"north":{"uv":[12.366667,12.566668,12.933333,12.966667],"rotation":0,"texture":"#0","tintindex":0},"south":{"uv":[12.6,6.4333334,13.166667,6.8333335],"rotation":0,"texture":"#0","tintindex":0},"up":{"uv":[13.933333,11.066668,13.366667,10.966667],"rotation":0,"texture":"#0","tintindex":0},"west":{"uv":[13.433333,13.800001,13.533333,14.2],"rotation":0,"texture":"#0","tintindex":0}}},{"name":"cube","from":[22.695202,25.251736,11.9312],"to":[24.2864,26.374935,12.4928],"rotation":{"angle":0.0,"axis":"x","origin":[10.6208,29.884937,8.0]},"faces":{"down":{"uv":[14.166667,8.3,13.866667,8.400001],"rotation":0,"texture":"#0","tintindex":0},"east":{"uv":[13.966667,7.2000003,14.066668,7.4000006],"rotation":0,"texture":"#0","tintindex":0},"north":{"uv":[13.300001,5.1000004,13.6,5.3],"rotation":0,"texture":"#0","tintindex":0},"south":{"uv":[13.300001,5.3,13.6,5.5],"rotation":0,"texture":"#0","tintindex":0},"up":{"uv":[14.166667,8.3,13.866667,8.200001],"rotation":0,"texture":"#0","tintindex":0},"west":{"uv":[7.8333335,13.966667,7.9333334,14.166667],"rotation":0,"texture":"#0","tintindex":0}}},{"name":"cube","from":[15.02,23.005333,12.4928],"to":[19.6064,28.621334,13.0544],"rotation":{"angle":0.0,"axis":"x","origin":[9.216801,29.884937,8.0]},"faces":{"down":{"uv":[13.933333,3.6000001,13.1,3.7000003],"rotation":0,"texture":"#0","tintindex":0},"east":{"uv":[12.733334,12.966667,12.833334,14.0],"rotation":0,"texture":"#0","tintindex":0},"north":{"uv":[10.333334,10.566668,11.166667,11.6],"rotation":0,"texture":"#0","tintindex":0},"south":{"uv":[3.1333332,10.6,3.9666667,11.633334],"rotation":0,"texture":"#0","tintindex":0},"up":{"uv":[13.933333,3.6000001,13.1,3.5],"rotation":0,"texture":"#0","tintindex":0},"west":{"uv":[12.833334,12.966667,12.933333,14.0],"rotation":0,"texture":"#0","tintindex":0}}},{"name":"cube","from":[19.6064,23.566936,11.9312],"to":[22.695202,28.059734,12.4928],"rotation":{"angle":0.0,"axis":"x","origin":[11.0888,29.884937,8.0]},"faces":{"down":{"uv":[13.933333,12.7,13.366667,12.800001],"rotation":0,"texture":"#0","tintindex":0},"east":{"uv":[8.766666,13.2,8.866667,14.033333],"rotation":0,"texture":"#0","tintindex":0},"north":{"uv":[11.5,7.0,12.066668,7.8333335],"rotation":0,"texture":"#0","tintindex":0},"south":{"uv":[10.266666,11.6,10.833334,12.433333],"rotation":0,"texture":"#0","tintindex":0},"up":{"uv":[13.933333,12.7,13.366667,12.6],"rotation":0,"texture":"#0","tintindex":0},"west":{"uv":[8.866667,13.2,8.966667,14.033333],"rotation":0,"texture":"#0","tintindex":0}}},{"name":"cube","from":[22.695202,24.128532,11.3696],"to":[24.2864,27.498135,11.9312],"rotation":{"angle":0.0,"axis":"x","origin":[10.6208,29.884937,8.0]},"faces":{"down":{"uv":[14.166667,8.966667,13.866667,9.066668],"rotation":0,"texture":"#0","tintindex":0},"east":{"uv":[2.766667,13.333334,2.8666668,13.966667],"rotation":0,"texture":"#0","tintindex":0},"north":{"uv":[12.633334,0.6,12.933333,1.2333333],"rotation":0,"texture":"#0","tintindex":0},"south":{"uv":[12.633334,1.8000001,12.933333,2.4333334],"rotation":0,"texture":"#0","tintindex":0},"up":{"uv":[14.166667,8.6,13.866667,8.5],"rotation":0,"texture":"#0","tintindex":0},"west":{"uv":[2.8666668,13.333334,2.9666667,13.966667],"rotation":0,"texture":"#0","tintindex":0}}},{"name":"cube","from":[24.2864,23.566936,5.7536],"to":[25.316002,26.799736,10.2464],"rotation":{"angle":0.0,"axis":"x","origin":[12.0248,29.884937,8.0]},"faces":{"down":{"uv":[1.0,12.7,0.8000001,13.533333],"rotation":0,"texture":"#0","tintindex":0},"east":{"uv":[11.166667,2.4333334,12.0,3.266667],"rotation":0,"texture":"#0","tintindex":0},"north":{"uv":[0.20000002,12.7,0.40000004,13.533333],"rotation":0,"texture":"#0","tintindex":0},"south":{"uv":[0.40000004,12.7,0.6,13.533333],"rotation":0,"texture":"#0","tintindex":0},"up":{"uv":[0.8000001,13.533333,0.6,12.7],"rotation":0,"texture":"#0","tintindex":0},"west":{"uv":[8.3,11.300001,9.133333,12.133334],"rotation":0,"texture":"#0","tintindex":0}}},{"name":"cube","from":[19.6064,23.005333,11.3696],"to":[22.695202,28.621334,11.9312],"rotation":{"angle":0.0,"axis":"x","origin":[11.0888,29.884937,8.0]},"faces":{"down":{"uv":[13.966667,0.0,13.400001,0.10000001],"rotation":0,"texture":"#0","tintindex":0},"east":{"uv":[8.3,13.0,8.400001,14.033333],"rotation":0,"texture":"#0","tintindex":0},"north":{"uv":[5.566667,11.333334,6.133333,12.366667],"rotation":0,"texture":"#0","tintindex":0},"south":{"uv":[6.133333,11.333334,6.7000003,12.366667],"rotation":0,"texture":"#0","tintindex":0},"up":{"uv":[13.933333,12.900001,13.366667,12.800001],"rotation":0,"texture":"#0","tintindex":0},"west":{"uv":[8.400001,13.0,8.5,14.033333],"rotation":0,"texture":"#0","tintindex":0}}},{"name":"cube","from":[22.695202,23.566936,10.808001],"to":[24.2864,28.059734,11.3696],"rotation":{"angle":0.0,"axis":"x","origin":[10.6208,29.884937,8.0]},"faces":{"down":{"uv":[9.766666,13.866667,9.466667,13.966667],"rotation":0,"texture":"#0","tintindex":0},"east":{"uv":[8.966667,13.2,9.066668,14.033333],"rotation":0,"texture":"#0","tintindex":0},"north":{"uv":[4.8333335,12.466667,5.133333,13.300001],"rotation":0,"texture":"#0","tintindex":0},"south":{"uv":[12.5,4.1000004,12.800001,4.9333334],"rotation":0,"texture":"#0","tintindex":0},"up":{"uv":[14.166667,9.366667,13.866667,9.266666],"rotation":0,"texture":"#0","tintindex":0},"west":{"uv":[9.066668,13.2,9.166667,14.033333],"rotation":0,"texture":"#0","tintindex":0}}},{"name":"cube","from":[22.695202,23.005333,5.192],"to":[24.2864,27.361336,10.808001],"rotation":{"angle":0.0,"axis":"x","origin":[10.6208,29.884937,8.0]},"faces":{"down":{"uv":[12.666667,11.1,12.366667,12.133334],"rotation":0,"texture":"#0","tintindex":0},"east":{"uv":[10.033334,4.366667,11.066668,5.4000006],"rotation":0,"texture":"#0","tintindex":0},"north":{"uv":[5.566667,12.366667,5.866667,13.400001],"rotation":0,"texture":"#0","tintindex":0},"south":{"uv":[5.866667,12.366667,6.166667,13.400001],"rotation":0,"texture":"#0","tintindex":0},"up":{"uv":[6.4666667,13.400001,6.166667,12.366667],"rotation":0,"texture":"#0","tintindex":0},"west":{"uv":[10.033334,5.4000006,11.066668,6.4333334],"rotation":0,"texture":"#0","tintindex":0}}},{"name":"cube","from":[19.6064,22.443733,4.6303997],"to":[22.695202,27.922935,11.3696],"rotation":{"angle":0.0,"axis":"x","origin":[11.0888,29.884937,8.0]},"faces":{"down":{"uv":[4.533334,11.300001,3.9666667,12.533333],"rotation":0,"texture":"#0","tintindex":0},"east":{"uv":[8.666667,8.6,9.900001,9.833334],"rotation":0,"texture":"#0","tintindex":0},"north":{"uv":[11.066668,4.1000004,11.633334,5.3333335],"rotation":0,"texture":"#0","tintindex":0},"south":{"uv":[11.166667,10.566668,11.733334,11.800001],"rotation":0,"texture":"#0","tintindex":0},"up":{"uv":[11.833334,1.2333333,11.266666,0.0],"rotation":0,"texture":"#0","tintindex":0},"west":{"uv":[0.0,8.966667,1.2333333,10.200001],"rotation":0,"texture":"#0","tintindex":0}}},{"name":"cube","from":[15.02,21.882137,4.0688],"to":[19.6064,28.484535,11.9312],"rotation":{"angle":0.0,"axis":"x","origin":[9.216801,29.884937,8.0]},"faces":{"down":{"uv":[10.333334,9.833334,9.5,11.300001],"rotation":0,"texture":"#0","tintindex":0},"east":{"uv":[2.9333334,7.666667,4.4,9.133333],"rotation":0,"texture":"#0","tintindex":0},"north":{"uv":[9.200001,5.8333335,10.033334,7.3],"rotation":0,"texture":"#0","tintindex":0},"south":{"uv":[9.6,1.2333333,10.433333,2.7000003],"rotation":0,"texture":"#0","tintindex":0},"up":{"uv":[9.5,11.300001,8.666667,9.833334],"rotation":0,"texture":"#0","tintindex":0},"west":{"uv":[4.4,7.666667,5.866667,9.133333],"rotation":0,"texture":"#0","tintindex":0}}},{"name":"cube","from":[-0.14320016,20.298012,5.1865377],"to":[15.02,20.859612,10.802538],"rotation":{"angle":0.0,"axis":"x","origin":[8.0,25.914013,3.9229376]},"faces":{"down":{"uv":[5.6,1.0333333,8.400001,2.0666666],"rotation":0,"texture":"#0","tintindex":0},"east":{"uv":[12.933333,12.566668,13.033333,13.6],"rotation":270,"texture":"#0","tintindex":0},"north":{"uv":[14.7,4.0,11.900001,4.1000004],"rotation":180,"texture":"#0","tintindex":0},"south":{"uv":[14.7,4.0,11.900001,3.9],"rotation":0,"texture":"#0","tintindex":0},"up":{"uv":[5.6,0.0,8.400001,1.0333333],"rotation":180,"texture":"#0","tintindex":0},"west":{"uv":[12.966667,1.3333334,13.066668,2.3666668],"rotation":90,"texture":"#0","tintindex":0}}},{"name":"cube","from":[-0.14320016,20.859612,4.063338],"to":[15.02,21.421207,11.925738],"rotation":{"angle":0.0,"axis":"x","origin":[8.0,25.914013,3.9229376]},"faces":{"down":{"uv":[2.8,3.3333335,5.6,4.8],"rotation":0,"texture":"#0","tintindex":0},"east":{"uv":[3.5666666,12.166667,3.6666667,13.633334],"rotation":270,"texture":"#0","tintindex":0},"north":{"uv":[14.6,10.466667,11.800001,10.566668],"rotation":180,"texture":"#0","tintindex":0},"south":{"uv":[14.6,10.466667,11.800001,10.366667],"rotation":0,"texture":"#0","tintindex":0},"up":{"uv":[0.0,3.3333335,2.8,4.8],"rotation":180,"texture":"#0","tintindex":0},"west":{"uv":[11.366667,12.433333,11.466667,13.900001],"rotation":90,"texture":"#0","tintindex":0}}},{"name":"cube","from":[0.4183998,19.736408,6.309738],"to":[14.4584,20.298012,9.679338],"rotation":{"angle":0.0,"axis":"x","origin":[8.0,25.914013,3.9229376]},"faces":{"down":{"uv":[7.9333334,3.7333333,10.533334,4.366667],"rotation":0,"texture":"#0","tintindex":0},"east":{"uv":[12.033333,13.2,12.133334,13.833334],"rotation":270,"texture":"#0","tintindex":0},"north":{"uv":[15.033333,9.833334,12.433333,9.933333],"rotation":180,"texture":"#0","tintindex":0},"south":{"uv":[14.6,3.2333333,12.0,3.1333332],"rotation":0,"texture":"#0","tintindex":0},"up":{"uv":[7.2666664,3.1000001,9.866667,3.7333333],"rotation":180,"texture":"#0","tintindex":0},"west":{"uv":[7.066667,13.233334,7.166667,13.866667],"rotation":90,"texture":"#0","tintindex":0}}},{"name":"cube","from":[-9.4096,22.54441,5.748138],"to":[-7.8184004,23.10601,10.240938],"rotation":{"angle":0.0,"axis":"x","origin":[4.256,25.914013,3.9229376]},"faces":{"down":{"uv":[4.533334,12.466667,4.8333335,13.300001],"rotation":0,"texture":"#0","tintindex":0},"east":{"uv":[13.166667,1.3333334,13.266666,2.1666667],"rotation":270,"texture":"#0","tintindex":0},"north":{"uv":[14.1,1.0666667,13.800001,1.1666667],"rotation":180,"texture":"#0","tintindex":0},"south":{"uv":[14.066668,13.0,13.766666,12.900001],"rotation":0,"texture":"#0","tintindex":0},"up":{"uv":[10.933333,0.0,11.233334,0.8333334],"rotation":180,"texture":"#0","tintindex":0},"west":{"uv":[13.166667,7.7000003,13.266666,8.533334],"rotation":90,"texture":"#0","tintindex":0}}},{"name":"cube","from":[-7.8184004,21.982811,5.1865377],"to":[-4.7296004,22.54441,10.802538],"rotation":{"angle":0.0,"axis":"x","origin":[3.7879996,25.914013,3.9229376]},"faces":{"down":{"uv":[9.700001,11.300001,10.266666,12.333334],"rotation":0,"texture":"#0","tintindex":0},"east":{"uv":[12.333334,12.966667,12.433333,14.0],"rotation":270,"texture":"#0","tintindex":0},"north":{"uv":[13.866667,9.266666,13.300001,9.366667],"rotation":180,"texture":"#0","tintindex":0},"south":{"uv":[13.833334,8.566668,13.266666,8.466667],"rotation":0,"texture":"#0","tintindex":0},"up":{"uv":[9.133333,11.300001,9.700001,12.333334],"rotation":180,"texture":"#0","tintindex":0},"west":{"uv":[12.433333,12.966667,12.533333,14.0],"rotation":90,"texture":"#0","tintindex":0}}},{"name":"cube","from":[-9.4096,21.982811,6.309738],"to":[-7.8184004,22.54441,9.679338],"rotation":{"angle":0.0,"axis":"x","origin":[4.256,25.914013,3.9229376]},"faces":{"down":{"uv":[6.9333334,12.6,7.2333336,13.233334],"rotation":0,"texture":"#0","tintindex":0},"east":{"uv":[13.266666,1.3333334,13.366667,1.9666667],"rotation":270,"texture":"#0","tintindex":0},"north":{"uv":[14.166667,3.7000003,13.866667,3.8],"rotation":180,"texture":"#0","tintindex":0},"south":{"uv":[14.133334,8.5,13.833334,8.400001],"rotation":0,"texture":"#0","tintindex":0},"up":{"uv":[6.633333,12.6,6.9333334,13.233334],"rotation":180,"texture":"#0","tintindex":0},"west":{"uv":[13.266666,7.633333,13.366667,8.266666],"rotation":90,"texture":"#0","tintindex":0}}},{"name":"cube","from":[-7.8184004,21.421207,5.748138],"to":[-4.7296004,21.982811,10.240938],"rotation":{"angle":0.0,"axis":"x","origin":[3.7879996,25.914013,3.9229376]},"faces":{"down":{"uv":[11.5,6.166667,12.066668,7.0],"rotation":0,"texture":"#0","tintindex":0},"east":{"uv":[13.2,0.0,13.300001,0.8333334],"rotation":270,"texture":"#0","tintindex":0},"north":{"uv":[13.933333,10.666667,13.366667,10.766666],"rotation":180,"texture":"#0","tintindex":0},"south":{"uv":[13.933333,1.9333334,13.366667,1.8333334],"rotation":0,"texture":"#0","tintindex":0},"up":{"uv":[7.533334,11.333334,8.1,12.166667],"rotation":180,"texture":"#0","tintindex":0},"west":{"uv":[8.666667,13.2,8.766666,14.033333],"rotation":90,"texture":"#0","tintindex":0}}},{"name":"cube","from":[-4.7296004,20.859612,5.1865377],"to":[-0.14320016,21.421207,10.802538],"rotation":{"angle":0.0,"axis":"x","origin":[5.66,25.914013,3.9229376]},"faces":{"down":{"uv":[2.3000002,10.433333,3.1333332,11.466667],"rotation":0,"texture":"#0","tintindex":0},"east":{"uv":[12.533333,12.966667,12.633334,14.0],"rotation":270,"texture":"#0","tintindex":0},"north":{"uv":[13.900001,11.6,13.066668,11.7],"rotation":180,"texture":"#0","tintindex":0},"south":{"uv":[13.900001,11.6,13.066668,11.5],"rotation":0,"texture":"#0","tintindex":0},"up":{"uv":[10.433333,0.8666667,11.266666,1.9],"rotation":180,"texture":"#0","tintindex":0},"west":{"uv":[12.633334,12.966667,12.733334,14.0],"rotation":90,"texture":"#0","tintindex":0}}},{"name":"cube","from":[-9.4096,21.421207,7.4329376],"to":[-7.8184004,21.982811,8.556138],"rotation":{"angle":0.0,"axis":"x","origin":[4.256,25.914013,3.9229376]},"faces":{"down":{"uv":[10.833334,11.6,11.133334,11.800001],"rotation":0,"texture":"#0","tintindex":0},"east":{"uv":[1.1333334,10.200001,1.2333333,10.400001],"rotation":270,"texture":"#0","tintindex":0},"north":{"uv":[14.166667,8.1,13.866667,8.200001],"rotation":180,"texture":"#0","tintindex":0},"south":{"uv":[14.166667,8.1,13.866667,8.0],"rotation":0,"texture":"#0","tintindex":0},"up":{"uv":[0.8333334,10.200001,1.1333334,10.400001],"rotation":180,"texture":"#0","tintindex":0},"west":{"uv":[7.4333334,11.966667,7.533334,12.166667],"rotation":90,"texture":"#0","tintindex":0}}},{"name":"cube","from":[-7.8184004,20.859612,6.871338],"to":[-4.7296004,21.421207,9.117739],"rotation":{"angle":0.0,"axis":"x","origin":[3.7879996,25.914013,3.9229376]},"faces":{"down":{"uv":[12.533333,5.1000004,13.1,5.5],"rotation":0,"texture":"#0","tintindex":0},"east":{"uv":[10.466667,13.533333,10.566668,13.933333],"rotation":270,"texture":"#0","tintindex":0},"north":{"uv":[13.933333,10.866667,13.366667,10.966667],"rotation":180,"texture":"#0","tintindex":0},"south":{"uv":[13.933333,10.866667,13.366667,10.766666],"rotation":0,"texture":"#0","tintindex":0},"up":{"uv":[12.533333,3.4,13.1,3.8],"rotation":180,"texture":"#0","tintindex":0},"west":{"uv":[10.566668,13.533333,10.666667,13.933333],"rotation":90,"texture":"#0","tintindex":0}}},{"name":"cube","from":[-4.7296004,20.298012,6.309738],"to":[-0.14320016,20.859612,9.679338],"rotation":{"angle":0.0,"axis":"x","origin":[5.66,25.914013,3.9229376]},"faces":{"down":{"uv":[6.7000003,11.333334,7.533334,11.966667],"rotation":0,"texture":"#0","tintindex":0},"east":{"uv":[13.300001,0.0,13.400001,0.6333333],"rotation":270,"texture":"#0","tintindex":0},"north":{"uv":[13.900001,12.1,13.066668,12.2],"rotation":180,"texture":"#0","tintindex":0},"south":{"uv":[13.900001,11.800001,13.066668,11.7],"rotation":0,"texture":"#0","tintindex":0},"up":{"uv":[11.266666,1.2333333,12.1,1.8666667],"rotation":180,"texture":"#0","tintindex":0},"west":{"uv":[4.5,13.300001,4.6000004,13.933333],"rotation":90,"texture":"#0","tintindex":0}}},{"name":"cube","from":[-4.7296004,21.421207,4.624938],"to":[-0.14320016,21.982811,11.364138],"rotation":{"angle":0.0,"axis":"x","origin":[5.66,25.914013,3.9229376]},"faces":{"down":{"uv":[6.633333,10.1,7.4666667,11.333334],"rotation":0,"texture":"#0","tintindex":0},"east":{"uv":[7.666667,4.766667,7.7666664,6.0],"rotation":270,"texture":"#0","tintindex":0},"north":{"uv":[13.900001,12.300001,13.066668,12.400001],"rotation":180,"texture":"#0","tintindex":0},"south":{"uv":[13.900001,12.300001,13.066668,12.2],"rotation":0,"texture":"#0","tintindex":0},"up":{"uv":[5.8,10.1,6.633333,11.333334],"rotation":180,"texture":"#0","tintindex":0},"west":{"uv":[4.4,12.533333,4.5,13.766666],"rotation":90,"texture":"#0","tintindex":0}}},{"name":"cube","from":[-10.439201,23.10601,6.309738],"to":[-9.4096,23.66761,9.679338],"rotation":{"angle":0.0,"axis":"x","origin":[2.8519998,25.914013,3.9229376]},"faces":{"down":{"uv":[1.2,12.7,1.4,13.333334],"rotation":0,"texture":"#0","tintindex":0},"east":{"uv":[4.6000004,13.300001,4.7000003,13.933333],"rotation":270,"texture":"#0","tintindex":0},"north":{"uv":[14.133334,4.8,13.933333,4.9],"rotation":180,"texture":"#0","tintindex":0},"south":{"uv":[10.266666,12.433333,10.066668,12.333334],"rotation":0,"texture":"#0","tintindex":0},"up":{"uv":[1.0,12.7,1.2,13.333334],"rotation":180,"texture":"#0","tintindex":0},"west":{"uv":[4.7000003,13.300001,4.8,13.933333],"rotation":90,"texture":"#0","tintindex":0}}},{"name":"cube","from":[-10.439201,22.54441,6.871338],"to":[-9.4096,23.10601,9.117739],"rotation":{"angle":0.0,"axis":"x","origin":[2.8519998,25.914013,3.9229376]},"faces":{"down":{"uv":[11.5,7.8333335,11.7,8.233334],"rotation":0,"texture":"#0","tintindex":0},"east":{"uv":[13.566668,7.6,13.666667,8.0],"rotation":270,"texture":"#0","tintindex":0},"north":{"uv":[14.133334,5.8,13.933333,5.9000006],"rotation":180,"texture":"#0","tintindex":0},"south":{"uv":[5.7666664,14.033333,5.566667,13.933333],"rotation":0,"texture":"#0","tintindex":0},"up":{"uv":[9.6,2.7000003,9.8,3.1000001],"rotation":180,"texture":"#0","tintindex":0},"west":{"uv":[7.8333335,13.566668,7.9333334,13.966667],"rotation":90,"texture":"#0","tintindex":0}}},{"name":"cube","from":[-11.0008,23.66761,6.871338],"to":[-10.439201,24.22921,9.117739],"rotation":{"angle":0.0,"axis":"x","origin":[3.3199997,25.914013,3.9229376]},"faces":{"down":{"uv":[9.166667,13.566668,9.266666,13.966667],"rotation":0,"texture":"#0","tintindex":0},"east":{"uv":[13.566668,8.0,13.666667,8.400001],"rotation":270,"texture":"#0","tintindex":0},"north":{"uv":[14.1,14.0,14.0,14.1],"rotation":180,"texture":"#0","tintindex":0},"south":{"uv":[14.0,14.1,13.900001,14.0],"rotation":0,"texture":"#0","tintindex":0},"up":{"uv":[7.9333334,13.566668,8.033334,13.966667],"rotation":180,"texture":"#0","tintindex":0},"west":{"uv":[9.266666,13.566668,9.366667,13.966667],"rotation":90,"texture":"#0","tintindex":0}}},{"name":"cube","from":[22.695202,22.54441,5.654538],"to":[24.2864,23.10601,10.147338],"rotation":{"angle":0.0,"axis":"x","origin":[10.6208,25.914013,11.972538]},"faces":{"down":{"uv":[12.5,4.1000004,12.800001,4.9333334],"rotation":0,"texture":"#0","tintindex":0},"east":{"uv":[8.966667,13.2,9.066668,14.033333],"rotation":270,"texture":"#0","tintindex":0},"north":{"uv":[9.766666,13.866667,9.466667,13.966667],"rotation":180,"texture":"#0","tintindex":0},"south":{"uv":[14.166667,9.366667,13.866667,9.266666],"rotation":0,"texture":"#0","tintindex":0},"up":{"uv":[4.8333335,12.466667,5.133333,13.300001],"rotation":180,"texture":"#0","tintindex":0},"west":{"uv":[9.066668,13.2,9.166667,14.033333],"rotation":90,"texture":"#0","tintindex":0}}},{"name":"cube","from":[19.6064,21.982811,5.092938],"to":[22.695202,22.54441,10.708939],"rotation":{"angle":0.0,"axis":"x","origin":[11.0888,25.914013,11.972538]},"faces":{"down":{"uv":[6.133333,11.333334,6.7000003,12.366667],"rotation":0,"texture":"#0","tintindex":0},"east":{"uv":[8.3,13.0,8.400001,14.033333],"rotation":270,"texture":"#0","tintindex":0},"north":{"uv":[13.966667,0.0,13.400001,0.10000001],"rotation":180,"texture":"#0","tintindex":0},"south":{"uv":[13.933333,12.900001,13.366667,12.800001],"rotation":0,"texture":"#0","tintindex":0},"up":{"uv":[5.566667,11.333334,6.133333,12.366667],"rotation":180,"texture":"#0","tintindex":0},"west":{"uv":[8.400001,13.0,8.5,14.033333],"rotation":90,"texture":"#0","tintindex":0}}},{"name":"cube","from":[22.695202,21.982811,6.216138],"to":[24.2864,22.54441,9.585738],"rotation":{"angle":0.0,"axis":"x","origin":[10.6208,25.914013,11.972538]},"faces":{"down":{"uv":[12.633334,1.8000001,12.933333,2.4333334],"rotation":0,"texture":"#0","tintindex":0},"east":{"uv":[2.766667,13.333334,2.8666668,13.966667],"rotation":270,"texture":"#0","tintindex":0},"north":{"uv":[14.166667,8.966667,13.866667,9.066668],"rotation":180,"texture":"#0","tintindex":0},"south":{"uv":[14.166667,8.6,13.866667,8.5],"rotation":0,"texture":"#0","tintindex":0},"up":{"uv":[12.633334,0.6,12.933333,1.2333333],"rotation":180,"texture":"#0","tintindex":0},"west":{"uv":[2.8666668,13.333334,2.9666667,13.966667],"rotation":90,"texture":"#0","tintindex":0}}},{"name":"cube","from":[19.6064,21.421207,5.654538],"to":[22.695202,21.982811,10.147338],"rotation":{"angle":0.0,"axis":"x","origin":[11.0888,25.914013,11.972538]},"faces":{"down":{"uv":[10.266666,11.6,10.833334,12.433333],"rotation":0,"texture":"#0","tintindex":0},"east":{"uv":[8.766666,13.2,8.866667,14.033333],"rotation":270,"texture":"#0","tintindex":0},"north":{"uv":[13.933333,12.7,13.366667,12.800001],"rotation":180,"texture":"#0","tintindex":0},"south":{"uv":[13.933333,12.7,13.366667,12.6],"rotation":0,"texture":"#0","tintindex":0},"up":{"uv":[11.5,7.0,12.066668,7.8333335],"rotation":180,"texture":"#0","tintindex":0},"west":{"uv":[8.866667,13.2,8.966667,14.033333],"rotation":90,"texture":"#0","tintindex":0}}},{"name":"cube","from":[15.02,20.859612,5.092938],"to":[19.6064,21.421207,10.708939],"rotation":{"angle":0.0,"axis":"x","origin":[9.216801,25.914013,11.972538]},"faces":{"down":{"uv":[3.1333332,10.6,3.9666667,11.633334],"rotation":0,"texture":"#0","tintindex":0},"east":{"uv":[12.733334,12.966667,12.833334,14.0],"rotation":270,"texture":"#0","tintindex":0},"north":{"uv":[13.933333,3.6000001,13.1,3.7000003],"rotation":180,"texture":"#0","tintindex":0},"south":{"uv":[13.933333,3.6000001,13.1,3.5],"rotation":0,"texture":"#0","tintindex":0},"up":{"uv":[10.333334,10.566668,11.166667,11.6],"rotation":180,"texture":"#0","tintindex":0},"west":{"uv":[12.833334,12.966667,12.933333,14.0],"rotation":90,"texture":"#0","tintindex":0}}},{"name":"cube","from":[22.695202,21.421207,7.339338],"to":[24.2864,21.982811,8.462538],"rotation":{"angle":0.0,"axis":"x","origin":[10.6208,25.914013,11.972538]},"faces":{"down":{"uv":[13.300001,5.3,13.6,5.5],"rotation":0,"texture":"#0","tintindex":0},"east":{"uv":[13.966667,7.2000003,14.066668,7.4000006],"rotation":270,"texture":"#0","tintindex":0},"north":{"uv":[14.166667,8.3,13.866667,8.400001],"rotation":180,"texture":"#0","tintindex":0},"south":{"uv":[14.166667,8.3,13.866667,8.200001],"rotation":0,"texture":"#0","tintindex":0},"up":{"uv":[13.300001,5.1000004,13.6,5.3],"rotation":180,"texture":"#0","tintindex":0},"west":{"uv":[7.8333335,13.966667,7.9333334,14.166667],"rotation":90,"texture":"#0","tintindex":0}}},{"name":"cube","from":[19.6064,20.859612,6.7777376],"to":[22.695202,21.421207,9.0241375],"rotation":{"angle":0.0,"axis":"x","origin":[11.0888,25.914013,11.972538]},"faces":{"down":{"uv":[12.6,6.4333334,13.166667,6.8333335],"rotation":0,"texture":"#0","tintindex":0},"east":{"uv":[13.800001,9.366667,13.900001,9.766666],"rotation":270,"texture":"#0","tintindex":0},"north":{"uv":[13.933333,12.5,13.366667,12.6],"rotation":180,"texture":"#0","tintindex":0},"south":{"uv":[13.933333,11.066668,13.366667,10.966667],"rotation":0,"texture":"#0","tintindex":0},"up":{"uv":[12.366667,12.566668,12.933333,12.966667],"rotation":180,"texture":"#0","tintindex":0},"west":{"uv":[13.433333,13.800001,13.533333,14.2],"rotation":90,"texture":"#0","tintindex":0}}},{"name":"cube","from":[15.02,20.298012,6.216138],"to":[19.6064,20.859612,9.585738],"rotation":{"angle":0.0,"axis":"x","origin":[9.216801,25.914013,11.972538]},"faces":{"down":{"uv":[1.9666667,11.466667,2.8,12.1],"rotation":0,"texture":"#0","tintindex":0},"east":{"uv":[1.3000001,13.333334,1.4,13.966667],"rotation":270,"texture":"#0","tintindex":0},"north":{"uv":[13.933333,3.4,13.1,3.5],"rotation":180,"texture":"#0","tintindex":0},"south":{"uv":[13.933333,1.0666667,13.1,0.9666667],"rotation":0,"texture":"#0","tintindex":0},"up":{"uv":[0.0,11.433333,0.8333334,12.066668],"rotation":180,"texture":"#0","tintindex":0},"west":{"uv":[2.6666667,13.333334,2.766667,13.966667],"rotation":90,"texture":"#0","tintindex":0}}},{"name":"cube","from":[15.02,21.421207,4.5313377],"to":[19.6064,21.982811,11.270538],"rotation":{"angle":0.0,"axis":"x","origin":[9.216801,25.914013,11.972538]},"faces":{"down":{"uv":[0.0,10.200001,0.8333334,11.433333],"rotation":0,"texture":"#0","tintindex":0},"east":{"uv":[7.2333336,12.6,7.3333335,13.833334],"rotation":270,"texture":"#0","tintindex":0},"north":{"uv":[13.933333,0.8666667,13.1,0.9666667],"rotation":180,"texture":"#0","tintindex":0},"south":{"uv":[13.900001,12.5,13.066668,12.400001],"rotation":0,"texture":"#0","tintindex":0},"up":{"uv":[7.4666667,10.1,8.3,11.333334],"rotation":180,"texture":"#0","tintindex":0},"west":{"uv":[1.4,12.7,1.5,13.933333],"rotation":90,"texture":"#0","tintindex":0}}},{"name":"cube","from":[24.2864,23.10601,6.216138],"to":[25.316002,23.66761,9.585738],"rotation":{"angle":0.0,"axis":"x","origin":[12.0248,25.914013,11.972538]},"faces":{"down":{"uv":[11.666667,12.800001,11.866667,13.433333],"rotation":0,"texture":"#0","tintindex":0},"east":{"uv":[1.1,13.333334,1.2,13.966667],"rotation":270,"texture":"#0","tintindex":0},"north":{"uv":[14.133334,13.2,13.933333,13.300001],"rotation":180,"texture":"#0","tintindex":0},"south":{"uv":[14.133334,11.466667,13.933333,11.366667],"rotation":0,"texture":"#0","tintindex":0},"up":{"uv":[12.800001,4.1000004,13.0,4.7333336],"rotation":180,"texture":"#0","tintindex":0},"west":{"uv":[1.2,13.333334,1.3000001,13.966667],"rotation":90,"texture":"#0","tintindex":0}}},{"name":"cube","from":[24.2864,22.54441,6.7777376],"to":[25.316002,23.10601,9.0241375],"rotation":{"angle":0.0,"axis":"x","origin":[12.0248,25.914013,11.972538]},"faces":{"down":{"uv":[13.166667,4.1000004,13.366667,4.5],"rotation":0,"texture":"#0","tintindex":0},"east":{"uv":[4.366667,13.766666,4.4666667,14.166667],"rotation":270,"texture":"#0","tintindex":0},"north":{"uv":[14.133334,7.4333334,13.933333,7.533334],"rotation":180,"texture":"#0","tintindex":0},"south":{"uv":[14.133334,6.0,13.933333,5.9000006],"rotation":0,"texture":"#0","tintindex":0},"up":{"uv":[13.1,5.1000004,13.300001,5.5],"rotation":180,"texture":"#0","tintindex":0},"west":{"uv":[6.5,13.766666,6.6,14.166667],"rotation":90,"texture":"#0","tintindex":0}}},{"name":"cube","from":[25.316002,23.66761,6.7777376],"to":[25.877598,24.22921,9.0241375],"rotation":{"angle":0.0,"axis":"x","origin":[11.556801,25.914013,11.972538]},"faces":{"down":{"uv":[11.666667,13.7,11.766666,14.1],"rotation":0,"texture":"#0","tintindex":0},"east":{"uv":[2.1000001,13.666667,2.2,14.066668],"rotation":270,"texture":"#0","tintindex":0},"north":{"uv":[14.133334,6.5,14.033333,6.6],"rotation":180,"texture":"#0","tintindex":0},"south":{"uv":[14.133334,6.5,14.033333,6.4000006],"rotation":0,"texture":"#0","tintindex":0},"up":{"uv":[3.5666666,13.633334,3.6666667,14.033333],"rotation":180,"texture":"#0","tintindex":0},"west":{"uv":[5.7666664,13.733334,5.866667,14.133334],"rotation":90,"texture":"#0","tintindex":0}}},{"name":"cube","from":[-0.14320016,19.736408,6.871338],"to":[0.4183998,20.298012,9.117739],"rotation":{"angle":0.0,"axis":"x","origin":[8.0,25.914013,3.9229376]},"faces":{"down":{"uv":[11.133334,13.566668,11.233334,13.966667],"rotation":0,"texture":"#0","tintindex":0},"east":{"uv":[10.666667,13.566668,10.766666,13.966667],"rotation":270,"texture":"#0","tintindex":0},"north":{"uv":[2.4,14.033333,2.3000002,14.133334],"rotation":180,"texture":"#0","tintindex":0},"south":{"uv":[2.3000002,14.133334,2.2,14.033333],"rotation":0,"texture":"#0","tintindex":0},"up":{"uv":[9.366667,13.566668,9.466667,13.966667],"rotation":180,"texture":"#0","tintindex":0},"west":{"uv":[11.233334,13.566668,11.333334,13.966667],"rotation":90,"texture":"#0","tintindex":0}}},{"name":"cube","from":[14.4584,19.736408,6.871338],"to":[15.02,20.298012,9.117739],"rotation":{"angle":0.0,"axis":"x","origin":[8.0,25.914013,3.9229376]},"faces":{"down":{"uv":[12.933333,13.6,13.033333,14.0],"rotation":0,"texture":"#0","tintindex":0},"east":{"uv":[8.5,13.6,8.6,14.0],"rotation":270,"texture":"#0","tintindex":0},"north":{"uv":[14.133334,3.0,14.033333,3.1000001],"rotation":180,"texture":"#0","tintindex":0},"south":{"uv":[14.133334,3.0,14.033333,2.9],"rotation":0,"texture":"#0","tintindex":0},"up":{"uv":[13.6,5.1000004,13.7,5.5],"rotation":180,"texture":"#0","tintindex":0},"west":{"uv":[13.333334,13.6,13.433333,14.0],"rotation":90,"texture":"#0","tintindex":0}}},{"name":"cube","from":[-0.14320016,23.111473,2.4036136],"to":[15.02,28.727474,2.9652133],"rotation":{"angle":0.0,"axis":"x","origin":[8.0,29.991074,8.019614]},"faces":{"down":{"uv":[14.7,4.0,11.900001,3.9],"rotation":0,"texture":"#0","tintindex":0},"east":{"uv":[12.933333,12.566668,13.033333,13.6],"rotation":180,"texture":"#0","tintindex":0},"north":{"uv":[5.6,1.0333333,8.400001,2.0666666],"rotation":180,"texture":"#0","tintindex":0},"south":{"uv":[5.6,0.0,8.400001,1.0333333],"rotation":180,"texture":"#0","tintindex":0},"up":{"uv":[14.7,4.0,11.900001,4.1000004],"rotation":0,"texture":"#0","tintindex":0},"west":{"uv":[12.966667,1.3333334,13.066668,2.3666668],"rotation":180,"texture":"#0","tintindex":0}}},{"name":"cube","from":[-0.14320016,21.988274,2.9652133],"to":[15.02,29.850674,3.5268135],"rotation":{"angle":0.0,"axis":"x","origin":[8.0,29.991074,8.019614]},"faces":{"down":{"uv":[14.6,10.466667,11.800001,10.366667],"rotation":0,"texture":"#0","tintindex":0},"east":{"uv":[3.5666666,12.166667,3.6666667,13.633334],"rotation":180,"texture":"#0","tintindex":0},"north":{"uv":[2.8,3.3333335,5.6,4.8],"rotation":180,"texture":"#0","tintindex":0},"south":{"uv":[0.0,3.3333335,2.8,4.8],"rotation":180,"texture":"#0","tintindex":0},"up":{"uv":[14.6,10.466667,11.800001,10.566668],"rotation":0,"texture":"#0","tintindex":0},"west":{"uv":[11.366667,12.433333,11.466667,13.900001],"rotation":180,"texture":"#0","tintindex":0}}},{"name":"cube","from":[0.4183998,24.234673,1.8420135],"to":[14.4584,27.604275,2.4036136],"rotation":{"angle":0.0,"axis":"x","origin":[8.0,29.991074,8.019614]},"faces":{"down":{"uv":[14.6,3.2333333,12.0,3.1333332],"rotation":0,"texture":"#0","tintindex":0},"east":{"uv":[12.033333,13.2,12.133334,13.833334],"rotation":180,"texture":"#0","tintindex":0},"north":{"uv":[7.9333334,3.7333333,10.533334,4.366667],"rotation":180,"texture":"#0","tintindex":0},"south":{"uv":[7.2666664,3.1000001,9.866667,3.7333333],"rotation":180,"texture":"#0","tintindex":0},"up":{"uv":[15.033333,9.833334,12.433333,9.933333],"rotation":0,"texture":"#0","tintindex":0},"west":{"uv":[7.066667,13.233334,7.166667,13.866667],"rotation":180,"texture":"#0","tintindex":0}}},{"name":"cube","from":[-9.4096,23.673073,4.650014],"to":[-7.8184004,28.165874,5.2116137],"rotation":{"angle":0.0,"axis":"x","origin":[4.256,29.991074,8.019614]},"faces":{"down":{"uv":[14.066668,13.0,13.766666,12.900001],"rotation":0,"texture":"#0","tintindex":0},"east":{"uv":[13.166667,1.3333334,13.266666,2.1666667],"rotation":180,"texture":"#0","tintindex":0},"north":{"uv":[4.533334,12.466667,4.8333335,13.300001],"rotation":180,"texture":"#0","tintindex":0},"south":{"uv":[10.933333,0.0,11.233334,0.8333334],"rotation":180,"texture":"#0","tintindex":0},"up":{"uv":[14.1,1.0666667,13.800001,1.1666667],"rotation":0,"texture":"#0","tintindex":0},"west":{"uv":[13.166667,7.7000003,13.266666,8.533334],"rotation":180,"texture":"#0","tintindex":0}}},{"name":"cube","from":[-7.8184004,23.111473,4.0884137],"to":[-4.7296004,28.727474,4.650014],"rotation":{"angle":0.0,"axis":"x","origin":[3.7879996,29.991074,8.019614]},"faces":{"down":{"uv":[13.833334,8.566668,13.266666,8.466667],"rotation":0,"texture":"#0","tintindex":0},"east":{"uv":[12.333334,12.966667,12.433333,14.0],"rotation":180,"texture":"#0","tintindex":0},"north":{"uv":[9.700001,11.300001,10.266666,12.333334],"rotation":180,"texture":"#0","tintindex":0},"south":{"uv":[9.133333,11.300001,9.700001,12.333334],"rotation":180,"texture":"#0","tintindex":0},"up":{"uv":[13.866667,9.266666,13.300001,9.366667],"rotation":0,"texture":"#0","tintindex":0},"west":{"uv":[12.433333,12.966667,12.533333,14.0],"rotation":180,"texture":"#0","tintindex":0}}},{"name":"cube","from":[-9.4096,24.234673,4.0884137],"to":[-7.8184004,27.604275,4.650014],"rotation":{"angle":0.0,"axis":"x","origin":[4.256,29.991074,8.019614]},"faces":{"down":{"uv":[14.133334,8.5,13.833334,8.400001],"rotation":0,"texture":"#0","tintindex":0},"east":{"uv":[13.266666,1.3333334,13.366667,1.9666667],"rotation":180,"texture":"#0","tintindex":0},"north":{"uv":[6.9333334,12.6,7.2333336,13.233334],"rotation":180,"texture":"#0","tintindex":0},"south":{"uv":[6.633333,12.6,6.9333334,13.233334],"rotation":180,"texture":"#0","tintindex":0},"up":{"uv":[14.166667,3.7000003,13.866667,3.8],"rotation":0,"texture":"#0","tintindex":0},"west":{"uv":[13.266666,7.633333,13.366667,8.266666],"rotation":180,"texture":"#0","tintindex":0}}},{"name":"cube","from":[-7.8184004,23.673073,3.5268135],"to":[-4.7296004,28.165874,4.0884137],"rotation":{"angle":0.0,"axis":"x","origin":[3.7879996,29.991074,8.019614]},"faces":{"down":{"uv":[13.933333,1.9333334,13.366667,1.8333334],"rotation":0,"texture":"#0","tintindex":0},"east":{"uv":[13.2,0.0,13.300001,0.8333334],"rotation":180,"texture":"#0","tintindex":0},"north":{"uv":[11.5,6.166667,12.066668,7.0],"rotation":180,"texture":"#0","tintindex":0},"south":{"uv":[7.533334,11.333334,8.1,12.166667],"rotation":180,"texture":"#0","tintindex":0},"up":{"uv":[13.933333,10.666667,13.366667,10.766666],"rotation":0,"texture":"#0","tintindex":0},"west":{"uv":[8.666667,13.2,8.766666,14.033333],"rotation":180,"texture":"#0","tintindex":0}}},{"name":"cube","from":[-4.7296004,23.111473,2.9652133],"to":[-0.14320016,28.727474,3.5268135],"rotation":{"angle":0.0,"axis":"x","origin":[5.66,29.991074,8.019614]},"faces":{"down":{"uv":[13.900001,11.6,13.066668,11.5],"rotation":0,"texture":"#0","tintindex":0},"east":{"uv":[12.533333,12.966667,12.633334,14.0],"rotation":180,"texture":"#0","tintindex":0},"north":{"uv":[2.3000002,10.433333,3.1333332,11.466667],"rotation":180,"texture":"#0","tintindex":0},"south":{"uv":[10.433333,0.8666667,11.266666,1.9],"rotation":180,"texture":"#0","tintindex":0},"up":{"uv":[13.900001,11.6,13.066668,11.7],"rotation":0,"texture":"#0","tintindex":0},"west":{"uv":[12.633334,12.966667,12.733334,14.0],"rotation":180,"texture":"#0","tintindex":0}}},{"name":"cube","from":[-9.4096,25.357872,3.5268135],"to":[-7.8184004,26.481075,4.0884137],"rotation":{"angle":0.0,"axis":"x","origin":[4.256,29.991074,8.019614]},"faces":{"down":{"uv":[14.166667,8.1,13.866667,8.0],"rotation":0,"texture":"#0","tintindex":0},"east":{"uv":[1.1333334,10.200001,1.2333333,10.400001],"rotation":180,"texture":"#0","tintindex":0},"north":{"uv":[10.833334,11.6,11.133334,11.800001],"rotation":180,"texture":"#0","tintindex":0},"south":{"uv":[0.8333334,10.200001,1.1333334,10.400001],"rotation":180,"texture":"#0","tintindex":0},"up":{"uv":[14.166667,8.1,13.866667,8.200001],"rotation":0,"texture":"#0","tintindex":0},"west":{"uv":[7.4333334,11.966667,7.533334,12.166667],"rotation":180,"texture":"#0","tintindex":0}}},{"name":"cube","from":[-7.8184004,24.796276,2.9652133],"to":[-4.7296004,27.042671,3.5268135],"rotation":{"angle":0.0,"axis":"x","origin":[3.7879996,29.991074,8.019614]},"faces":{"down":{"uv":[13.933333,10.866667,13.366667,10.766666],"rotation":0,"texture":"#0","tintindex":0},"east":{"uv":[10.466667,13.533333,10.566668,13.933333],"rotation":180,"texture":"#0","tintindex":0},"north":{"uv":[12.533333,5.1000004,13.1,5.5],"rotation":180,"texture":"#0","tintindex":0},"south":{"uv":[12.533333,3.4,13.1,3.8],"rotation":180,"texture":"#0","tintindex":0},"up":{"uv":[13.933333,10.866667,13.366667,10.966667],"rotation":0,"texture":"#0","tintindex":0},"west":{"uv":[10.566668,13.533333,10.666667,13.933333],"rotation":180,"texture":"#0","tintindex":0}}},{"name":"cube","from":[-4.7296004,24.234673,2.4036136],"to":[-0.14320016,27.604275,2.9652133],"rotation":{"angle":0.0,"axis":"x","origin":[5.66,29.991074,8.019614]},"faces":{"down":{"uv":[13.900001,11.800001,13.066668,11.7],"rotation":0,"texture":"#0","tintindex":0},"east":{"uv":[13.300001,0.0,13.400001,0.6333333],"rotation":180,"texture":"#0","tintindex":0},"north":{"uv":[6.7000003,11.333334,7.533334,11.966667],"rotation":180,"texture":"#0","tintindex":0},"south":{"uv":[11.266666,1.2333333,12.1,1.8666667],"rotation":180,"texture":"#0","tintindex":0},"up":{"uv":[13.900001,12.1,13.066668,12.2],"rotation":0,"texture":"#0","tintindex":0},"west":{"uv":[4.5,13.300001,4.6000004,13.933333],"rotation":180,"texture":"#0","tintindex":0}}},{"name":"cube","from":[-4.7296004,22.54987,3.5268135],"to":[-0.14320016,29.289074,4.0884137],"rotation":{"angle":0.0,"axis":"x","origin":[5.66,29.991074,8.019614]},"faces":{"down":{"uv":[13.900001,12.300001,13.066668,12.2],"rotation":0,"texture":"#0","tintindex":0},"east":{"uv":[7.666667,4.766667,7.7666664,6.0],"rotation":180,"texture":"#0","tintindex":0},"north":{"uv":[6.633333,10.1,7.4666667,11.333334],"rotation":180,"texture":"#0","tintindex":0},"south":{"uv":[5.8,10.1,6.633333,11.333334],"rotation":180,"texture":"#0","tintindex":0},"up":{"uv":[13.900001,12.300001,13.066668,12.400001],"rotation":0,"texture":"#0","tintindex":0},"west":{"uv":[4.4,12.533333,4.5,13.766666],"rotation":180,"texture":"#0","tintindex":0}}},{"name":"cube","from":[-10.439201,24.234673,5.2116137],"to":[-9.4096,27.604275,5.7732134],"rotation":{"angle":0.0,"axis":"x","origin":[2.8519998,29.991074,8.019614]},"faces":{"down":{"uv":[10.266666,12.433333,10.066668,12.333334],"rotation":0,"texture":"#0","tintindex":0},"east":{"uv":[4.6000004,13.300001,4.7000003,13.933333],"rotation":180,"texture":"#0","tintindex":0},"north":{"uv":[1.2,12.7,1.4,13.333334],"rotation":180,"texture":"#0","tintindex":0},"south":{"uv":[1.0,12.7,1.2,13.333334],"rotation":180,"texture":"#0","tintindex":0},"up":{"uv":[14.133334,4.8,13.933333,4.9],"rotation":0,"texture":"#0","tintindex":0},"west":{"uv":[4.7000003,13.300001,4.8,13.933333],"rotation":180,"texture":"#0","tintindex":0}}},{"name":"cube","from":[-10.439201,24.796276,4.650014],"to":[-9.4096,27.042671,5.2116137],"rotation":{"angle":0.0,"axis":"x","origin":[2.8519998,29.991074,8.019614]},"faces":{"down":{"uv":[5.7666664,14.033333,5.566667,13.933333],"rotation":0,"texture":"#0","tintindex":0},"east":{"uv":[13.566668,7.6,13.666667,8.0],"rotation":180,"texture":"#0","tintindex":0},"north":{"uv":[11.5,7.8333335,11.7,8.233334],"rotation":180,"texture":"#0","tintindex":0},"south":{"uv":[9.6,2.7000003,9.8,3.1000001],"rotation":180,"texture":"#0","tintindex":0},"up":{"uv":[14.133334,5.8,13.933333,5.9000006],"rotation":0,"texture":"#0","tintindex":0},"west":{"uv":[7.8333335,13.566668,7.9333334,13.966667],"rotation":180,"texture":"#0","tintindex":0}}},{"name":"cube","from":[-11.0008,24.796276,5.7732134],"to":[-10.439201,27.042671,6.3348136],"rotation":{"angle":0.0,"axis":"x","origin":[3.3199997,29.991074,8.019614]},"faces":{"down":{"uv":[14.0,14.1,13.900001,14.0],"rotation":0,"texture":"#0","tintindex":0},"east":{"uv":[13.566668,8.0,13.666667,8.400001],"rotation":180,"texture":"#0","tintindex":0},"north":{"uv":[9.166667,13.566668,9.266666,13.966667],"rotation":180,"texture":"#0","tintindex":0},"south":{"uv":[7.9333334,13.566668,8.033334,13.966667],"rotation":180,"texture":"#0","tintindex":0},"up":{"uv":[14.1,14.0,14.0,14.1],"rotation":0,"texture":"#0","tintindex":0},"west":{"uv":[9.266666,13.566668,9.366667,13.966667],"rotation":180,"texture":"#0","tintindex":0}}},{"name":"cube","from":[22.695202,23.76667,4.650014],"to":[24.2864,28.259476,5.2116137],"rotation":{"angle":0.0,"axis":"x","origin":[10.6208,21.941471,8.019614]},"faces":{"down":{"uv":[14.166667,9.366667,13.866667,9.266666],"rotation":0,"texture":"#0","tintindex":0},"east":{"uv":[8.966667,13.2,9.066668,14.033333],"rotation":180,"texture":"#0","tintindex":0},"north":{"uv":[12.5,4.1000004,12.800001,4.9333334],"rotation":180,"texture":"#0","tintindex":0},"south":{"uv":[4.8333335,12.466667,5.133333,13.300001],"rotation":180,"texture":"#0","tintindex":0},"up":{"uv":[9.766666,13.866667,9.466667,13.966667],"rotation":0,"texture":"#0","tintindex":0},"west":{"uv":[9.066668,13.2,9.166667,14.033333],"rotation":180,"texture":"#0","tintindex":0}}},{"name":"cube","from":[19.6064,23.205074,4.0884137],"to":[22.695202,28.821075,4.650014],"rotation":{"angle":0.0,"axis":"x","origin":[11.0888,21.941471,8.019614]},"faces":{"down":{"uv":[13.933333,12.900001,13.366667,12.800001],"rotation":0,"texture":"#0","tintindex":0},"east":{"uv":[8.3,13.0,8.400001,14.033333],"rotation":180,"texture":"#0","tintindex":0},"north":{"uv":[6.133333,11.333334,6.7000003,12.366667],"rotation":180,"texture":"#0","tintindex":0},"south":{"uv":[5.566667,11.333334,6.133333,12.366667],"rotation":180,"texture":"#0","tintindex":0},"up":{"uv":[13.966667,0.0,13.400001,0.10000001],"rotation":0,"texture":"#0","tintindex":0},"west":{"uv":[8.400001,13.0,8.5,14.033333],"rotation":180,"texture":"#0","tintindex":0}}},{"name":"cube","from":[22.695202,24.328274,4.0884137],"to":[24.2864,27.697872,4.650014],"rotation":{"angle":0.0,"axis":"x","origin":[10.6208,21.941471,8.019614]},"faces":{"down":{"uv":[14.166667,8.6,13.866667,8.5],"rotation":0,"texture":"#0","tintindex":0},"east":{"uv":[2.766667,13.333334,2.8666668,13.966667],"rotation":180,"texture":"#0","tintindex":0},"north":{"uv":[12.633334,1.8000001,12.933333,2.4333334],"rotation":180,"texture":"#0","tintindex":0},"south":{"uv":[12.633334,0.6,12.933333,1.2333333],"rotation":180,"texture":"#0","tintindex":0},"up":{"uv":[14.166667,8.966667,13.866667,9.066668],"rotation":0,"texture":"#0","tintindex":0},"west":{"uv":[2.8666668,13.333334,2.9666667,13.966667],"rotation":180,"texture":"#0","tintindex":0}}},{"name":"cube","from":[19.6064,23.76667,3.5268135],"to":[22.695202,28.259476,4.0884137],"rotation":{"angle":0.0,"axis":"x","origin":[11.0888,21.941471,8.019614]},"faces":{"down":{"uv":[13.933333,12.7,13.366667,12.6],"rotation":0,"texture":"#0","tintindex":0},"east":{"uv":[8.766666,13.2,8.866667,14.033333],"rotation":180,"texture":"#0","tintindex":0},"north":{"uv":[10.266666,11.6,10.833334,12.433333],"rotation":180,"texture":"#0","tintindex":0},"south":{"uv":[11.5,7.0,12.066668,7.8333335],"rotation":180,"texture":"#0","tintindex":0},"up":{"uv":[13.933333,12.7,13.366667,12.800001],"rotation":0,"texture":"#0","tintindex":0},"west":{"uv":[8.866667,13.2,8.966667,14.033333],"rotation":180,"texture":"#0","tintindex":0}}},{"name":"cube","from":[15.02,23.205074,2.9652133],"to":[19.6064,28.821075,3.5268135],"rotation":{"angle":0.0,"axis":"x","origin":[9.216801,21.941471,8.019614]},"faces":{"down":{"uv":[13.933333,3.6000001,13.1,3.5],"rotation":0,"texture":"#0","tintindex":0},"east":{"uv":[12.733334,12.966667,12.833334,14.0],"rotation":180,"texture":"#0","tintindex":0},"north":{"uv":[3.1333332,10.6,3.9666667,11.633334],"rotation":180,"texture":"#0","tintindex":0},"south":{"uv":[10.333334,10.566668,11.166667,11.6],"rotation":180,"texture":"#0","tintindex":0},"up":{"uv":[13.933333,3.6000001,13.1,3.7000003],"rotation":0,"texture":"#0","tintindex":0},"west":{"uv":[12.833334,12.966667,12.933333,14.0],"rotation":180,"texture":"#0","tintindex":0}}},{"name":"cube","from":[22.695202,25.451473,3.5268135],"to":[24.2864,26.574673,4.0884137],"rotation":{"angle":0.0,"axis":"x","origin":[10.6208,21.941471,8.019614]},"faces":{"down":{"uv":[14.166667,8.3,13.866667,8.200001],"rotation":0,"texture":"#0","tintindex":0},"east":{"uv":[13.966667,7.2000003,14.066668,7.4000006],"rotation":180,"texture":"#0","tintindex":0},"north":{"uv":[13.300001,5.3,13.6,5.5],"rotation":180,"texture":"#0","tintindex":0},"south":{"uv":[13.300001,5.1000004,13.6,5.3],"rotation":180,"texture":"#0","tintindex":0},"up":{"uv":[14.166667,8.3,13.866667,8.400001],"rotation":0,"texture":"#0","tintindex":0},"west":{"uv":[7.8333335,13.966667,7.9333334,14.166667],"rotation":180,"texture":"#0","tintindex":0}}},{"name":"cube","from":[19.6064,24.889874,2.9652133],"to":[22.695202,27.136272,3.5268135],"rotation":{"angle":0.0,"axis":"x","origin":[11.0888,21.941471,8.019614]},"faces":{"down":{"uv":[13.933333,11.066668,13.366667,10.966667],"rotation":0,"texture":"#0","tintindex":0},"east":{"uv":[13.800001,9.366667,13.900001,9.766666],"rotation":180,"texture":"#0","tintindex":0},"north":{"uv":[12.6,6.4333334,13.166667,6.8333335],"rotation":180,"texture":"#0","tintindex":0},"south":{"uv":[12.366667,12.566668,12.933333,12.966667],"rotation":180,"texture":"#0","tintindex":0},"up":{"uv":[13.933333,12.5,13.366667,12.6],"rotation":0,"texture":"#0","tintindex":0},"west":{"uv":[13.433333,13.800001,13.533333,14.2],"rotation":180,"texture":"#0","tintindex":0}}},{"name":"cube","from":[15.02,24.328274,2.4036136],"to":[19.6064,27.697872,2.9652133],"rotation":{"angle":0.0,"axis":"x","origin":[9.216801,21.941471,8.019614]},"faces":{"down":{"uv":[13.933333,1.0666667,13.1,0.9666667],"rotation":0,"texture":"#0","tintindex":0},"east":{"uv":[1.3000001,13.333334,1.4,13.966667],"rotation":180,"texture":"#0","tintindex":0},"north":{"uv":[1.9666667,11.466667,2.8,12.1],"rotation":180,"texture":"#0","tintindex":0},"south":{"uv":[0.0,11.433333,0.8333334,12.066668],"rotation":180,"texture":"#0","tintindex":0},"up":{"uv":[13.933333,3.4,13.1,3.5],"rotation":0,"texture":"#0","tintindex":0},"west":{"uv":[2.6666667,13.333334,2.766667,13.966667],"rotation":180,"texture":"#0","tintindex":0}}},{"name":"cube","from":[15.02,22.64347,3.5268135],"to":[19.6064,29.382671,4.0884137],"rotation":{"angle":0.0,"axis":"x","origin":[9.216801,21.941471,8.019614]},"faces":{"down":{"uv":[13.900001,12.5,13.066668,12.400001],"rotation":0,"texture":"#0","tintindex":0},"east":{"uv":[7.2333336,12.6,7.3333335,13.833334],"rotation":180,"texture":"#0","tintindex":0},"north":{"uv":[0.0,10.200001,0.8333334,11.433333],"rotation":180,"texture":"#0","tintindex":0},"south":{"uv":[7.4666667,10.1,8.3,11.333334],"rotation":180,"texture":"#0","tintindex":0},"up":{"uv":[13.933333,0.8666667,13.1,0.9666667],"rotation":0,"texture":"#0","tintindex":0},"west":{"uv":[1.4,12.7,1.5,13.933333],"rotation":180,"texture":"#0","tintindex":0}}},{"name":"cube","from":[24.2864,24.328274,5.2116137],"to":[25.316002,27.697872,5.7732134],"rotation":{"angle":0.0,"axis":"x","origin":[12.0248,21.941471,8.019614]},"faces":{"down":{"uv":[14.133334,11.466667,13.933333,11.366667],"rotation":0,"texture":"#0","tintindex":0},"east":{"uv":[1.1,13.333334,1.2,13.966667],"rotation":180,"texture":"#0","tintindex":0},"north":{"uv":[11.666667,12.800001,11.866667,13.433333],"rotation":180,"texture":"#0","tintindex":0},"south":{"uv":[12.800001,4.1000004,13.0,4.7333336],"rotation":180,"texture":"#0","tintindex":0},"up":{"uv":[14.133334,13.2,13.933333,13.300001],"rotation":0,"texture":"#0","tintindex":0},"west":{"uv":[1.2,13.333334,1.3000001,13.966667],"rotation":180,"texture":"#0","tintindex":0}}},{"name":"cube","from":[24.2864,24.889874,4.650014],"to":[25.316002,27.136272,5.2116137],"rotation":{"angle":0.0,"axis":"x","origin":[12.0248,21.941471,8.019614]},"faces":{"down":{"uv":[14.133334,6.0,13.933333,5.9000006],"rotation":0,"texture":"#0","tintindex":0},"east":{"uv":[4.366667,13.766666,4.4666667,14.166667],"rotation":180,"texture":"#0","tintindex":0},"north":{"uv":[13.166667,4.1000004,13.366667,4.5],"rotation":180,"texture":"#0","tintindex":0},"south":{"uv":[13.1,5.1000004,13.300001,5.5],"rotation":180,"texture":"#0","tintindex":0},"up":{"uv":[14.133334,7.4333334,13.933333,7.533334],"rotation":0,"texture":"#0","tintindex":0},"west":{"uv":[6.5,13.766666,6.6,14.166667],"rotation":180,"texture":"#0","tintindex":0}}},{"name":"cube","from":[25.316002,24.889874,5.7732134],"to":[25.877598,27.136272,6.3348136],"rotation":{"angle":0.0,"axis":"x","origin":[11.556801,21.941471,8.019614]},"faces":{"down":{"uv":[14.133334,6.5,14.033333,6.4000006],"rotation":0,"texture":"#0","tintindex":0},"east":{"uv":[2.1000001,13.666667,2.2,14.066668],"rotation":180,"texture":"#0","tintindex":0},"north":{"uv":[11.666667,13.7,11.766666,14.1],"rotation":180,"texture":"#0","tintindex":0},"south":{"uv":[3.5666666,13.633334,3.6666667,14.033333],"rotation":180,"texture":"#0","tintindex":0},"up":{"uv":[14.133334,6.5,14.033333,6.6],"rotation":0,"texture":"#0","tintindex":0},"west":{"uv":[5.7666664,13.733334,5.866667,14.133334],"rotation":180,"texture":"#0","tintindex":0}}},{"name":"cube","from":[-0.14320016,24.796276,1.8420135],"to":[0.4183998,27.042671,2.4036136],"rotation":{"angle":0.0,"axis":"x","origin":[8.0,29.991074,8.019614]},"faces":{"down":{"uv":[2.3000002,14.133334,2.2,14.033333],"rotation":0,"texture":"#0","tintindex":0},"east":{"uv":[10.666667,13.566668,10.766666,13.966667],"rotation":180,"texture":"#0","tintindex":0},"north":{"uv":[11.133334,13.566668,11.233334,13.966667],"rotation":180,"texture":"#0","tintindex":0},"south":{"uv":[9.366667,13.566668,9.466667,13.966667],"rotation":180,"texture":"#0","tintindex":0},"up":{"uv":[2.4,14.033333,2.3000002,14.133334],"rotation":0,"texture":"#0","tintindex":0},"west":{"uv":[11.233334,13.566668,11.333334,13.966667],"rotation":180,"texture":"#0","tintindex":0}}},{"name":"cube","from":[14.4584,24.796276,1.8420135],"to":[15.02,27.042671,2.4036136],"rotation":{"angle":0.0,"axis":"x","origin":[8.0,29.991074,8.019614]},"faces":{"down":{"uv":[14.133334,3.0,14.033333,2.9],"rotation":0,"texture":"#0","tintindex":0},"east":{"uv":[8.5,13.6,8.6,14.0],"rotation":180,"texture":"#0","tintindex":0},"north":{"uv":[12.933333,13.6,13.033333,14.0],"rotation":180,"texture":"#0","tintindex":0},"south":{"uv":[13.6,5.1000004,13.7,5.5],"rotation":180,"texture":"#0","tintindex":0},"up":{"uv":[14.133334,3.0,14.033333,3.1000001],"rotation":0,"texture":"#0","tintindex":0},"west":{"uv":[13.333334,13.6,13.433333,14.0],"rotation":180,"texture":"#0","tintindex":0}}},{"name":"cube","from":[-0.14320016,30.876797,5.217076],"to":[15.02,31.438396,10.8330765],"rotation":{"angle":0.0,"axis":"x","origin":[8.0,25.8224,12.096676]},"faces":{"down":{"uv":[5.6,0.0,8.400001,1.0333333],"rotation":180,"texture":"#0","tintindex":0},"east":{"uv":[12.933333,12.566668,13.033333,13.6],"rotation":90,"texture":"#0","tintindex":0},"north":{"uv":[14.7,4.0,11.900001,3.9],"rotation":180,"texture":"#0","tintindex":0},"south":{"uv":[14.7,4.0,11.900001,4.1000004],"rotation":0,"texture":"#0","tintindex":0},"up":{"uv":[5.6,1.0333333,8.400001,2.0666666],"rotation":0,"texture":"#0","tintindex":0},"west":{"uv":[12.966667,1.3333334,13.066668,2.3666668],"rotation":270,"texture":"#0","tintindex":0}}},{"name":"cube","from":[-0.14320016,30.315197,4.093876],"to":[15.02,30.876797,11.956276],"rotation":{"angle":0.0,"axis":"x","origin":[8.0,25.8224,12.096676]},"faces":{"down":{"uv":[0.0,3.3333335,2.8,4.8],"rotation":180,"texture":"#0","tintindex":0},"east":{"uv":[3.5666666,12.166667,3.6666667,13.633334],"rotation":90,"texture":"#0","tintindex":0},"north":{"uv":[14.6,10.466667,11.800001,10.366667],"rotation":180,"texture":"#0","tintindex":0},"south":{"uv":[14.6,10.466667,11.800001,10.566668],"rotation":0,"texture":"#0","tintindex":0},"up":{"uv":[2.8,3.3333335,5.6,4.8],"rotation":0,"texture":"#0","tintindex":0},"west":{"uv":[11.366667,12.433333,11.466667,13.900001],"rotation":270,"texture":"#0","tintindex":0}}},{"name":"cube","from":[0.4183998,31.438396,6.340276],"to":[14.4584,32.0,9.709876],"rotation":{"angle":0.0,"axis":"x","origin":[8.0,25.8224,12.096676]},"faces":{"down":{"uv":[7.2666664,3.1000001,9.866667,3.7333333],"rotation":180,"texture":"#0","tintindex":0},"east":{"uv":[12.033333,13.2,12.133334,13.833334],"rotation":90,"texture":"#0","tintindex":0},"north":{"uv":[14.6,3.2333333,12.0,3.1333332],"rotation":180,"texture":"#0","tintindex":0},"south":{"uv":[15.033333,9.833334,12.433333,9.933333],"rotation":0,"texture":"#0","tintindex":0},"up":{"uv":[7.9333334,3.7333333,10.533334,4.366667],"rotation":0,"texture":"#0","tintindex":0},"west":{"uv":[7.066667,13.233334,7.166667,13.866667],"rotation":270,"texture":"#0","tintindex":0}}},{"name":"cube","from":[-9.4096,28.630398,5.778676],"to":[-7.8184004,29.191998,10.271477],"rotation":{"angle":0.0,"axis":"x","origin":[4.256,25.8224,12.096676]},"faces":{"down":{"uv":[10.933333,0.0,11.233334,0.8333334],"rotation":180,"texture":"#0","tintindex":0},"east":{"uv":[13.166667,1.3333334,13.266666,2.1666667],"rotation":90,"texture":"#0","tintindex":0},"north":{"uv":[14.066668,13.0,13.766666,12.900001],"rotation":180,"texture":"#0","tintindex":0},"south":{"uv":[14.1,1.0666667,13.800001,1.1666667],"rotation":0,"texture":"#0","tintindex":0},"up":{"uv":[4.533334,12.466667,4.8333335,13.300001],"rotation":0,"texture":"#0","tintindex":0},"west":{"uv":[13.166667,7.7000003,13.266666,8.533334],"rotation":270,"texture":"#0","tintindex":0}}},{"name":"cube","from":[-7.8184004,29.191998,5.217076],"to":[-4.7296004,29.753597,10.8330765],"rotation":{"angle":0.0,"axis":"x","origin":[3.7879996,25.8224,12.096676]},"faces":{"down":{"uv":[9.133333,11.300001,9.700001,12.333334],"rotation":180,"texture":"#0","tintindex":0},"east":{"uv":[12.333334,12.966667,12.433333,14.0],"rotation":90,"texture":"#0","tintindex":0},"north":{"uv":[13.833334,8.566668,13.266666,8.466667],"rotation":180,"texture":"#0","tintindex":0},"south":{"uv":[13.866667,9.266666,13.300001,9.366667],"rotation":0,"texture":"#0","tintindex":0},"up":{"uv":[9.700001,11.300001,10.266666,12.333334],"rotation":0,"texture":"#0","tintindex":0},"west":{"uv":[12.433333,12.966667,12.533333,14.0],"rotation":270,"texture":"#0","tintindex":0}}},{"name":"cube","from":[-9.4096,29.191998,6.340276],"to":[-7.8184004,29.753597,9.709876],"rotation":{"angle":0.0,"axis":"x","origin":[4.256,25.8224,12.096676]},"faces":{"down":{"uv":[6.633333,12.6,6.9333334,13.233334],"rotation":180,"texture":"#0","tintindex":0},"east":{"uv":[13.266666,1.3333334,13.366667,1.9666667],"rotation":90,"texture":"#0","tintindex":0},"north":{"uv":[14.133334,8.5,13.833334,8.400001],"rotation":180,"texture":"#0","tintindex":0},"south":{"uv":[14.166667,3.7000003,13.866667,3.8],"rotation":0,"texture":"#0","tintindex":0},"up":{"uv":[6.9333334,12.6,7.2333336,13.233334],"rotation":0,"texture":"#0","tintindex":0},"west":{"uv":[13.266666,7.633333,13.366667,8.266666],"rotation":270,"texture":"#0","tintindex":0}}},{"name":"cube","from":[-7.8184004,29.753597,5.778676],"to":[-4.7296004,30.315197,10.271477],"rotation":{"angle":0.0,"axis":"x","origin":[3.7879996,25.8224,12.096676]},"faces":{"down":{"uv":[7.533334,11.333334,8.1,12.166667],"rotation":180,"texture":"#0","tintindex":0},"east":{"uv":[13.2,0.0,13.300001,0.8333334],"rotation":90,"texture":"#0","tintindex":0},"north":{"uv":[13.933333,1.9333334,13.366667,1.8333334],"rotation":180,"texture":"#0","tintindex":0},"south":{"uv":[13.933333,10.666667,13.366667,10.766666],"rotation":0,"texture":"#0","tintindex":0},"up":{"uv":[11.5,6.166667,12.066668,7.0],"rotation":0,"texture":"#0","tintindex":0},"west":{"uv":[8.666667,13.2,8.766666,14.033333],"rotation":270,"texture":"#0","tintindex":0}}},{"name":"cube","from":[-4.7296004,30.315197,5.217076],"to":[-0.14320016,30.876797,10.8330765],"rotation":{"angle":0.0,"axis":"x","origin":[5.66,25.8224,12.096676]},"faces":{"down":{"uv":[10.433333,0.8666667,11.266666,1.9],"rotation":180,"texture":"#0","tintindex":0},"east":{"uv":[12.533333,12.966667,12.633334,14.0],"rotation":90,"texture":"#0","tintindex":0},"north":{"uv":[13.900001,11.6,13.066668,11.5],"rotation":180,"texture":"#0","tintindex":0},"south":{"uv":[13.900001,11.6,13.066668,11.7],"rotation":0,"texture":"#0","tintindex":0},"up":{"uv":[2.3000002,10.433333,3.1333332,11.466667],"rotation":0,"texture":"#0","tintindex":0},"west":{"uv":[12.633334,12.966667,12.733334,14.0],"rotation":270,"texture":"#0","tintindex":0}}},{"name":"cube","from":[-9.4096,29.753597,7.4634757],"to":[-7.8184004,30.315197,8.586676],"rotation":{"angle":0.0,"axis":"x","origin":[4.256,25.8224,12.096676]},"faces":{"down":{"uv":[0.8333334,10.200001,1.1333334,10.400001],"rotation":180,"texture":"#0","tintindex":0},"east":{"uv":[1.1333334,10.200001,1.2333333,10.400001],"rotation":90,"texture":"#0","tintindex":0},"north":{"uv":[14.166667,8.1,13.866667,8.0],"rotation":180,"texture":"#0","tintindex":0},"south":{"uv":[14.166667,8.1,13.866667,8.200001],"rotation":0,"texture":"#0","tintindex":0},"up":{"uv":[10.833334,11.6,11.133334,11.800001],"rotation":0,"texture":"#0","tintindex":0},"west":{"uv":[7.4333334,11.966667,7.533334,12.166667],"rotation":270,"texture":"#0","tintindex":0}}},{"name":"cube","from":[-7.8184004,30.315197,6.9018755],"to":[-4.7296004,30.876797,9.148276],"rotation":{"angle":0.0,"axis":"x","origin":[3.7879996,25.8224,12.096676]},"faces":{"down":{"uv":[12.533333,3.4,13.1,3.8],"rotation":180,"texture":"#0","tintindex":0},"east":{"uv":[10.466667,13.533333,10.566668,13.933333],"rotation":90,"texture":"#0","tintindex":0},"north":{"uv":[13.933333,10.866667,13.366667,10.766666],"rotation":180,"texture":"#0","tintindex":0},"south":{"uv":[13.933333,10.866667,13.366667,10.966667],"rotation":0,"texture":"#0","tintindex":0},"up":{"uv":[12.533333,5.1000004,13.1,5.5],"rotation":0,"texture":"#0","tintindex":0},"west":{"uv":[10.566668,13.533333,10.666667,13.933333],"rotation":270,"texture":"#0","tintindex":0}}},{"name":"cube","from":[-4.7296004,30.876797,6.340276],"to":[-0.14320016,31.438396,9.709876],"rotation":{"angle":0.0,"axis":"x","origin":[5.66,25.8224,12.096676]},"faces":{"down":{"uv":[11.266666,1.2333333,12.1,1.8666667],"rotation":180,"texture":"#0","tintindex":0},"east":{"uv":[13.300001,0.0,13.400001,0.6333333],"rotation":90,"texture":"#0","tintindex":0},"north":{"uv":[13.900001,11.800001,13.066668,11.7],"rotation":180,"texture":"#0","tintindex":0},"south":{"uv":[13.900001,12.1,13.066668,12.2],"rotation":0,"texture":"#0","tintindex":0},"up":{"uv":[6.7000003,11.333334,7.533334,11.966667],"rotation":0,"texture":"#0","tintindex":0},"west":{"uv":[4.5,13.300001,4.6000004,13.933333],"rotation":270,"texture":"#0","tintindex":0}}},{"name":"cube","from":[-4.7296004,29.753597,4.6554756],"to":[-0.14320016,30.315197,11.394676],"rotation":{"angle":0.0,"axis":"x","origin":[5.66,25.8224,12.096676]},"faces":{"down":{"uv":[5.8,10.1,6.633333,11.333334],"rotation":180,"texture":"#0","tintindex":0},"east":{"uv":[7.666667,4.766667,7.7666664,6.0],"rotation":90,"texture":"#0","tintindex":0},"north":{"uv":[13.900001,12.300001,13.066668,12.2],"rotation":180,"texture":"#0","tintindex":0},"south":{"uv":[13.900001,12.300001,13.066668,12.400001],"rotation":0,"texture":"#0","tintindex":0},"up":{"uv":[6.633333,10.1,7.4666667,11.333334],"rotation":0,"texture":"#0","tintindex":0},"west":{"uv":[4.4,12.533333,4.5,13.766666],"rotation":270,"texture":"#0","tintindex":0}}},{"name":"cube","from":[-10.439201,28.068798,6.340276],"to":[-9.4096,28.630398,9.709876],"rotation":{"angle":0.0,"axis":"x","origin":[2.8519998,25.8224,12.096676]},"faces":{"down":{"uv":[1.0,12.7,1.2,13.333334],"rotation":180,"texture":"#0","tintindex":0},"east":{"uv":[4.6000004,13.300001,4.7000003,13.933333],"rotation":90,"texture":"#0","tintindex":0},"north":{"uv":[10.266666,12.433333,10.066668,12.333334],"rotation":180,"texture":"#0","tintindex":0},"south":{"uv":[14.133334,4.8,13.933333,4.9],"rotation":0,"texture":"#0","tintindex":0},"up":{"uv":[1.2,12.7,1.4,13.333334],"rotation":0,"texture":"#0","tintindex":0},"west":{"uv":[4.7000003,13.300001,4.8,13.933333],"rotation":270,"texture":"#0","tintindex":0}}},{"name":"cube","from":[-10.439201,28.630398,6.9018755],"to":[-9.4096,29.191998,9.148276],"rotation":{"angle":0.0,"axis":"x","origin":[2.8519998,25.8224,12.096676]},"faces":{"down":{"uv":[9.6,2.7000003,9.8,3.1000001],"rotation":180,"texture":"#0","tintindex":0},"east":{"uv":[13.566668,7.6,13.666667,8.0],"rotation":90,"texture":"#0","tintindex":0},"north":{"uv":[5.7666664,14.033333,5.566667,13.933333],"rotation":180,"texture":"#0","tintindex":0},"south":{"uv":[14.133334,5.8,13.933333,5.9000006],"rotation":0,"texture":"#0","tintindex":0},"up":{"uv":[11.5,7.8333335,11.7,8.233334],"rotation":0,"texture":"#0","tintindex":0},"west":{"uv":[7.8333335,13.566668,7.9333334,13.966667],"rotation":270,"texture":"#0","tintindex":0}}},{"name":"cube","from":[-11.0008,27.507198,6.9018755],"to":[-10.439201,28.068798,9.148276],"rotation":{"angle":0.0,"axis":"x","origin":[3.3199997,25.8224,12.096676]},"faces":{"down":{"uv":[7.9333334,13.566668,8.033334,13.966667],"rotation":180,"texture":"#0","tintindex":0},"east":{"uv":[13.566668,8.0,13.666667,8.400001],"rotation":90,"texture":"#0","tintindex":0},"north":{"uv":[14.0,14.1,13.900001,14.0],"rotation":180,"texture":"#0","tintindex":0},"south":{"uv":[14.1,14.0,14.0,14.1],"rotation":0,"texture":"#0","tintindex":0},"up":{"uv":[9.166667,13.566668,9.266666,13.966667],"rotation":0,"texture":"#0","tintindex":0},"west":{"uv":[9.266666,13.566668,9.366667,13.966667],"rotation":270,"texture":"#0","tintindex":0}}},{"name":"cube","from":[22.695202,28.630398,5.872276],"to":[24.2864,29.191998,10.365076],"rotation":{"angle":0.0,"axis":"x","origin":[10.6208,25.8224,4.0470757]},"faces":{"down":{"uv":[4.8333335,12.466667,5.133333,13.300001],"rotation":180,"texture":"#0","tintindex":0},"east":{"uv":[8.966667,13.2,9.066668,14.033333],"rotation":90,"texture":"#0","tintindex":0},"north":{"uv":[14.166667,9.366667,13.866667,9.266666],"rotation":180,"texture":"#0","tintindex":0},"south":{"uv":[9.766666,13.866667,9.466667,13.966667],"rotation":0,"texture":"#0","tintindex":0},"up":{"uv":[12.5,4.1000004,12.800001,4.9333334],"rotation":0,"texture":"#0","tintindex":0},"west":{"uv":[9.066668,13.2,9.166667,14.033333],"rotation":270,"texture":"#0","tintindex":0}}},{"name":"cube","from":[19.6064,29.191998,5.3106756],"to":[22.695202,29.753597,10.926676],"rotation":{"angle":0.0,"axis":"x","origin":[11.0888,25.8224,4.0470757]},"faces":{"down":{"uv":[5.566667,11.333334,6.133333,12.366667],"rotation":180,"texture":"#0","tintindex":0},"east":{"uv":[8.3,13.0,8.400001,14.033333],"rotation":90,"texture":"#0","tintindex":0},"north":{"uv":[13.933333,12.900001,13.366667,12.800001],"rotation":180,"texture":"#0","tintindex":0},"south":{"uv":[13.966667,0.0,13.400001,0.10000001],"rotation":0,"texture":"#0","tintindex":0},"up":{"uv":[6.133333,11.333334,6.7000003,12.366667],"rotation":0,"texture":"#0","tintindex":0},"west":{"uv":[8.400001,13.0,8.5,14.033333],"rotation":270,"texture":"#0","tintindex":0}}},{"name":"cube","from":[22.695202,29.191998,6.433876],"to":[24.2864,29.753597,9.803476],"rotation":{"angle":0.0,"axis":"x","origin":[10.6208,25.8224,4.0470757]},"faces":{"down":{"uv":[12.633334,0.6,12.933333,1.2333333],"rotation":180,"texture":"#0","tintindex":0},"east":{"uv":[2.766667,13.333334,2.8666668,13.966667],"rotation":90,"texture":"#0","tintindex":0},"north":{"uv":[14.166667,8.6,13.866667,8.5],"rotation":180,"texture":"#0","tintindex":0},"south":{"uv":[14.166667,8.966667,13.866667,9.066668],"rotation":0,"texture":"#0","tintindex":0},"up":{"uv":[12.633334,1.8000001,12.933333,2.4333334],"rotation":0,"texture":"#0","tintindex":0},"west":{"uv":[2.8666668,13.333334,2.9666667,13.966667],"rotation":270,"texture":"#0","tintindex":0}}},{"name":"cube","from":[19.6064,29.753597,5.872276],"to":[22.695202,30.315197,10.365076],"rotation":{"angle":0.0,"axis":"x","origin":[11.0888,25.8224,4.0470757]},"faces":{"down":{"uv":[11.5,7.0,12.066668,7.8333335],"rotation":180,"texture":"#0","tintindex":0},"east":{"uv":[8.766666,13.2,8.866667,14.033333],"rotation":90,"texture":"#0","tintindex":0},"north":{"uv":[13.933333,12.7,13.366667,12.6],"rotation":180,"texture":"#0","tintindex":0},"south":{"uv":[13.933333,12.7,13.366667,12.800001],"rotation":0,"texture":"#0","tintindex":0},"up":{"uv":[10.266666,11.6,10.833334,12.433333],"rotation":0,"texture":"#0","tintindex":0},"west":{"uv":[8.866667,13.2,8.966667,14.033333],"rotation":270,"texture":"#0","tintindex":0}}},{"name":"cube","from":[15.02,30.315197,5.3106756],"to":[19.6064,30.876797,10.926676],"rotation":{"angle":0.0,"axis":"x","origin":[9.216801,25.8224,4.0470757]},"faces":{"down":{"uv":[10.333334,10.566668,11.166667,11.6],"rotation":180,"texture":"#0","tintindex":0},"east":{"uv":[12.733334,12.966667,12.833334,14.0],"rotation":90,"texture":"#0","tintindex":0},"north":{"uv":[13.933333,3.6000001,13.1,3.5],"rotation":180,"texture":"#0","tintindex":0},"south":{"uv":[13.933333,3.6000001,13.1,3.7000003],"rotation":0,"texture":"#0","tintindex":0},"up":{"uv":[3.1333332,10.6,3.9666667,11.633334],"rotation":0,"texture":"#0","tintindex":0},"west":{"uv":[12.833334,12.966667,12.933333,14.0],"rotation":270,"texture":"#0","tintindex":0}}},{"name":"cube","from":[22.695202,29.753597,7.557076],"to":[24.2864,30.315197,8.680276],"rotation":{"angle":0.0,"axis":"x","origin":[10.6208,25.8224,4.0470757]},"faces":{"down":{"uv":[13.300001,5.1000004,13.6,5.3],"rotation":180,"texture":"#0","tintindex":0},"east":{"uv":[13.966667,7.2000003,14.066668,7.4000006],"rotation":90,"texture":"#0","tintindex":0},"north":{"uv":[14.166667,8.3,13.866667,8.200001],"rotation":180,"texture":"#0","tintindex":0},"south":{"uv":[14.166667,8.3,13.866667,8.400001],"rotation":0,"texture":"#0","tintindex":0},"up":{"uv":[13.300001,5.3,13.6,5.5],"rotation":0,"texture":"#0","tintindex":0},"west":{"uv":[7.8333335,13.966667,7.9333334,14.166667],"rotation":270,"texture":"#0","tintindex":0}}},{"name":"cube","from":[19.6064,30.315197,6.995476],"to":[22.695202,30.876797,9.241876],"rotation":{"angle":0.0,"axis":"x","origin":[11.0888,25.8224,4.0470757]},"faces":{"down":{"uv":[12.366667,12.566668,12.933333,12.966667],"rotation":180,"texture":"#0","tintindex":0},"east":{"uv":[13.800001,9.366667,13.900001,9.766666],"rotation":90,"texture":"#0","tintindex":0},"north":{"uv":[13.933333,11.066668,13.366667,10.966667],"rotation":180,"texture":"#0","tintindex":0},"south":{"uv":[13.933333,12.5,13.366667,12.6],"rotation":0,"texture":"#0","tintindex":0},"up":{"uv":[12.6,6.4333334,13.166667,6.8333335],"rotation":0,"texture":"#0","tintindex":0},"west":{"uv":[13.433333,13.800001,13.533333,14.2],"rotation":270,"texture":"#0","tintindex":0}}},{"name":"cube","from":[15.02,30.876797,6.433876],"to":[19.6064,31.438396,9.803476],"rotation":{"angle":0.0,"axis":"x","origin":[9.216801,25.8224,4.0470757]},"faces":{"down":{"uv":[0.0,11.433333,0.8333334,12.066668],"rotation":180,"texture":"#0","tintindex":0},"east":{"uv":[1.3000001,13.333334,1.4,13.966667],"rotation":90,"texture":"#0","tintindex":0},"north":{"uv":[13.933333,1.0666667,13.1,0.9666667],"rotation":180,"texture":"#0","tintindex":0},"south":{"uv":[13.933333,3.4,13.1,3.5],"rotation":0,"texture":"#0","tintindex":0},"up":{"uv":[1.9666667,11.466667,2.8,12.1],"rotation":0,"texture":"#0","tintindex":0},"west":{"uv":[2.6666667,13.333334,2.766667,13.966667],"rotation":270,"texture":"#0","tintindex":0}}},{"name":"cube","from":[15.02,29.753597,4.749076],"to":[19.6064,30.315197,11.4882765],"rotation":{"angle":0.0,"axis":"x","origin":[9.216801,25.8224,4.0470757]},"faces":{"down":{"uv":[7.4666667,10.1,8.3,11.333334],"rotation":180,"texture":"#0","tintindex":0},"east":{"uv":[7.2333336,12.6,7.3333335,13.833334],"rotation":90,"texture":"#0","tintindex":0},"north":{"uv":[13.900001,12.5,13.066668,12.400001],"rotation":180,"texture":"#0","tintindex":0},"south":{"uv":[13.933333,0.8666667,13.1,0.9666667],"rotation":0,"texture":"#0","tintindex":0},"up":{"uv":[0.0,10.200001,0.8333334,11.433333],"rotation":0,"texture":"#0","tintindex":0},"west":{"uv":[1.4,12.7,1.5,13.933333],"rotation":270,"texture":"#0","tintindex":0}}},{"name":"cube","from":[24.2864,28.068798,6.433876],"to":[25.316002,28.630398,9.803476],"rotation":{"angle":0.0,"axis":"x","origin":[12.0248,25.8224,4.0470757]},"faces":{"down":{"uv":[12.800001,4.1000004,13.0,4.7333336],"rotation":180,"texture":"#0","tintindex":0},"east":{"uv":[1.1,13.333334,1.2,13.966667],"rotation":90,"texture":"#0","tintindex":0},"north":{"uv":[14.133334,11.466667,13.933333,11.366667],"rotation":180,"texture":"#0","tintindex":0},"south":{"uv":[14.133334,13.2,13.933333,13.300001],"rotation":0,"texture":"#0","tintindex":0},"up":{"uv":[11.666667,12.800001,11.866667,13.433333],"rotation":0,"texture":"#0","tintindex":0},"west":{"uv":[1.2,13.333334,1.3000001,13.966667],"rotation":270,"texture":"#0","tintindex":0}}},{"name":"cube","from":[24.2864,28.630398,6.995476],"to":[25.316002,29.191998,9.241876],"rotation":{"angle":0.0,"axis":"x","origin":[12.0248,25.8224,4.0470757]},"faces":{"down":{"uv":[13.1,5.1000004,13.300001,5.5],"rotation":180,"texture":"#0","tintindex":0},"east":{"uv":[4.366667,13.766666,4.4666667,14.166667],"rotation":90,"texture":"#0","tintindex":0},"north":{"uv":[14.133334,6.0,13.933333,5.9000006],"rotation":180,"texture":"#0","tintindex":0},"south":{"uv":[14.133334,7.4333334,13.933333,7.533334],"rotation":0,"texture":"#0","tintindex":0},"up":{"uv":[13.166667,4.1000004,13.366667,4.5],"rotation":0,"texture":"#0","tintindex":0},"west":{"uv":[6.5,13.766666,6.6,14.166667],"rotation":270,"texture":"#0","tintindex":0}}},{"name":"cube","from":[25.316002,27.507198,6.995476],"to":[25.877598,28.068798,9.241876],"rotation":{"angle":0.0,"axis":"x","origin":[11.556801,25.8224,4.0470757]},"faces":{"down":{"uv":[3.5666666,13.633334,3.6666667,14.033333],"rotation":180,"texture":"#0","tintindex":0},"east":{"uv":[2.1000001,13.666667,2.2,14.066668],"rotation":90,"texture":"#0","tintindex":0},"north":{"uv":[14.133334,6.5,14.033333,6.4000006],"rotation":180,"texture":"#0","tintindex":0},"south":{"uv":[14.133334,6.5,14.033333,6.6],"rotation":0,"texture":"#0","tintindex":0},"up":{"uv":[11.666667,13.7,11.766666,14.1],"rotation":0,"texture":"#0","tintindex":0},"west":{"uv":[5.7666664,13.733334,5.866667,14.133334],"rotation":270,"texture":"#0","tintindex":0}}},{"name":"cube","from":[-0.14320016,31.438396,6.9018755],"to":[0.4183998,32.0,9.148276],"rotation":{"angle":0.0,"axis":"x","origin":[8.0,25.8224,12.096676]},"faces":{"down":{"uv":[9.366667,13.566668,9.466667,13.966667],"rotation":180,"texture":"#0","tintindex":0},"east":{"uv":[10.666667,13.566668,10.766666,13.966667],"rotation":90,"texture":"#0","tintindex":0},"north":{"uv":[2.3000002,14.133334,2.2,14.033333],"rotation":180,"texture":"#0","tintindex":0},"south":{"uv":[2.4,14.033333,2.3000002,14.133334],"rotation":0,"texture":"#0","tintindex":0},"up":{"uv":[11.133334,13.566668,11.233334,13.966667],"rotation":0,"texture":"#0","tintindex":0},"west":{"uv":[11.233334,13.566668,11.333334,13.966667],"rotation":270,"texture":"#0","tintindex":0}}},{"name":"cube","from":[14.4584,31.438396,6.9018755],"to":[15.02,32.0,9.148276],"rotation":{"angle":0.0,"axis":"x","origin":[8.0,25.8224,12.096676]},"faces":{"down":{"uv":[13.6,5.1000004,13.7,5.5],"rotation":180,"texture":"#0","tintindex":0},"east":{"uv":[8.5,13.6,8.6,14.0],"rotation":90,"texture":"#0","tintindex":0},"north":{"uv":[14.133334,3.0,14.033333,2.9],"rotation":180,"texture":"#0","tintindex":0},"south":{"uv":[14.133334,3.0,14.033333,3.1000001],"rotation":0,"texture":"#0","tintindex":0},"up":{"uv":[12.933333,13.6,13.033333,14.0],"rotation":0,"texture":"#0","tintindex":0},"west":{"uv":[13.333334,13.6,13.433333,14.0],"rotation":270,"texture":"#0","tintindex":0}}},{"name":"cube","from":[24.2864,24.956535,5.7536],"to":[25.316002,28.189335,10.2464],"rotation":{"angle":0.0,"axis":"x","origin":[12.0248,-10.456667,8.0]},"faces":{"down":{"uv":[0.8000001,12.7,0.6,13.533333],"rotation":0,"texture":"#0","tintindex":0},"east":{"uv":[11.166667,3.266667,12.0,2.4333334],"rotation":0,"texture":"#0","tintindex":0},"north":{"uv":[0.20000002,13.533333,0.40000004,12.7],"rotation":0,"texture":"#0","tintindex":0},"south":{"uv":[0.40000004,13.533333,0.6,12.7],"rotation":0,"texture":"#0","tintindex":0},"up":{"uv":[1.0,13.533333,0.8000001,12.7],"rotation":0,"texture":"#0","tintindex":0},"west":{"uv":[8.3,12.133334,9.133333,11.300001],"rotation":0,"texture":"#0","tintindex":0}}},{"name":"cube","from":[22.695202,24.394932,5.192],"to":[24.2864,28.750935,10.808001],"rotation":{"angle":0.0,"axis":"x","origin":[10.6208,-10.456667,8.0]},"faces":{"down":{"uv":[6.4666667,12.366667,6.166667,13.400001],"rotation":0,"texture":"#0","tintindex":0},"east":{"uv":[10.033334,5.4000006,11.066668,4.366667],"rotation":0,"texture":"#0","tintindex":0},"north":{"uv":[5.566667,13.400001,5.866667,12.366667],"rotation":0,"texture":"#0","tintindex":0},"south":{"uv":[5.866667,13.400001,6.166667,12.366667],"rotation":0,"texture":"#0","tintindex":0},"up":{"uv":[12.666667,12.133334,12.366667,11.1],"rotation":0,"texture":"#0","tintindex":0},"west":{"uv":[10.033334,6.4333334,11.066668,5.4000006],"rotation":0,"texture":"#0","tintindex":0}}},{"name":"cube","from":[19.6064,23.833336,4.6303997],"to":[22.695202,29.312538,11.3696],"rotation":{"angle":0.0,"axis":"x","origin":[11.0888,-10.456667,8.0]},"faces":{"down":{"uv":[11.833334,0.0,11.266666,1.2333333],"rotation":0,"texture":"#0","tintindex":0},"east":{"uv":[8.666667,9.833334,9.900001,8.6],"rotation":0,"texture":"#0","tintindex":0},"north":{"uv":[11.066668,5.3333335,11.633334,4.1000004],"rotation":0,"texture":"#0","tintindex":0},"south":{"uv":[11.166667,11.800001,11.733334,10.566668],"rotation":0,"texture":"#0","tintindex":0},"up":{"uv":[4.533334,12.533333,3.9666667,11.300001],"rotation":0,"texture":"#0","tintindex":0},"west":{"uv":[0.0,10.200001,1.2333333,8.966667],"rotation":0,"texture":"#0","tintindex":0}}},{"name":"cube","from":[15.02,23.271736,4.0688],"to":[19.6064,29.874134,11.9312],"rotation":{"angle":0.0,"axis":"x","origin":[9.216801,-10.456667,8.0]},"faces":{"down":{"uv":[9.5,9.833334,8.666667,11.300001],"rotation":0,"texture":"#0","tintindex":0},"east":{"uv":[2.9333334,9.133333,4.4,7.666667],"rotation":0,"texture":"#0","tintindex":0},"north":{"uv":[9.200001,7.3,10.033334,5.8333335],"rotation":0,"texture":"#0","tintindex":0},"south":{"uv":[9.6,2.7000003,10.433333,1.2333333],"rotation":0,"texture":"#0","tintindex":0},"up":{"uv":[10.333334,11.300001,9.5,9.833334],"rotation":0,"texture":"#0","tintindex":0},"west":{"uv":[4.4,9.133333,5.866667,7.666667],"rotation":0,"texture":"#0","tintindex":0}}},{"name":"cube","from":[-10.439201,24.862934,5.7536],"to":[-9.4096,28.095734,10.2464],"rotation":{"angle":0.0,"axis":"x","origin":[2.8519998,-2.4070663,8.0]},"faces":{"down":{"uv":[12.866667,10.566668,12.666667,11.400001],"rotation":0,"texture":"#0","tintindex":0},"east":{"uv":[10.933333,9.1,11.766666,8.266666],"rotation":0,"texture":"#0","tintindex":0},"north":{"uv":[2.266667,13.466667,2.4666667,12.633334],"rotation":0,"texture":"#0","tintindex":0},"south":{"uv":[2.4666667,13.466667,2.6666667,12.633334],"rotation":0,"texture":"#0","tintindex":0},"up":{"uv":[0.20000002,13.533333,0.0,12.7],"rotation":0,"texture":"#0","tintindex":0},"west":{"uv":[11.066668,6.166667,11.900001,5.3333335],"rotation":0,"texture":"#0","tintindex":0}}},{"name":"cube","from":[-9.4096,24.301334,5.192],"to":[-7.8184004,28.657337,10.808001],"rotation":{"angle":0.0,"axis":"x","origin":[4.256,-2.4070663,8.0]},"faces":{"down":{"uv":[9.766666,12.333334,9.466667,13.366667],"rotation":0,"texture":"#0","tintindex":0},"east":{"uv":[9.900001,8.333334,10.933333,7.3],"rotation":0,"texture":"#0","tintindex":0},"north":{"uv":[8.3,11.133334,8.6,10.1],"rotation":0,"texture":"#0","tintindex":0},"south":{"uv":[9.166667,13.366667,9.466667,12.333334],"rotation":0,"texture":"#0","tintindex":0},"up":{"uv":[10.066668,13.366667,9.766666,12.333334],"rotation":0,"texture":"#0","tintindex":0},"west":{"uv":[9.900001,9.366667,10.933333,8.333334],"rotation":0,"texture":"#0","tintindex":0}}},{"name":"cube","from":[-7.8184004,23.739735,4.6303997],"to":[-4.7296004,29.218937,11.3696],"rotation":{"angle":0.0,"axis":"x","origin":[3.7879996,-2.4070663,8.0]},"faces":{"down":{"uv":[1.4,11.033333,0.8333334,12.266666],"rotation":0,"texture":"#0","tintindex":0},"east":{"uv":[8.400001,1.2333333,9.633333,0.0],"rotation":0,"texture":"#0","tintindex":0},"north":{"uv":[5.0,11.833334,5.566667,10.6],"rotation":0,"texture":"#0","tintindex":0},"south":{"uv":[10.933333,8.266666,11.5,7.033334],"rotation":0,"texture":"#0","tintindex":0},"up":{"uv":[1.9666667,12.266666,1.4,11.033333],"rotation":0,"texture":"#0","tintindex":0},"west":{"uv":[8.666667,8.6,9.900001,7.366667],"rotation":0,"texture":"#0","tintindex":0}}},{"name":"cube","from":[-4.7296004,23.178135,4.0688],"to":[-0.14320016,29.780537,11.9312],"rotation":{"angle":0.0,"axis":"x","origin":[5.66,-2.4070663,8.0]},"faces":{"down":{"uv":[5.8,9.133333,4.9666667,10.6],"rotation":0,"texture":"#0","tintindex":0},"east":{"uv":[0.0,8.966667,1.4666667,7.5],"rotation":0,"texture":"#0","tintindex":0},"north":{"uv":[3.3,10.6,4.133333,9.133333],"rotation":0,"texture":"#0","tintindex":0},"south":{"uv":[4.133333,10.6,4.9666667,9.133333],"rotation":0,"texture":"#0","tintindex":0},"up":{"uv":[10.033334,5.8333335,9.200001,4.366667],"rotation":0,"texture":"#0","tintindex":0},"west":{"uv":[1.4666667,9.133333,2.9333334,7.666667],"rotation":0,"texture":"#0","tintindex":0}}},{"name":"cube","from":[-0.14320016,22.616535,3.5071998],"to":[15.02,30.342136,12.4928],"rotation":{"angle":0.0,"axis":"x","origin":[8.0,-2.4070663,8.0]},"faces":{"down":{"uv":[5.6,0.0,2.8,1.6666667],"rotation":0,"texture":"#0","tintindex":0},"east":{"uv":[5.6,3.7333333,7.2666664,2.0666666],"rotation":0,"texture":"#0","tintindex":0},"north":{"uv":[0.0,1.6666667,2.8,0.0],"rotation":0,"texture":"#0","tintindex":0},"south":{"uv":[0.0,3.3333335,2.8,1.6666667],"rotation":0,"texture":"#0","tintindex":0},"up":{"uv":[5.6,3.3333335,2.8,1.6666667],"rotation":0,"texture":"#0","tintindex":0},"west":{"uv":[2.8,7.666667,4.4666667,6.0],"rotation":0,"texture":"#0","tintindex":0}}}],"display":{"head":{"translation":[0.0,32.453045,0.0],"rotation":[0.0,0.0,0.0],"scale":[3.8095,3.8095,3.8095]}}}