{"textures":{"0":"modelengine:entity/airship","1":"modelengine:entity/stearingwheel"},"elements":[{"name":"cube","from":[17.492,-1.8280001,4.724],"to":[30.596,-1.3600006,11.276],"rotation":{"angle":0.0,"axis":"x","origin":[2.5159988,8.0,8.0]},"faces":{"down":{"uv":[7.666667,4.8,5.2333336,6.0],"rotation":0,"texture":"#0","tintindex":0},"east":{"uv":[8.400001,1.9333334,9.6,2.0333333],"rotation":0,"texture":"#0","tintindex":0},"north":{"uv":[12.433333,9.933333,14.866667,10.033334],"rotation":0,"texture":"#0","tintindex":0},"south":{"uv":[12.433333,10.033334,14.866667,10.133333],"rotation":0,"texture":"#0","tintindex":0},"up":{"uv":[5.2333336,6.0,2.8,4.8],"rotation":0,"texture":"#0","tintindex":0},"west":{"uv":[12.633334,3.0333335,13.833334,3.1333332],"rotation":0,"texture":"#0","tintindex":0}}},{"name":"cube","from":[12.812,-0.8920002,5.66],"to":[15.152,1.9159995,10.34],"rotation":{"angle":0.0,"axis":"x","origin":[2.5159988,8.0,8.0]},"faces":{"down":{"uv":[3.1333332,12.166667,2.7000003,13.033333],"rotation":0,"texture":"#0","tintindex":0},"east":{"uv":[2.8,11.633334,3.6666667,12.166667],"rotation":0,"texture":"#0","tintindex":0},"north":{"uv":[4.533334,11.300001,4.9666667,11.833334],"rotation":0,"texture":"#0","tintindex":0},"south":{"uv":[3.9666667,12.533333,4.4,13.066668],"rotation":0,"texture":"#0","tintindex":0},"up":{"uv":[8.733334,13.0,8.3,12.133334],"rotation":0,"texture":"#0","tintindex":0},"west":{"uv":[11.633334,4.1000004,12.5,4.633333],"rotation":0,"texture":"#0","tintindex":0}}},{"name":"cube","from":[11.875999,-0.42400026,6.1280003],"to":[12.812,1.9159995,9.872],"rotation":{"angle":0.0,"axis":"x","origin":[2.5159988,8.0,8.0]},"faces":{"down":{"uv":[12.333334,12.800001,12.166667,13.5],"rotation":0,"texture":"#0","tintindex":0},"east":{"uv":[11.666667,12.366667,12.366667,12.800001],"rotation":0,"texture":"#0","tintindex":0},"north":{"uv":[13.2,10.666667,13.366667,11.1],"rotation":0,"texture":"#0","tintindex":0},"south":{"uv":[11.866667,13.2,12.033333,13.633334],"rotation":0,"texture":"#0","tintindex":0},"up":{"uv":[9.6,1.9333334,9.433333,1.2333333],"rotation":0,"texture":"#0","tintindex":0},"west":{"uv":[12.366667,12.133334,13.066668,12.566668],"rotation":0,"texture":"#0","tintindex":0}}},{"name":"cube","from":[10.939999,0.043999434,6.5959997],"to":[11.875999,1.9159995,9.404],"rotation":{"angle":0.0,"axis":"x","origin":[2.5159988,8.0,8.0]},"faces":{"down":{"uv":[10.833334,13.033333,10.666667,13.566668],"rotation":0,"texture":"#0","tintindex":0},"east":{"uv":[9.633333,0.8666667,10.166667,1.2],"rotation":0,"texture":"#0","tintindex":0},"north":{"uv":[11.900001,5.8,12.066668,6.133333],"rotation":0,"texture":"#0","tintindex":0},"south":{"uv":[9.866667,13.366667,10.033334,13.7],"rotation":0,"texture":"#0","tintindex":0},"up":{"uv":[13.2,11.1,13.033333,10.566668],"rotation":0,"texture":"#0","tintindex":0},"west":{"uv":[12.6,6.8333335,13.133334,7.166667],"rotation":0,"texture":"#0","tintindex":0}}},{"name":"cube","from":[10.003999,0.5120001,7.064],"to":[10.939999,1.9159995,8.936],"rotation":{"angle":0.0,"axis":"x","origin":[2.5159988,8.0,8.0]},"faces":{"down":{"uv":[13.566668,2.7000003,13.400001,3.0333335],"rotation":0,"texture":"#0","tintindex":0},"east":{"uv":[11.066668,6.166667,11.400001,6.4333334],"rotation":0,"texture":"#0","tintindex":0},"north":{"uv":[6.1,13.400001,6.2666664,13.666667],"rotation":0,"texture":"#0","tintindex":0},"south":{"uv":[6.2666664,13.400001,6.4333334,13.666667],"rotation":0,"texture":"#0","tintindex":0},"up":{"uv":[13.566668,0.43333334,13.400001,0.10000001],"rotation":0,"texture":"#0","tintindex":0},"west":{"uv":[10.833334,13.033333,11.166667,13.300001],"rotation":0,"texture":"#0","tintindex":0}}},{"name":"cube","from":[5.791999,0.9799998,7.532],"to":[10.003999,1.9159995,8.468],"rotation":{"angle":0.0,"axis":"x","origin":[2.5159988,8.0,8.0]},"faces":{"down":{"uv":[13.466667,5.9666667,12.7,6.133333],"rotation":0,"texture":"#0","tintindex":0},"east":{"uv":[1.2333333,8.966667,1.4,9.133333],"rotation":0,"texture":"#0","tintindex":0},"north":{"uv":[12.633334,2.7000003,13.400001,2.8666668],"rotation":0,"texture":"#0","tintindex":0},"south":{"uv":[12.633334,2.8666668,13.400001,3.0333335],"rotation":0,"texture":"#0","tintindex":0},"up":{"uv":[13.466667,5.9666667,12.7,5.8],"rotation":0,"texture":"#0","tintindex":0},"west":{"uv":[10.3,3.5666666,10.466667,3.7333333],"rotation":0,"texture":"#0","tintindex":0}}},{"name":"cube","from":[23.576,-1.3600006,5.192],"to":[31.064003,5.66,10.808001],"rotation":{"angle":0.0,"axis":"x","origin":[2.5159988,8.0,8.0]},"faces":{"down":{"uv":[8.666667,9.066668,7.2666664,10.1],"rotation":0,"texture":"#0","tintindex":0},"east":{"uv":[1.2333333,9.133333,2.266667,10.433333],"rotation":0,"texture":"#0","tintindex":0},"north":{"uv":[7.8,4.766667,9.200001,6.066667],"rotation":0,"texture":"#0","tintindex":0},"south":{"uv":[7.8,6.066667,9.200001,7.366667],"rotation":0,"texture":"#0","tintindex":0},"up":{"uv":[7.2666664,10.1,5.866667,9.066668],"rotation":0,"texture":"#0","tintindex":0},"west":{"uv":[2.266667,9.133333,3.3,10.433333],"rotation":0,"texture":"#0","tintindex":0}}},{"name":"cube","from":[31.064003,-0.8920002,5.66],"to":[31.532001,1.9159995,10.34],"rotation":{"angle":0.0,"axis":"x","origin":[2.5159988,8.0,8.0]},"faces":{"down":{"uv":[13.166667,1.3333334,13.066668,2.2],"rotation":0,"texture":"#0","tintindex":0},"east":{"uv":[11.633334,4.633333,12.5,5.166667],"rotation":0,"texture":"#0","tintindex":0},"north":{"uv":[5.9000006,13.400001,6.0,13.933333],"rotation":0,"texture":"#0","tintindex":0},"south":{"uv":[6.0,13.400001,6.1,13.933333],"rotation":0,"texture":"#0","tintindex":0},"up":{"uv":[7.8333335,13.900001,7.7333336,13.033333],"rotation":0,"texture":"#0","tintindex":0},"west":{"uv":[11.733334,10.566668,12.6,11.1],"rotation":0,"texture":"#0","tintindex":0}}},{"name":"cube","from":[22.64,-1.3600006,4.724],"to":[30.596,1.9159995,5.192],"rotation":{"angle":0.0,"axis":"x","origin":[2.5159988,8.0,8.0]},"faces":{"down":{"uv":[14.0,5.5,12.533333,5.6],"rotation":0,"texture":"#0","tintindex":0},"east":{"uv":[2.9666667,13.333334,3.0666666,13.933333],"rotation":0,"texture":"#0","tintindex":0},"north":{"uv":[10.033334,6.4333334,11.5,7.033334],"rotation":0,"texture":"#0","tintindex":0},"south":{"uv":[10.333334,9.366667,11.800001,9.966667],"rotation":0,"texture":"#0","tintindex":0},"up":{"uv":[14.0,3.9,12.533333,3.8],"rotation":0,"texture":"#0","tintindex":0},"west":{"uv":[3.0666666,13.333334,3.1666667,13.933333],"rotation":0,"texture":"#0","tintindex":0}}},{"name":"cube","from":[31.064003,1.9159995,5.192],"to":[32.0,5.66,10.808001],"rotation":{"angle":0.0,"axis":"x","origin":[2.5159988,8.0,8.0]},"faces":{"down":{"uv":[2.266667,12.633334,2.1000001,13.666667],"rotation":0,"texture":"#0","tintindex":0},"east":{"uv":[8.400001,1.2333333,9.433333,1.9333334],"rotation":0,"texture":"#0","tintindex":0},"north":{"uv":[12.833334,7.9666667,13.0,8.666667],"rotation":0,"texture":"#0","tintindex":0},"south":{"uv":[12.866667,10.566668,13.033333,11.266666],"rotation":0,"texture":"#0","tintindex":0},"up":{"uv":[2.1000001,13.666667,1.9333334,12.633334],"rotation":0,"texture":"#0","tintindex":0},"west":{"uv":[3.9666667,10.6,5.0,11.300001],"rotation":0,"texture":"#0","tintindex":0}}},{"name":"cube","from":[31.064003,5.66,5.66],"to":[31.532001,6.1280003,10.34],"rotation":{"angle":0.0,"axis":"x","origin":[2.5159988,8.0,8.0]},"faces":{"down":{"uv":[4.166667,13.066668,4.0666666,13.933333],"rotation":0,"texture":"#0","tintindex":0},"east":{"uv":[12.866667,11.900001,13.733334,12.0],"rotation":0,"texture":"#0","tintindex":0},"north":{"uv":[3.5666666,14.033333,3.6666667,14.133334],"rotation":0,"texture":"#0","tintindex":0},"south":{"uv":[4.4666667,14.033333,4.5666666,14.133334],"rotation":0,"texture":"#0","tintindex":0},"up":{"uv":[4.0666666,13.933333,3.9666667,13.066668],"rotation":0,"texture":"#0","tintindex":0},"west":{"uv":[12.866667,12.0,13.733334,12.1],"rotation":0,"texture":"#0","tintindex":0}}},{"name":"cube","from":[24.043999,5.66,5.66],"to":[31.064003,6.1280003,10.34],"rotation":{"angle":0.0,"axis":"x","origin":[2.5159988,8.0,8.0]},"faces":{"down":{"uv":[11.166667,2.7000003,9.866667,3.5666666],"rotation":0,"texture":"#0","tintindex":0},"east":{"uv":[12.933333,1.1333334,13.800001,1.2333333],"rotation":0,"texture":"#0","tintindex":0},"north":{"uv":[12.633334,1.2333333,13.933333,1.3333334],"rotation":0,"texture":"#0","tintindex":0},"south":{"uv":[12.633334,2.6000001,13.933333,2.7000003],"rotation":0,"texture":"#0","tintindex":0},"up":{"uv":[10.933333,0.8666667,9.633333,0.0],"rotation":0,"texture":"#0","tintindex":0},"west":{"uv":[13.0,8.566668,13.866667,8.666667],"rotation":0,"texture":"#0","tintindex":0}}},{"name":"cube","from":[15.152,-1.3600006,5.66],"to":[17.492,-0.8920002,10.34],"rotation":{"angle":0.0,"axis":"x","origin":[2.5159988,8.0,8.0]},"faces":{"down":{"uv":[7.866667,12.166667,7.4333334,13.033333],"rotation":0,"texture":"#0","tintindex":0},"east":{"uv":[13.033333,11.1,13.900001,11.2],"rotation":0,"texture":"#0","tintindex":0},"north":{"uv":[13.5,7.5,13.933333,7.6],"rotation":0,"texture":"#0","tintindex":0},"south":{"uv":[13.5,13.066668,13.933333,13.166667],"rotation":0,"texture":"#0","tintindex":0},"up":{"uv":[3.5666666,13.033333,3.1333332,12.166667],"rotation":0,"texture":"#0","tintindex":0},"west":{"uv":[13.066668,2.2,13.933333,2.3000002],"rotation":0,"texture":"#0","tintindex":0}}},{"name":"cube","from":[15.152,-1.3600006,5.192],"to":[17.492,1.9159995,5.66],"rotation":{"angle":0.0,"axis":"x","origin":[2.5159988,8.0,8.0]},"faces":{"down":{"uv":[13.966667,13.400001,13.533333,13.5],"rotation":0,"texture":"#0","tintindex":0},"east":{"uv":[3.1666667,13.333334,3.266667,13.933333],"rotation":0,"texture":"#0","tintindex":0},"north":{"uv":[10.066668,12.433333,10.5,13.033333],"rotation":0,"texture":"#0","tintindex":0},"south":{"uv":[10.5,12.433333,10.933333,13.033333],"rotation":0,"texture":"#0","tintindex":0},"up":{"uv":[13.966667,13.400001,13.533333,13.300001],"rotation":0,"texture":"#0","tintindex":0},"west":{"uv":[3.266667,13.333334,3.3666668,13.933333],"rotation":0,"texture":"#0","tintindex":0}}},{"name":"cube","from":[15.152,-0.8920002,5.66],"to":[15.619999,1.4479997,10.34],"rotation":{"angle":0.0,"axis":"x","origin":[2.5159988,8.0,8.0]},"faces":{"down":{"uv":[4.366667,13.066668,4.266667,13.933333],"rotation":0,"texture":"#0","tintindex":0},"east":{"uv":[12.1,1.3666667,12.966667,1.8000001],"rotation":0,"texture":"#0","tintindex":0},"north":{"uv":[2.5333333,13.466667,2.6333334,13.900001],"rotation":0,"texture":"#0","tintindex":0},"south":{"uv":[0.6,13.533333,0.7,13.966667],"rotation":0,"texture":"#0","tintindex":0},"up":{"uv":[4.266667,13.933333,4.166667,13.066668],"rotation":0,"texture":"#0","tintindex":0},"west":{"uv":[0.6333333,12.266666,1.5,12.7],"rotation":0,"texture":"#0","tintindex":0}}},{"name":"cube","from":[15.619999,-0.8920002,5.66],"to":[16.087997,0.9799998,10.34],"rotation":{"angle":0.0,"axis":"x","origin":[2.5159988,8.0,8.0]},"faces":{"down":{"uv":[13.133334,13.1,13.033333,13.966667],"rotation":0,"texture":"#0","tintindex":0},"east":{"uv":[7.9333334,4.366667,8.8,4.7000003],"rotation":0,"texture":"#0","tintindex":0},"north":{"uv":[2.4,13.833334,2.5,14.166667],"rotation":0,"texture":"#0","tintindex":0},"south":{"uv":[7.2000003,13.833334,7.3,14.166667],"rotation":0,"texture":"#0","tintindex":0},"up":{"uv":[13.2,0.8666667,13.1,0.0],"rotation":0,"texture":"#0","tintindex":0},"west":{"uv":[12.433333,9.1,13.300001,9.433333],"rotation":0,"texture":"#0","tintindex":0}}},{"name":"cube","from":[16.087997,-0.8920002,5.66],"to":[16.556,0.5120001,10.34],"rotation":{"angle":0.0,"axis":"x","origin":[2.5159988,8.0,8.0]},"faces":{"down":{"uv":[1.7,13.133334,1.6000001,14.0],"rotation":0,"texture":"#0","tintindex":0},"east":{"uv":[7.8,7.366667,8.666667,7.633333],"rotation":0,"texture":"#0","tintindex":0},"north":{"uv":[11.400001,6.166667,11.5,6.4333334],"rotation":0,"texture":"#0","tintindex":0},"south":{"uv":[11.666667,9.1,11.766666,9.366667],"rotation":0,"texture":"#0","tintindex":0},"up":{"uv":[1.6000001,14.0,1.5,13.133334],"rotation":0,"texture":"#0","tintindex":0},"west":{"uv":[10.033334,7.033334,10.900001,7.3],"rotation":0,"texture":"#0","tintindex":0}}},{"name":"cube","from":[16.556,-0.8920002,5.66],"to":[17.023998,0.043999434,10.34],"rotation":{"angle":0.0,"axis":"x","origin":[2.5159988,8.0,8.0]},"faces":{"down":{"uv":[1.9,13.133334,1.8000001,14.0],"rotation":0,"texture":"#0","tintindex":0},"east":{"uv":[1.4666667,7.5,2.3333335,7.666667],"rotation":0,"texture":"#0","tintindex":0},"north":{"uv":[8.566668,11.133334,8.666667,11.300001],"rotation":0,"texture":"#0","tintindex":0},"south":{"uv":[10.666667,13.966667,10.766666,14.133334],"rotation":0,"texture":"#0","tintindex":0},"up":{"uv":[1.8000001,14.0,1.7,13.133334],"rotation":0,"texture":"#0","tintindex":0},"west":{"uv":[12.633334,2.4333334,13.5,2.6000001],"rotation":0,"texture":"#0","tintindex":0}}},{"name":"cube","from":[16.556,0.043999434,6.92],"to":[17.023998,0.5120001,9.08],"rotation":{"angle":0.0,"axis":"x","origin":[2.5159988,8.0,8.0]},"faces":{"down":{"uv":[1.9,13.133334,1.8000001,14.0],"rotation":0,"texture":"#0","tintindex":0},"east":{"uv":[1.4666667,7.5,2.3333335,7.666667],"rotation":0,"texture":"#0","tintindex":0},"north":{"uv":[8.566668,11.133334,8.666667,11.300001],"rotation":0,"texture":"#0","tintindex":0},"south":{"uv":[10.666667,13.966667,10.766666,14.133334],"rotation":0,"texture":"#0","tintindex":0},"up":{"uv":[1.8000001,14.0,1.7,13.133334],"rotation":0,"texture":"#0","tintindex":0},"west":{"uv":[12.633334,2.4333334,13.5,2.6000001],"rotation":0,"texture":"#0","tintindex":0}}},{"name":"cube","from":[17.023998,-0.42400026,6.92],"to":[17.492,0.043999434,9.08],"rotation":{"angle":0.0,"axis":"x","origin":[2.5159988,8.0,8.0]},"faces":{"down":{"uv":[1.9,13.133334,1.8000001,14.0],"rotation":0,"texture":"#0","tintindex":0},"east":{"uv":[1.4666667,7.5,2.3333335,7.666667],"rotation":0,"texture":"#0","tintindex":0},"north":{"uv":[8.566668,11.133334,8.666667,11.300001],"rotation":0,"texture":"#0","tintindex":0},"south":{"uv":[10.666667,13.966667,10.766666,14.133334],"rotation":0,"texture":"#0","tintindex":0},"up":{"uv":[1.8000001,14.0,1.7,13.133334],"rotation":0,"texture":"#0","tintindex":0},"west":{"uv":[12.633334,2.4333334,13.5,2.6000001],"rotation":0,"texture":"#0","tintindex":0}}},{"name":"cube","from":[17.492,-1.3600006,6.92],"to":[17.96,-0.8920002,9.08],"rotation":{"angle":0.0,"axis":"x","origin":[2.5159988,8.0,8.0]},"faces":{"down":{"uv":[1.9,13.133334,1.8000001,14.0],"rotation":0,"texture":"#0","tintindex":0},"east":{"uv":[1.4666667,7.5,2.3333335,7.666667],"rotation":0,"texture":"#0","tintindex":0},"north":{"uv":[8.566668,11.133334,8.666667,11.300001],"rotation":0,"texture":"#0","tintindex":0},"south":{"uv":[10.666667,13.966667,10.766666,14.133334],"rotation":0,"texture":"#0","tintindex":0},"up":{"uv":[1.8000001,14.0,1.7,13.133334],"rotation":0,"texture":"#0","tintindex":0},"west":{"uv":[12.633334,2.4333334,13.5,2.6000001],"rotation":0,"texture":"#0","tintindex":0}}},{"name":"cube","from":[17.96,-1.3600006,6.92],"to":[18.427998,-0.8920002,9.08],"rotation":{"angle":0.0,"axis":"x","origin":[2.5159988,8.0,8.0]},"faces":{"down":{"uv":[1.9,13.133334,1.8000001,14.0],"rotation":0,"texture":"#0","tintindex":0},"east":{"uv":[1.4666667,7.5,2.3333335,7.666667],"rotation":0,"texture":"#0","tintindex":0},"north":{"uv":[8.566668,11.133334,8.666667,11.300001],"rotation":0,"texture":"#0","tintindex":0},"south":{"uv":[10.666667,13.966667,10.766666,14.133334],"rotation":0,"texture":"#0","tintindex":0},"up":{"uv":[1.8000001,14.0,1.7,13.133334],"rotation":0,"texture":"#0","tintindex":0},"west":{"uv":[12.633334,2.4333334,13.5,2.6000001],"rotation":0,"texture":"#0","tintindex":0}}},{"name":"cube","from":[17.492,-0.8920002,6.92],"to":[17.96,-0.42400026,9.08],"rotation":{"angle":0.0,"axis":"x","origin":[2.5159988,8.0,8.0]},"faces":{"down":{"uv":[1.9,13.133334,1.8000001,14.0],"rotation":0,"texture":"#0","tintindex":0},"east":{"uv":[1.4666667,7.5,2.3333335,7.666667],"rotation":0,"texture":"#0","tintindex":0},"north":{"uv":[8.566668,11.133334,8.666667,11.300001],"rotation":0,"texture":"#0","tintindex":0},"south":{"uv":[10.666667,13.966667,10.766666,14.133334],"rotation":0,"texture":"#0","tintindex":0},"up":{"uv":[1.8000001,14.0,1.7,13.133334],"rotation":0,"texture":"#0","tintindex":0},"west":{"uv":[12.633334,2.4333334,13.5,2.6000001],"rotation":0,"texture":"#0","tintindex":0}}},{"name":"cube","from":[17.023998,-0.8920002,5.66],"to":[17.492,-0.42400026,10.34],"rotation":{"angle":0.0,"axis":"x","origin":[2.5159988,8.0,8.0]},"faces":{"down":{"uv":[13.233334,13.1,13.133334,13.966667],"rotation":0,"texture":"#0","tintindex":0},"east":{"uv":[13.066668,2.3000002,13.933333,2.4],"rotation":0,"texture":"#0","tintindex":0},"north":{"uv":[4.5666666,14.033333,4.666667,14.133334],"rotation":0,"texture":"#0","tintindex":0},"south":{"uv":[4.666667,14.033333,4.766667,14.133334],"rotation":0,"texture":"#0","tintindex":0},"up":{"uv":[13.233334,7.7000003,13.133334,6.8333335],"rotation":0,"texture":"#0","tintindex":0},"west":{"uv":[13.066668,11.2,13.933333,11.300001],"rotation":0,"texture":"#0","tintindex":0}}},{"name":"cube","from":[24.043999,1.9159995,4.724],"to":[30.128002,2.384,5.192],"rotation":{"angle":0.0,"axis":"x","origin":[2.5159988,8.0,8.0]},"faces":{"down":{"uv":[13.933333,4.7333336,12.800001,4.8333335],"rotation":0,"texture":"#0","tintindex":0},"east":{"uv":[4.766667,14.033333,4.866667,14.133334],"rotation":0,"texture":"#0","tintindex":0},"north":{"uv":[12.7,6.133333,13.833334,6.2333336],"rotation":0,"texture":"#0","tintindex":0},"south":{"uv":[12.7,6.2333336,13.833334,6.3333335],"rotation":0,"texture":"#0","tintindex":0},"up":{"uv":[13.833334,6.4333334,12.7,6.3333335],"rotation":0,"texture":"#0","tintindex":0},"west":{"uv":[4.866667,14.033333,4.9666667,14.133334],"rotation":0,"texture":"#0","tintindex":0}}},{"name":"cube","from":[24.98,2.384,4.724],"to":[29.191998,2.8519998,5.192],"rotation":{"angle":0.0,"axis":"x","origin":[2.5159988,8.0,8.0]},"faces":{"down":{"uv":[13.933333,6.4333334,13.166667,6.533334],"rotation":0,"texture":"#0","tintindex":0},"east":{"uv":[5.566667,14.033333,5.666667,14.133334],"rotation":0,"texture":"#0","tintindex":0},"north":{"uv":[13.1,3.7000003,13.866667,3.8],"rotation":0,"texture":"#0","tintindex":0},"south":{"uv":[13.166667,4.5,13.933333,4.6000004],"rotation":0,"texture":"#0","tintindex":0},"up":{"uv":[13.933333,4.7000003,13.166667,4.6000004],"rotation":0,"texture":"#0","tintindex":0},"west":{"uv":[5.666667,14.033333,5.7666664,14.133334],"rotation":0,"texture":"#0","tintindex":0}}},{"name":"cube","from":[15.152,-1.8280001,5.66],"to":[17.492,-1.3600006,10.34],"rotation":{"angle":0.0,"axis":"x","origin":[2.5159988,8.0,8.0]},"faces":{"down":{"uv":[9.166667,12.333334,8.733334,13.2],"rotation":0,"texture":"#0","tintindex":0},"east":{"uv":[13.066668,11.300001,13.933333,11.400001],"rotation":0,"texture":"#0","tintindex":0},"north":{"uv":[13.533333,13.5,13.966667,13.6],"rotation":0,"texture":"#0","tintindex":0},"south":{"uv":[13.566668,0.10000001,14.0,0.20000002],"rotation":0,"texture":"#0","tintindex":0},"up":{"uv":[1.9333334,13.133334,1.5,12.266666],"rotation":0,"texture":"#0","tintindex":0},"west":{"uv":[13.066668,11.400001,13.933333,11.5],"rotation":0,"texture":"#0","tintindex":0}}},{"name":"cube","from":[17.492,-2.2960005,5.192],"to":[30.128002,-1.8280001,10.808001],"rotation":{"angle":0.0,"axis":"x","origin":[2.5159988,8.0,8.0]},"faces":{"down":{"uv":[9.6,2.0666666,7.2666664,3.1000001],"rotation":0,"texture":"#0","tintindex":0},"east":{"uv":[12.833334,8.966667,13.866667,9.066668],"rotation":0,"texture":"#0","tintindex":0},"north":{"uv":[12.433333,10.133333,14.766666,10.233334],"rotation":0,"texture":"#0","tintindex":0},"south":{"uv":[12.433333,10.233334,14.766666,10.333334],"rotation":0,"texture":"#0","tintindex":0},"up":{"uv":[7.9333334,4.766667,5.6,3.7333333],"rotation":0,"texture":"#0","tintindex":0},"west":{"uv":[12.866667,11.800001,13.900001,11.900001],"rotation":0,"texture":"#0","tintindex":0}}},{"name":"cube","from":[12.812,-1.3600006,6.1280003],"to":[15.152,-0.8920002,9.872],"rotation":{"angle":0.0,"axis":"x","origin":[2.5159988,8.0,8.0]},"faces":{"down":{"uv":[12.833334,8.400001,12.400001,9.1],"rotation":0,"texture":"#0","tintindex":0},"east":{"uv":[11.166667,3.4666667,11.866667,3.5666666],"rotation":0,"texture":"#0","tintindex":0},"north":{"uv":[13.566668,0.20000002,14.0,0.3],"rotation":0,"texture":"#0","tintindex":0},"south":{"uv":[13.566668,0.3,14.0,0.40000004],"rotation":0,"texture":"#0","tintindex":0},"up":{"uv":[12.833334,8.400001,12.400001,7.7000003],"rotation":0,"texture":"#0","tintindex":0},"west":{"uv":[13.233334,13.2,13.933333,13.300001],"rotation":0,"texture":"#0","tintindex":0}}},{"name":"cube","from":[11.875999,-0.8920002,6.5959997],"to":[12.812,-0.42400026,9.404],"rotation":{"angle":0.0,"axis":"x","origin":[2.5159988,8.0,8.0]},"faces":{"down":{"uv":[13.2,12.566668,13.033333,13.1],"rotation":0,"texture":"#0","tintindex":0},"east":{"uv":[13.400001,0.43333334,13.933333,0.53333336],"rotation":0,"texture":"#0","tintindex":0},"north":{"uv":[6.3,13.666667,6.4666667,13.766666],"rotation":0,"texture":"#0","tintindex":0},"south":{"uv":[13.966667,0.0,14.133334,0.10000001],"rotation":0,"texture":"#0","tintindex":0},"up":{"uv":[11.333334,13.566668,11.166667,13.033333],"rotation":0,"texture":"#0","tintindex":0},"west":{"uv":[13.400001,0.53333336,13.933333,0.6333333],"rotation":0,"texture":"#0","tintindex":0}}},{"name":"cube","from":[10.939999,-0.42400026,7.064],"to":[11.875999,0.043999434,8.936],"rotation":{"angle":0.0,"axis":"x","origin":[2.5159988,8.0,8.0]},"faces":{"down":{"uv":[5.9000006,13.400001,5.7333336,13.733334],"rotation":0,"texture":"#0","tintindex":0},"east":{"uv":[12.066668,7.7000003,12.400001,7.8],"rotation":0,"texture":"#0","tintindex":0},"north":{"uv":[13.966667,10.566668,14.133334,10.666667],"rotation":0,"texture":"#0","tintindex":0},"south":{"uv":[12.133334,13.966667,12.300001,14.066668],"rotation":0,"texture":"#0","tintindex":0},"up":{"uv":[5.7333336,13.733334,5.566667,13.400001],"rotation":0,"texture":"#0","tintindex":0},"west":{"uv":[13.566668,2.0333333,13.900001,2.1333334],"rotation":0,"texture":"#0","tintindex":0}}},{"name":"cube","from":[10.003999,0.043999434,7.532],"to":[10.939999,0.5120001,8.468],"rotation":{"angle":0.0,"axis":"x","origin":[2.5159988,8.0,8.0]},"faces":{"down":{"uv":[12.133334,13.833334,11.966667,14.0],"rotation":0,"texture":"#0","tintindex":0},"east":{"uv":[13.966667,13.300001,14.133334,13.400001],"rotation":0,"texture":"#0","tintindex":0},"north":{"uv":[13.033333,13.966667,13.2,14.066668],"rotation":0,"texture":"#0","tintindex":0},"south":{"uv":[13.966667,13.400001,14.133334,13.5],"rotation":0,"texture":"#0","tintindex":0},"up":{"uv":[3.3,10.6,3.1333332,10.433333],"rotation":0,"texture":"#0","tintindex":0},"west":{"uv":[13.966667,13.5,14.133334,13.6],"rotation":0,"texture":"#0","tintindex":0}}},{"name":"cube","from":[7.6639986,0.5120001,7.532],"to":[10.003999,0.9799998,8.468],"rotation":{"angle":0.0,"axis":"x","origin":[2.5159988,8.0,8.0]},"faces":{"down":{"uv":[10.3,3.5666666,9.866667,3.7333333],"rotation":0,"texture":"#0","tintindex":0},"east":{"uv":[14.0,0.10000001,14.166667,0.20000002],"rotation":0,"texture":"#0","tintindex":0},"north":{"uv":[13.566668,1.3333334,14.0,1.4333334],"rotation":0,"texture":"#0","tintindex":0},"south":{"uv":[13.566668,1.4333334,14.0,1.5333333],"rotation":0,"texture":"#0","tintindex":0},"up":{"uv":[2.766667,7.666667,2.3333335,7.5],"rotation":0,"texture":"#0","tintindex":0},"west":{"uv":[0.16666667,14.0,0.33333334,14.1],"rotation":0,"texture":"#0","tintindex":0}}},{"name":"cube","from":[22.64,-1.3600006,10.808001],"to":[30.596,1.9159995,11.276],"rotation":{"angle":0.0,"axis":"x","origin":[2.5159988,8.0,8.0]},"faces":{"down":{"uv":[14.0,5.7000003,12.533333,5.8],"rotation":0,"texture":"#0","tintindex":0},"east":{"uv":[3.3666668,13.333334,3.4666667,13.933333],"rotation":0,"texture":"#0","tintindex":0},"north":{"uv":[10.333334,9.966667,11.800001,10.566668],"rotation":0,"texture":"#0","tintindex":0},"south":{"uv":[0.8333334,10.433333,2.3000002,11.033333],"rotation":0,"texture":"#0","tintindex":0},"up":{"uv":[14.0,5.7000003,12.533333,5.6],"rotation":0,"texture":"#0","tintindex":0},"west":{"uv":[3.4666667,13.333334,3.5666666,13.933333],"rotation":0,"texture":"#0","tintindex":0}}},{"name":"cube","from":[15.152,-1.3600006,10.34],"to":[17.492,1.9159995,10.808001],"rotation":{"angle":0.0,"axis":"x","origin":[2.5159988,8.0,8.0]},"faces":{"down":{"uv":[14.0,1.9333334,13.566668,2.0333333],"rotation":0,"texture":"#0","tintindex":0},"east":{"uv":[7.4333334,13.333334,7.533334,13.933333],"rotation":0,"texture":"#0","tintindex":0},"north":{"uv":[10.933333,12.433333,11.366667,13.033333],"rotation":0,"texture":"#0","tintindex":0},"south":{"uv":[12.466667,0.0,12.900001,0.6],"rotation":0,"texture":"#0","tintindex":0},"up":{"uv":[14.0,1.6333334,13.566668,1.5333333],"rotation":0,"texture":"#0","tintindex":0},"west":{"uv":[7.533334,13.333334,7.633333,13.933333],"rotation":0,"texture":"#0","tintindex":0}}},{"name":"cube","from":[24.98,2.384,10.808001],"to":[29.191998,2.8519998,11.276],"rotation":{"angle":0.0,"axis":"x","origin":[2.5159988,8.0,8.0]},"faces":{"down":{"uv":[13.966667,10.566668,13.2,10.666667],"rotation":0,"texture":"#0","tintindex":0},"east":{"uv":[14.033333,6.0,14.133334,6.1],"rotation":0,"texture":"#0","tintindex":0},"north":{"uv":[13.166667,6.533334,13.933333,6.633333],"rotation":0,"texture":"#0","tintindex":0},"south":{"uv":[13.166667,6.633333,13.933333,6.7333336],"rotation":0,"texture":"#0","tintindex":0},"up":{"uv":[13.933333,6.8333335,13.166667,6.7333336],"rotation":0,"texture":"#0","tintindex":0},"west":{"uv":[14.033333,6.1,14.133334,6.2000003],"rotation":0,"texture":"#0","tintindex":0}}},{"name":"cube","from":[24.043999,1.9159995,10.808001],"to":[30.128002,2.384,11.276],"rotation":{"angle":0.0,"axis":"x","origin":[2.5159988,8.0,8.0]},"faces":{"down":{"uv":[13.966667,8.866667,12.833334,8.966667],"rotation":0,"texture":"#0","tintindex":0},"east":{"uv":[14.033333,6.2000003,14.133334,6.3],"rotation":0,"texture":"#0","tintindex":0},"north":{"uv":[12.800001,4.8333335,13.933333,4.9333334],"rotation":0,"texture":"#0","tintindex":0},"south":{"uv":[12.833334,8.666667,13.966667,8.766666],"rotation":0,"texture":"#0","tintindex":0},"up":{"uv":[13.966667,8.866667,12.833334,8.766666],"rotation":0,"texture":"#0","tintindex":0},"west":{"uv":[14.033333,6.3,14.133334,6.4000006],"rotation":0,"texture":"#0","tintindex":0}}},{"name":"cube","from":[17.492,-1.3600006,4.724],"to":[18.427998,1.9159995,5.192],"rotation":{"angle":0.0,"axis":"x","origin":[2.5159988,8.0,8.0]},"faces":{"down":{"uv":[14.166667,0.3,14.0,0.40000004],"rotation":0,"texture":"#0","tintindex":0},"east":{"uv":[7.633333,13.333334,7.7333336,13.933333],"rotation":0,"texture":"#0","tintindex":0},"north":{"uv":[12.933333,0.53333336,13.1,1.1333334],"rotation":0,"texture":"#0","tintindex":0},"south":{"uv":[13.0,4.1000004,13.166667,4.7000003],"rotation":0,"texture":"#0","tintindex":0},"up":{"uv":[14.166667,0.3,14.0,0.20000002],"rotation":0,"texture":"#0","tintindex":0},"west":{"uv":[10.066668,13.333334,10.166667,13.933333],"rotation":0,"texture":"#0","tintindex":0}}},{"name":"cube","from":[17.492,-1.3600006,10.808001],"to":[18.427998,1.9159995,11.276],"rotation":{"angle":0.0,"axis":"x","origin":[2.5159988,8.0,8.0]},"faces":{"down":{"uv":[14.166667,0.5666667,14.0,0.6666667],"rotation":0,"texture":"#0","tintindex":0},"east":{"uv":[10.166667,13.333334,10.266666,13.933333],"rotation":0,"texture":"#0","tintindex":0},"north":{"uv":[13.0,7.9666667,13.166667,8.566668],"rotation":0,"texture":"#0","tintindex":0},"south":{"uv":[8.5,13.0,8.666667,13.6],"rotation":0,"texture":"#0","tintindex":0},"up":{"uv":[0.5,14.1,0.33333334,14.0],"rotation":0,"texture":"#0","tintindex":0},"west":{"uv":[10.266666,13.333334,10.366667,13.933333],"rotation":0,"texture":"#0","tintindex":0}}},{"name":"cube","from":[18.427998,-1.3600006,4.724],"to":[18.896,-0.8920002,5.192],"rotation":{"angle":0.0,"axis":"x","origin":[2.5159988,8.0,8.0]},"faces":{"down":{"uv":[8.866667,14.033333,8.766666,14.133334],"rotation":0,"texture":"#0","tintindex":0},"east":{"uv":[14.033333,6.7000003,14.133334,6.8],"rotation":0,"texture":"#0","tintindex":0},"north":{"uv":[14.033333,6.6,14.133334,6.7000003],"rotation":0,"texture":"#0","tintindex":0},"south":{"uv":[8.3,14.033333,8.400001,14.133334],"rotation":0,"texture":"#0","tintindex":0},"up":{"uv":[8.766666,14.133334,8.666667,14.033333],"rotation":0,"texture":"#0","tintindex":0},"west":{"uv":[8.400001,14.033333,8.5,14.133334],"rotation":0,"texture":"#0","tintindex":0}}},{"name":"cube","from":[18.427998,-1.3600006,10.808001],"to":[18.896,-0.8920002,11.276],"rotation":{"angle":0.0,"axis":"x","origin":[2.5159988,8.0,8.0]},"faces":{"down":{"uv":[14.133334,10.866667,14.033333,10.966667],"rotation":0,"texture":"#0","tintindex":0},"east":{"uv":[8.966667,14.033333,9.066668,14.133334],"rotation":0,"texture":"#0","tintindex":0},"north":{"uv":[8.866667,14.033333,8.966667,14.133334],"rotation":0,"texture":"#0","tintindex":0},"south":{"uv":[9.066668,14.033333,9.166667,14.133334],"rotation":0,"texture":"#0","tintindex":0},"up":{"uv":[14.133334,10.866667,14.033333,10.766666],"rotation":0,"texture":"#0","tintindex":0},"west":{"uv":[14.033333,10.666667,14.133334,10.766666],"rotation":0,"texture":"#0","tintindex":0}}},{"name":"cube","from":[22.171997,-1.3600006,4.724],"to":[22.64,-0.8920002,5.192],"rotation":{"angle":0.0,"axis":"x","origin":[2.5159988,8.0,8.0]},"faces":{"down":{"uv":[11.966667,14.033333,11.866667,14.133334],"rotation":0,"texture":"#0","tintindex":0},"east":{"uv":[14.033333,11.166667,14.133334,11.266666],"rotation":0,"texture":"#0","tintindex":0},"north":{"uv":[14.033333,10.966667,14.133334,11.066668],"rotation":0,"texture":"#0","tintindex":0},"south":{"uv":[14.033333,11.266666,14.133334,11.366667],"rotation":0,"texture":"#0","tintindex":0},"up":{"uv":[14.133334,11.933333,14.033333,11.833334],"rotation":0,"texture":"#0","tintindex":0},"west":{"uv":[11.766666,14.033333,11.866667,14.133334],"rotation":0,"texture":"#0","tintindex":0}}},{"name":"cube","from":[22.171997,-1.3600006,10.808001],"to":[22.64,-0.8920002,11.276],"rotation":{"angle":0.0,"axis":"x","origin":[2.5159988,8.0,8.0]},"faces":{"down":{"uv":[14.133334,13.0,14.033333,13.1],"rotation":0,"texture":"#0","tintindex":0},"east":{"uv":[14.033333,12.433333,14.133334,12.533333],"rotation":0,"texture":"#0","tintindex":0},"north":{"uv":[14.033333,11.933333,14.133334,12.033333],"rotation":0,"texture":"#0","tintindex":0},"south":{"uv":[14.033333,12.533333,14.133334,12.633334],"rotation":0,"texture":"#0","tintindex":0},"up":{"uv":[14.133334,12.833334,14.033333,12.733334],"rotation":0,"texture":"#0","tintindex":0},"west":{"uv":[14.033333,12.633334,14.133334,12.733334],"rotation":0,"texture":"#0","tintindex":0}}},{"name":"cube","from":[17.96,1.9159995,4.724],"to":[18.427998,2.384,5.192],"rotation":{"angle":0.0,"axis":"x","origin":[2.5159988,8.0,8.0]},"faces":{"down":{"uv":[0.10000001,14.066668,0.0,14.166667],"rotation":0,"texture":"#0","tintindex":0},"east":{"uv":[14.033333,13.6,14.133334,13.7],"rotation":0,"texture":"#0","tintindex":0},"north":{"uv":[14.033333,13.1,14.133334,13.2],"rotation":0,"texture":"#0","tintindex":0},"south":{"uv":[14.033333,13.7,14.133334,13.800001],"rotation":0,"texture":"#0","tintindex":0},"up":{"uv":[14.133334,14.0,14.033333,13.900001],"rotation":0,"texture":"#0","tintindex":0},"west":{"uv":[14.033333,13.800001,14.133334,13.900001],"rotation":0,"texture":"#0","tintindex":0}}},{"name":"cube","from":[22.64,1.9159995,4.724],"to":[23.107998,2.384,5.192],"rotation":{"angle":0.0,"axis":"x","origin":[2.5159988,8.0,8.0]},"faces":{"down":{"uv":[14.166667,2.0333333,14.066668,2.1333334],"rotation":0,"texture":"#0","tintindex":0},"east":{"uv":[14.066668,1.7333333,14.166667,1.8333334],"rotation":0,"texture":"#0","tintindex":0},"north":{"uv":[14.066668,1.6333334,14.166667,1.7333333],"rotation":0,"texture":"#0","tintindex":0},"south":{"uv":[1.8333334,14.066668,1.9333334,14.166667],"rotation":0,"texture":"#0","tintindex":0},"up":{"uv":[2.1333334,14.166667,2.0333333,14.066668],"rotation":0,"texture":"#0","tintindex":0},"west":{"uv":[1.9333334,14.066668,2.0333333,14.166667],"rotation":0,"texture":"#0","tintindex":0}}},{"name":"cube","from":[22.64,1.9159995,10.808001],"to":[23.107998,2.384,11.276],"rotation":{"angle":0.0,"axis":"x","origin":[2.5159988,8.0,8.0]},"faces":{"down":{"uv":[14.166667,4.1000004,14.066668,4.2000003],"rotation":0,"texture":"#0","tintindex":0},"east":{"uv":[14.066668,2.4666667,14.166667,2.5666666],"rotation":0,"texture":"#0","tintindex":0},"north":{"uv":[14.066668,2.3666668,14.166667,2.4666667],"rotation":0,"texture":"#0","tintindex":0},"south":{"uv":[2.5,14.066668,2.6000001,14.166667],"rotation":0,"texture":"#0","tintindex":0},"up":{"uv":[14.166667,2.9,14.066668,2.8],"rotation":0,"texture":"#0","tintindex":0},"west":{"uv":[14.066668,2.7000003,14.166667,2.8],"rotation":0,"texture":"#0","tintindex":0}}},{"name":"cube","from":[17.96,1.9159995,10.808001],"to":[18.427998,2.384,11.276],"rotation":{"angle":0.0,"axis":"x","origin":[2.5159988,8.0,8.0]},"faces":{"down":{"uv":[14.166667,5.1000004,14.066668,5.2000003],"rotation":0,"texture":"#0","tintindex":0},"east":{"uv":[14.066668,4.3,14.166667,4.4],"rotation":0,"texture":"#0","tintindex":0},"north":{"uv":[14.066668,4.2000003,14.166667,4.3],"rotation":0,"texture":"#0","tintindex":0},"south":{"uv":[14.066668,4.4,14.166667,4.5],"rotation":0,"texture":"#0","tintindex":0},"up":{"uv":[14.166667,5.1000004,14.066668,5.0],"rotation":0,"texture":"#0","tintindex":0},"west":{"uv":[14.066668,4.9,14.166667,5.0],"rotation":0,"texture":"#0","tintindex":0}}},{"name":"cube","from":[15.152,1.4479997,4.724],"to":[15.619999,1.9159995,5.192],"rotation":{"angle":0.0,"axis":"x","origin":[2.5159988,8.0,8.0]},"faces":{"down":{"uv":[6.8,14.066668,6.7000003,14.166667],"rotation":0,"texture":"#0","tintindex":0},"east":{"uv":[14.066668,5.3,14.166667,5.4000006],"rotation":0,"texture":"#0","tintindex":0},"north":{"uv":[14.066668,5.2000003,14.166667,5.3],"rotation":0,"texture":"#0","tintindex":0},"south":{"uv":[6.066667,14.066668,6.166667,14.166667],"rotation":0,"texture":"#0","tintindex":0},"up":{"uv":[6.7000003,14.166667,6.6,14.066668],"rotation":0,"texture":"#0","tintindex":0},"west":{"uv":[6.166667,14.066668,6.2666664,14.166667],"rotation":0,"texture":"#0","tintindex":0}}},{"name":"cube","from":[29.191998,1.4479997,4.256],"to":[29.66,1.9159995,4.724],"rotation":{"angle":0.0,"axis":"x","origin":[2.5159988,8.0,8.0]},"faces":{"down":{"uv":[14.166667,7.0,14.066668,7.1],"rotation":0,"texture":"#0","tintindex":0},"east":{"uv":[14.066668,6.8,14.166667,6.9000006],"rotation":0,"texture":"#0","tintindex":0},"north":{"uv":[6.8,14.066668,6.9000006,14.166667],"rotation":0,"texture":"#0","tintindex":0},"south":{"uv":[6.9000006,14.066668,7.0,14.166667],"rotation":0,"texture":"#0","tintindex":0},"up":{"uv":[7.1,14.166667,7.0,14.066668],"rotation":0,"texture":"#0","tintindex":0},"west":{"uv":[14.066668,6.9000006,14.166667,7.0],"rotation":0,"texture":"#0","tintindex":0}}},{"name":"cube","from":[23.107998,1.4479997,4.256],"to":[23.576,1.9159995,4.724],"rotation":{"angle":0.0,"axis":"x","origin":[2.5159988,8.0,8.0]},"faces":{"down":{"uv":[14.166667,7.633333,14.066668,7.7333336],"rotation":0,"texture":"#0","tintindex":0},"east":{"uv":[14.066668,7.1,14.166667,7.2000003],"rotation":0,"texture":"#0","tintindex":0},"north":{"uv":[7.1,14.066668,7.2000003,14.166667],"rotation":0,"texture":"#0","tintindex":0},"south":{"uv":[14.066668,7.2000003,14.166667,7.3],"rotation":0,"texture":"#0","tintindex":0},"up":{"uv":[14.166667,7.633333,14.066668,7.533334],"rotation":0,"texture":"#0","tintindex":0},"west":{"uv":[14.066668,7.3,14.166667,7.4000006],"rotation":0,"texture":"#0","tintindex":0}}},{"name":"cube","from":[15.058399,1.3543996,4.256],"to":[15.7136,2.0095997,4.724],"rotation":{"angle":0.0,"axis":"x","origin":[2.5159988,8.0,8.0]},"faces":{"down":{"uv":[12.566668,14.0,12.433333,14.1],"rotation":0,"texture":"#0","tintindex":0},"east":{"uv":[13.733334,6.0,13.833334,6.133333],"rotation":0,"texture":"#0","tintindex":0},"north":{"uv":[13.966667,8.8,14.1,8.933333],"rotation":0,"texture":"#0","tintindex":0},"south":{"uv":[9.366667,13.966667,9.5,14.1],"rotation":0,"texture":"#0","tintindex":0},"up":{"uv":[12.433333,14.1,12.300001,14.0],"rotation":0,"texture":"#0","tintindex":0},"west":{"uv":[11.966667,14.0,12.066668,14.133334],"rotation":0,"texture":"#0","tintindex":0}}},{"name":"cube","from":[23.014397,1.3543996,3.7879999],"to":[23.669601,2.0095997,4.256],"rotation":{"angle":0.0,"axis":"x","origin":[2.5159988,8.0,8.0]},"faces":{"down":{"uv":[13.033333,14.0,12.900001,14.1],"rotation":0,"texture":"#0","tintindex":0},"east":{"uv":[12.566668,14.0,12.666667,14.133334],"rotation":0,"texture":"#0","tintindex":0},"north":{"uv":[9.5,13.966667,9.633333,14.1],"rotation":0,"texture":"#0","tintindex":0},"south":{"uv":[9.633333,13.966667,9.766666,14.1],"rotation":0,"texture":"#0","tintindex":0},"up":{"uv":[12.900001,14.1,12.766666,14.0],"rotation":0,"texture":"#0","tintindex":0},"west":{"uv":[12.666667,14.0,12.766666,14.133334],"rotation":0,"texture":"#0","tintindex":0}}},{"name":"cube","from":[29.0984,1.3543996,3.7879999],"to":[29.753601,2.0095997,4.256],"rotation":{"angle":0.0,"axis":"x","origin":[2.5159988,8.0,8.0]},"faces":{"down":{"uv":[13.900001,14.0,13.766666,14.1],"rotation":0,"texture":"#0","tintindex":0},"east":{"uv":[13.333334,14.0,13.433333,14.133334],"rotation":0,"texture":"#0","tintindex":0},"north":{"uv":[10.333334,13.966667,10.466667,14.1],"rotation":0,"texture":"#0","tintindex":0},"south":{"uv":[11.066668,13.966667,11.2,14.1],"rotation":0,"texture":"#0","tintindex":0},"up":{"uv":[13.766666,14.1,13.633334,14.0],"rotation":0,"texture":"#0","tintindex":0},"west":{"uv":[13.533333,14.0,13.633334,14.133334],"rotation":0,"texture":"#0","tintindex":0}}},{"name":"cube","from":[29.191998,1.7512727,3.3807507],"to":[29.66,22.811275,3.8487506],"rotation":{"angle":0.0,"axis":"x","origin":[29.425999,12.281273,3.1467505]},"faces":{"down":{"uv":[14.166667,7.8333335,14.066668,7.9333334],"rotation":0,"texture":"#0","tintindex":0},"east":{"uv":[8.200001,11.333334,8.3,15.233334],"rotation":0,"texture":"#0","tintindex":0},"north":{"uv":[8.1,11.333334,8.200001,15.233334],"rotation":0,"texture":"#0","tintindex":0},"south":{"uv":[3.6666667,11.633334,3.766667,15.533333],"rotation":0,"texture":"#0","tintindex":0},"up":{"uv":[14.166667,7.8333335,14.066668,7.7333336],"rotation":0,"texture":"#0","tintindex":0},"west":{"uv":[3.766667,11.633334,3.8666668,15.533333],"rotation":0,"texture":"#0","tintindex":0}}},{"name":"cube","from":[23.107998,1.7512727,3.3807507],"to":[23.576,22.811275,3.8487506],"rotation":{"angle":0.0,"axis":"x","origin":[29.425999,12.281273,3.1467505]},"faces":{"down":{"uv":[14.166667,8.700001,14.066668,8.8],"rotation":0,"texture":"#0","tintindex":0},"east":{"uv":[11.466667,11.800001,11.566668,15.7],"rotation":0,"texture":"#0","tintindex":0},"north":{"uv":[3.8666668,11.633334,3.9666667,15.533333],"rotation":0,"texture":"#0","tintindex":0},"south":{"uv":[11.566668,11.800001,11.666667,15.7],"rotation":0,"texture":"#0","tintindex":0},"up":{"uv":[14.166667,8.700001,14.066668,8.6],"rotation":0,"texture":"#0","tintindex":0},"west":{"uv":[5.166667,11.833334,5.266667,15.733334],"rotation":0,"texture":"#0","tintindex":0}}},{"name":"cube","from":[15.152,1.6576726,3.8019505],"to":[15.619999,22.717674,4.269951],"rotation":{"angle":0.0,"axis":"x","origin":[29.425999,12.281273,3.1467505]},"faces":{"down":{"uv":[14.166667,9.466667,14.066668,9.566668],"rotation":0,"texture":"#0","tintindex":0},"east":{"uv":[5.366667,11.833334,5.4666667,15.733334],"rotation":0,"texture":"#0","tintindex":0},"north":{"uv":[5.266667,11.833334,5.366667,15.733334],"rotation":0,"texture":"#0","tintindex":0},"south":{"uv":[5.4666667,11.833334,5.566667,15.733334],"rotation":0,"texture":"#0","tintindex":0},"up":{"uv":[14.166667,9.466667,14.066668,9.366667],"rotation":0,"texture":"#0","tintindex":0},"west":{"uv":[7.3333335,11.966667,7.4333334,15.866667],"rotation":0,"texture":"#0","tintindex":0}}},{"name":"cube","from":[15.152,1.4479997,10.808001],"to":[15.619999,1.9159995,11.276],"rotation":{"angle":0.0,"axis":"x","origin":[2.5159988,8.0,8.0]},"faces":{"down":{"uv":[6.8,14.166667,6.7000003,14.066668],"rotation":0,"texture":"#0","tintindex":0},"east":{"uv":[14.166667,5.3,14.066668,5.4000006],"rotation":0,"texture":"#0","tintindex":0},"north":{"uv":[6.166667,14.066668,6.066667,14.166667],"rotation":0,"texture":"#0","tintindex":0},"south":{"uv":[14.166667,5.2000003,14.066668,5.3],"rotation":0,"texture":"#0","tintindex":0},"up":{"uv":[6.7000003,14.066668,6.6,14.166667],"rotation":0,"texture":"#0","tintindex":0},"west":{"uv":[6.2666664,14.066668,6.166667,14.166667],"rotation":0,"texture":"#0","tintindex":0}}},{"name":"cube","from":[29.191998,1.4479997,11.276],"to":[29.66,1.9159995,11.744],"rotation":{"angle":0.0,"axis":"x","origin":[2.5159988,8.0,8.0]},"faces":{"down":{"uv":[14.166667,7.1,14.066668,7.0],"rotation":0,"texture":"#0","tintindex":0},"east":{"uv":[14.166667,6.8,14.066668,6.9000006],"rotation":0,"texture":"#0","tintindex":0},"north":{"uv":[7.0,14.066668,6.9000006,14.166667],"rotation":0,"texture":"#0","tintindex":0},"south":{"uv":[6.9000006,14.066668,6.8,14.166667],"rotation":0,"texture":"#0","tintindex":0},"up":{"uv":[7.1,14.066668,7.0,14.166667],"rotation":0,"texture":"#0","tintindex":0},"west":{"uv":[14.166667,6.9000006,14.066668,7.0],"rotation":0,"texture":"#0","tintindex":0}}},{"name":"cube","from":[23.107998,1.4479997,11.276],"to":[23.576,1.9159995,11.744],"rotation":{"angle":0.0,"axis":"x","origin":[2.5159988,8.0,8.0]},"faces":{"down":{"uv":[14.166667,7.7333336,14.066668,7.633333],"rotation":0,"texture":"#0","tintindex":0},"east":{"uv":[14.166667,7.1,14.066668,7.2000003],"rotation":0,"texture":"#0","tintindex":0},"north":{"uv":[14.166667,7.2000003,14.066668,7.3],"rotation":0,"texture":"#0","tintindex":0},"south":{"uv":[7.2000003,14.066668,7.1,14.166667],"rotation":0,"texture":"#0","tintindex":0},"up":{"uv":[14.166667,7.533334,14.066668,7.633333],"rotation":0,"texture":"#0","tintindex":0},"west":{"uv":[14.166667,7.3,14.066668,7.4000006],"rotation":0,"texture":"#0","tintindex":0}}},{"name":"cube","from":[15.058399,1.3543996,11.276],"to":[15.7136,2.0095997,11.744],"rotation":{"angle":0.0,"axis":"x","origin":[2.5159988,8.0,8.0]},"faces":{"down":{"uv":[12.566668,14.1,12.433333,14.0],"rotation":0,"texture":"#0","tintindex":0},"east":{"uv":[13.833334,6.0,13.733334,6.133333],"rotation":0,"texture":"#0","tintindex":0},"north":{"uv":[9.5,13.966667,9.366667,14.1],"rotation":0,"texture":"#0","tintindex":0},"south":{"uv":[14.1,8.8,13.966667,8.933333],"rotation":0,"texture":"#0","tintindex":0},"up":{"uv":[12.433333,14.0,12.300001,14.1],"rotation":0,"texture":"#0","tintindex":0},"west":{"uv":[12.066668,14.0,11.966667,14.133334],"rotation":0,"texture":"#0","tintindex":0}}},{"name":"cube","from":[23.014397,1.3543996,11.744],"to":[23.669601,2.0095997,12.212001],"rotation":{"angle":0.0,"axis":"x","origin":[2.5159988,8.0,8.0]},"faces":{"down":{"uv":[13.033333,14.1,12.900001,14.0],"rotation":0,"texture":"#0","tintindex":0},"east":{"uv":[12.666667,14.0,12.566668,14.133334],"rotation":0,"texture":"#0","tintindex":0},"north":{"uv":[9.766666,13.966667,9.633333,14.1],"rotation":0,"texture":"#0","tintindex":0},"south":{"uv":[9.633333,13.966667,9.5,14.1],"rotation":0,"texture":"#0","tintindex":0},"up":{"uv":[12.900001,14.0,12.766666,14.1],"rotation":0,"texture":"#0","tintindex":0},"west":{"uv":[12.766666,14.0,12.666667,14.133334],"rotation":0,"texture":"#0","tintindex":0}}},{"name":"cube","from":[29.0984,1.3543996,11.744],"to":[29.753601,2.0095997,12.212001],"rotation":{"angle":0.0,"axis":"x","origin":[2.5159988,8.0,8.0]},"faces":{"down":{"uv":[13.900001,14.1,13.766666,14.0],"rotation":0,"texture":"#0","tintindex":0},"east":{"uv":[13.433333,14.0,13.333334,14.133334],"rotation":0,"texture":"#0","tintindex":0},"north":{"uv":[11.2,13.966667,11.066668,14.1],"rotation":0,"texture":"#0","tintindex":0},"south":{"uv":[10.466667,13.966667,10.333334,14.1],"rotation":0,"texture":"#0","tintindex":0},"up":{"uv":[13.766666,14.0,13.633334,14.1],"rotation":0,"texture":"#0","tintindex":0},"west":{"uv":[13.633334,14.0,13.533333,14.133334],"rotation":0,"texture":"#0","tintindex":0}}},{"name":"cube","from":[29.191998,1.7512727,12.15125],"to":[29.66,22.811275,12.619249],"rotation":{"angle":0.0,"axis":"x","origin":[29.425999,12.281273,12.85325]},"faces":{"down":{"uv":[14.166667,7.9333334,14.066668,7.8333335],"rotation":0,"texture":"#0","tintindex":0},"east":{"uv":[8.3,11.333334,8.200001,15.233334],"rotation":0,"texture":"#0","tintindex":0},"north":{"uv":[3.766667,11.633334,3.6666667,15.533333],"rotation":0,"texture":"#0","tintindex":0},"south":{"uv":[8.200001,11.333334,8.1,15.233334],"rotation":0,"texture":"#0","tintindex":0},"up":{"uv":[14.166667,7.7333336,14.066668,7.8333335],"rotation":0,"texture":"#0","tintindex":0},"west":{"uv":[3.8666668,11.633334,3.766667,15.533333],"rotation":0,"texture":"#0","tintindex":0}}},{"name":"cube","from":[23.107998,1.7512727,12.15125],"to":[23.576,22.811275,12.619249],"rotation":{"angle":0.0,"axis":"x","origin":[29.425999,12.281273,12.85325]},"faces":{"down":{"uv":[14.166667,8.8,14.066668,8.700001],"rotation":0,"texture":"#0","tintindex":0},"east":{"uv":[11.566668,11.800001,11.466667,15.7],"rotation":0,"texture":"#0","tintindex":0},"north":{"uv":[11.666667,11.800001,11.566668,15.7],"rotation":0,"texture":"#0","tintindex":0},"south":{"uv":[3.9666667,11.633334,3.8666668,15.533333],"rotation":0,"texture":"#0","tintindex":0},"up":{"uv":[14.166667,8.6,14.066668,8.700001],"rotation":0,"texture":"#0","tintindex":0},"west":{"uv":[5.266667,11.833334,5.166667,15.733334],"rotation":0,"texture":"#0","tintindex":0}}},{"name":"cube","from":[15.152,1.6576726,11.73005],"to":[15.619999,22.717674,12.19805],"rotation":{"angle":0.0,"axis":"x","origin":[29.425999,12.281273,12.85325]},"faces":{"down":{"uv":[14.166667,9.566668,14.066668,9.466667],"rotation":0,"texture":"#0","tintindex":0},"east":{"uv":[5.4666667,11.833334,5.366667,15.733334],"rotation":0,"texture":"#0","tintindex":0},"north":{"uv":[5.566667,11.833334,5.4666667,15.733334],"rotation":0,"texture":"#0","tintindex":0},"south":{"uv":[5.366667,11.833334,5.266667,15.733334],"rotation":0,"texture":"#0","tintindex":0},"up":{"uv":[14.166667,9.366667,14.066668,9.466667],"rotation":0,"texture":"#0","tintindex":0},"west":{"uv":[7.4333334,11.966667,7.3333335,15.866667],"rotation":0,"texture":"#0","tintindex":0}}},{"name":"cube","from":[17.96,-0.42400026,11.3372],"to":[18.427998,1.9159995,11.3372],"rotation":{"angle":0.0,"axis":"x","origin":[2.5159988,8.0,8.0]},"faces":{"down":{"uv":[0.10000001,0.0,0.0,0.0],"rotation":0,"texture":"#0","tintindex":0},"east":{"uv":[0.0,0.0,0.0,0.43333334],"rotation":0,"texture":"#0","tintindex":0},"north":{"uv":[10.466667,13.533333,10.366667,13.966667],"rotation":0,"texture":"#0","tintindex":0},"south":{"uv":[1.0,13.533333,0.90000004,13.966667],"rotation":0,"texture":"#0","tintindex":0},"up":{"uv":[0.10000001,0.0,0.0,0.0],"rotation":0,"texture":"#0","tintindex":0},"west":{"uv":[0.0,0.0,0.0,0.43333334],"rotation":0,"texture":"#0","tintindex":0}}},{"name":"cube","from":[15.152,1.6576726,3.8019505],"to":[15.619999,22.717674,4.269951],"rotation":{"angle":0.0,"axis":"x","origin":[29.425999,12.281273,3.1467505]},"faces":{"down":{"uv":[14.166667,9.466667,14.066668,9.566668],"rotation":0,"texture":"#0","tintindex":0},"east":{"uv":[5.366667,11.833334,5.4666667,15.733334],"rotation":0,"texture":"#0","tintindex":0},"north":{"uv":[5.266667,11.833334,5.366667,15.733334],"rotation":0,"texture":"#0","tintindex":0},"south":{"uv":[5.4666667,11.833334,5.566667,15.733334],"rotation":0,"texture":"#0","tintindex":0},"up":{"uv":[14.166667,9.466667,14.066668,9.366667],"rotation":0,"texture":"#0","tintindex":0},"west":{"uv":[7.3333335,11.966667,7.4333334,15.866667],"rotation":0,"texture":"#0","tintindex":0}}},{"name":"cube","from":[23.107998,1.7512727,3.3807507],"to":[23.576,22.811275,3.8487506],"rotation":{"angle":0.0,"axis":"x","origin":[29.425999,12.281273,3.1467505]},"faces":{"down":{"uv":[14.166667,8.700001,14.066668,8.8],"rotation":0,"texture":"#0","tintindex":0},"east":{"uv":[11.466667,11.800001,11.566668,15.7],"rotation":0,"texture":"#0","tintindex":0},"north":{"uv":[3.8666668,11.633334,3.9666667,15.533333],"rotation":0,"texture":"#0","tintindex":0},"south":{"uv":[11.566668,11.800001,11.666667,15.7],"rotation":0,"texture":"#0","tintindex":0},"up":{"uv":[14.166667,8.700001,14.066668,8.6],"rotation":0,"texture":"#0","tintindex":0},"west":{"uv":[5.166667,11.833334,5.266667,15.733334],"rotation":0,"texture":"#0","tintindex":0}}},{"name":"cube","from":[29.191998,1.7512727,3.3807507],"to":[29.66,22.811275,3.8487506],"rotation":{"angle":0.0,"axis":"x","origin":[29.425999,12.281273,3.1467505]},"faces":{"down":{"uv":[14.166667,7.8333335,14.066668,7.9333334],"rotation":0,"texture":"#0","tintindex":0},"east":{"uv":[8.200001,11.333334,8.3,15.233334],"rotation":0,"texture":"#0","tintindex":0},"north":{"uv":[8.1,11.333334,8.200001,15.233334],"rotation":0,"texture":"#0","tintindex":0},"south":{"uv":[3.6666667,11.633334,3.766667,15.533333],"rotation":0,"texture":"#0","tintindex":0},"up":{"uv":[14.166667,7.8333335,14.066668,7.7333336],"rotation":0,"texture":"#0","tintindex":0},"west":{"uv":[3.766667,11.633334,3.8666668,15.533333],"rotation":0,"texture":"#0","tintindex":0}}},{"name":"cube","from":[23.014397,1.3543996,3.7879999],"to":[23.669601,2.0095997,4.256],"rotation":{"angle":0.0,"axis":"x","origin":[2.5159988,8.0,8.0]},"faces":{"down":{"uv":[13.033333,14.0,12.900001,14.1],"rotation":0,"texture":"#0","tintindex":0},"east":{"uv":[12.566668,14.0,12.666667,14.133334],"rotation":0,"texture":"#0","tintindex":0},"north":{"uv":[9.5,13.966667,9.633333,14.1],"rotation":0,"texture":"#0","tintindex":0},"south":{"uv":[9.633333,13.966667,9.766666,14.1],"rotation":0,"texture":"#0","tintindex":0},"up":{"uv":[12.900001,14.1,12.766666,14.0],"rotation":0,"texture":"#0","tintindex":0},"west":{"uv":[12.666667,14.0,12.766666,14.133334],"rotation":0,"texture":"#0","tintindex":0}}},{"name":"cube","from":[15.058399,1.3543996,4.256],"to":[15.7136,2.0095997,4.724],"rotation":{"angle":0.0,"axis":"x","origin":[2.5159988,8.0,8.0]},"faces":{"down":{"uv":[12.566668,14.0,12.433333,14.1],"rotation":0,"texture":"#0","tintindex":0},"east":{"uv":[13.733334,6.0,13.833334,6.133333],"rotation":0,"texture":"#0","tintindex":0},"north":{"uv":[13.966667,8.8,14.1,8.933333],"rotation":0,"texture":"#0","tintindex":0},"south":{"uv":[9.366667,13.966667,9.5,14.1],"rotation":0,"texture":"#0","tintindex":0},"up":{"uv":[12.433333,14.1,12.300001,14.0],"rotation":0,"texture":"#0","tintindex":0},"west":{"uv":[11.966667,14.0,12.066668,14.133334],"rotation":0,"texture":"#0","tintindex":0}}},{"name":"cube","from":[23.107998,1.4479997,4.256],"to":[23.576,1.9159995,4.724],"rotation":{"angle":0.0,"axis":"x","origin":[2.5159988,8.0,8.0]},"faces":{"down":{"uv":[14.166667,7.633333,14.066668,7.7333336],"rotation":0,"texture":"#0","tintindex":0},"east":{"uv":[14.066668,7.1,14.166667,7.2000003],"rotation":0,"texture":"#0","tintindex":0},"north":{"uv":[7.1,14.066668,7.2000003,14.166667],"rotation":0,"texture":"#0","tintindex":0},"south":{"uv":[14.066668,7.2000003,14.166667,7.3],"rotation":0,"texture":"#0","tintindex":0},"up":{"uv":[14.166667,7.633333,14.066668,7.533334],"rotation":0,"texture":"#0","tintindex":0},"west":{"uv":[14.066668,7.3,14.166667,7.4000006],"rotation":0,"texture":"#0","tintindex":0}}},{"name":"cube","from":[29.191998,1.4479997,4.256],"to":[29.66,1.9159995,4.724],"rotation":{"angle":0.0,"axis":"x","origin":[2.5159988,8.0,8.0]},"faces":{"down":{"uv":[14.166667,7.0,14.066668,7.1],"rotation":0,"texture":"#0","tintindex":0},"east":{"uv":[14.066668,6.8,14.166667,6.9000006],"rotation":0,"texture":"#0","tintindex":0},"north":{"uv":[6.8,14.066668,6.9000006,14.166667],"rotation":0,"texture":"#0","tintindex":0},"south":{"uv":[6.9000006,14.066668,7.0,14.166667],"rotation":0,"texture":"#0","tintindex":0},"up":{"uv":[7.1,14.166667,7.0,14.066668],"rotation":0,"texture":"#0","tintindex":0},"west":{"uv":[14.066668,6.9000006,14.166667,7.0],"rotation":0,"texture":"#0","tintindex":0}}},{"name":"cube","from":[15.152,1.4479997,4.724],"to":[15.619999,1.9159995,5.192],"rotation":{"angle":0.0,"axis":"x","origin":[2.5159988,8.0,8.0]},"faces":{"down":{"uv":[6.8,14.066668,6.7000003,14.166667],"rotation":0,"texture":"#0","tintindex":0},"east":{"uv":[14.066668,5.3,14.166667,5.4000006],"rotation":0,"texture":"#0","tintindex":0},"north":{"uv":[14.066668,5.2000003,14.166667,5.3],"rotation":0,"texture":"#0","tintindex":0},"south":{"uv":[6.066667,14.066668,6.166667,14.166667],"rotation":0,"texture":"#0","tintindex":0},"up":{"uv":[6.7000003,14.166667,6.6,14.066668],"rotation":0,"texture":"#0","tintindex":0},"west":{"uv":[6.166667,14.066668,6.2666664,14.166667],"rotation":0,"texture":"#0","tintindex":0}}},{"name":"cube","from":[29.0984,1.3543996,3.7879999],"to":[29.753601,2.0095997,4.256],"rotation":{"angle":0.0,"axis":"x","origin":[2.5159988,8.0,8.0]},"faces":{"down":{"uv":[13.900001,14.0,13.766666,14.1],"rotation":0,"texture":"#0","tintindex":0},"east":{"uv":[13.333334,14.0,13.433333,14.133334],"rotation":0,"texture":"#0","tintindex":0},"north":{"uv":[10.333334,13.966667,10.466667,14.1],"rotation":0,"texture":"#0","tintindex":0},"south":{"uv":[11.066668,13.966667,11.2,14.1],"rotation":0,"texture":"#0","tintindex":0},"up":{"uv":[13.766666,14.1,13.633334,14.0],"rotation":0,"texture":"#0","tintindex":0},"west":{"uv":[13.533333,14.0,13.633334,14.133334],"rotation":0,"texture":"#0","tintindex":0}}},{"name":"cube","from":[18.427998,1.4479997,4.9687996],"to":[18.896,1.9159995,4.9687996],"rotation":{"angle":0.0,"axis":"x","origin":[2.5159988,8.0,8.0]},"faces":{"down":{"uv":[0.10000001,0.0,0.0,0.0],"rotation":0,"texture":"#0","tintindex":0},"east":{"uv":[0.0,0.0,0.0,0.10000001],"rotation":0,"texture":"#0","tintindex":0},"north":{"uv":[9.866667,14.066668,9.766666,14.166667],"rotation":0,"texture":"#0","tintindex":0},"south":{"uv":[14.166667,9.566668,14.066668,9.666667],"rotation":0,"texture":"#0","tintindex":0},"up":{"uv":[0.10000001,0.0,0.0,0.0],"rotation":0,"texture":"#0","tintindex":0},"west":{"uv":[0.0,0.0,0.0,0.10000001],"rotation":0,"texture":"#0","tintindex":0}}},{"name":"cube","from":[18.896,0.9799998,4.9687996],"to":[19.832,1.4479997,4.9687996],"rotation":{"angle":0.0,"axis":"x","origin":[2.5159988,8.0,8.0]},"faces":{"down":{"uv":[0.16666667,0.0,0.0,0.0],"rotation":0,"texture":"#0","tintindex":0},"east":{"uv":[0.0,0.0,0.0,0.10000001],"rotation":0,"texture":"#0","tintindex":0},"north":{"uv":[8.666667,14.0,8.5,14.1],"rotation":0,"texture":"#0","tintindex":0},"south":{"uv":[14.166667,5.633333,14.0,5.7333336],"rotation":0,"texture":"#0","tintindex":0},"up":{"uv":[0.16666667,0.0,0.0,0.0],"rotation":0,"texture":"#0","tintindex":0},"west":{"uv":[0.0,0.0,0.0,0.10000001],"rotation":0,"texture":"#0","tintindex":0}}},{"name":"cube","from":[19.832,0.5120001,4.9687996],"to":[21.235996,0.9799998,4.9687996],"rotation":{"angle":0.0,"axis":"x","origin":[2.5159988,8.0,8.0]},"faces":{"down":{"uv":[0.26666668,0.0,0.0,0.0],"rotation":0,"texture":"#0","tintindex":0},"east":{"uv":[0.0,0.0,0.0,0.10000001],"rotation":0,"texture":"#0","tintindex":0},"north":{"uv":[5.0,13.933333,4.7333336,14.033333],"rotation":0,"texture":"#0","tintindex":0},"south":{"uv":[14.2,4.7000003,13.933333,4.8],"rotation":0,"texture":"#0","tintindex":0},"up":{"uv":[0.26666668,0.0,0.0,0.0],"rotation":0,"texture":"#0","tintindex":0},"west":{"uv":[0.0,0.0,0.0,0.10000001],"rotation":0,"texture":"#0","tintindex":0}}},{"name":"cube","from":[22.171997,1.4479997,4.9687996],"to":[22.64,1.9159995,4.9687996],"rotation":{"angle":0.0,"axis":"x","origin":[2.5159988,8.0,8.0]},"faces":{"down":{"uv":[0.10000001,0.0,0.0,0.0],"rotation":0,"texture":"#0","tintindex":0},"east":{"uv":[0.0,0.0,0.0,0.10000001],"rotation":0,"texture":"#0","tintindex":0},"north":{"uv":[14.166667,11.566668,14.066668,11.666667],"rotation":0,"texture":"#0","tintindex":0},"south":{"uv":[14.166667,11.466667,14.066668,11.566668],"rotation":0,"texture":"#0","tintindex":0},"up":{"uv":[0.10000001,0.0,0.0,0.0],"rotation":0,"texture":"#0","tintindex":0},"west":{"uv":[0.0,0.0,0.0,0.10000001],"rotation":0,"texture":"#0","tintindex":0}}},{"name":"cube","from":[21.235996,0.9799998,4.9687996],"to":[22.171997,1.4479997,4.9687996],"rotation":{"angle":0.0,"axis":"x","origin":[2.5159988,8.0,8.0]},"faces":{"down":{"uv":[0.16666667,0.0,0.0,0.0],"rotation":0,"texture":"#0","tintindex":0},"east":{"uv":[0.0,0.0,0.0,0.10000001],"rotation":0,"texture":"#0","tintindex":0},"north":{"uv":[14.166667,9.166667,14.0,9.266666],"rotation":0,"texture":"#0","tintindex":0},"south":{"uv":[14.166667,9.066668,14.0,9.166667],"rotation":0,"texture":"#0","tintindex":0},"up":{"uv":[0.16666667,0.0,0.0,0.0],"rotation":0,"texture":"#0","tintindex":0},"west":{"uv":[0.0,0.0,0.0,0.10000001],"rotation":0,"texture":"#0","tintindex":0}}}],"display":{"head":{"translation":[20.473604,-6.4,0.0],"rotation":[0.0,0.0,0.0],"scale":[3.8095,3.8095,3.8095]}}}